Workbook

Sheet README
A1: Whitfield Farms LLC
A2: AcreFlow test account SAM - Profitable with periodic cash-flow squeeze
A3: Fictional business. All names, customers, vendors and lenders are invented; market prices approximate public 2023-2026 data.
A5: Owner: Sam Whitfield ("Farmer Sam"); spouse Megan Whitfield
A6: Location: McPherson County (near Canton), Kansas + Carson County (near Panhandle), Texas
A7: Years Operating: 18
A8: Total Acres: 400
A9: Business Structure: Multi-member LLC taxed as partnership (Sam & Megan)
A10: Primary Activities: KS corn/soybean/wheat rotation (125 ac pivot-irrigated, 160 ac dryland); TX dryland cotton (96 planted ac, fully custom-farmed); custom combining & grain hauling for neighbors
A11: Employees Full Time: 0
A12: Employees Seasonal: 1 seasonal hand/CDL truck driver (May-Nov)
A13: Family Labor: Sam full-time (operates combine on custom jobs); Megan runs grain cart at harvest and keeps books (unpaid)
... A35: Seasonality: Dec prepay; Mar-May inputs/planting; Jun-Jul wheat harvest + custom wheat run; Sep-Nov fall harvest + custom corn/soy; Nov-Dec cotton stripping & ginning; Jan-Oct pool payments.

Sheet Checks
A1: Integrity checks - live formulas tying statements to the ledger and sub-ledgers (all differences should be 0)
A3: Check | B3: Year | C3: Ledger value (formula) | D3: Statement value | E3: Difference
A4: Revenue: ledger (section REV) vs IS_Annual TOTAL | B4: 2023 | C4: =SUMIFS(Transactions!$Q$2:$Q$1092,Transactions!$J$2:$J$1092,"REV",Transactions!$AA$2:$AA$1092,2023,Transactions!$F$2:$F$1092,"Current",Transactions!$C$2:$C$1092,"<="&DATE(2026,9,30)) -> 374668.55 | D4: =IS_Annual_Enterprise!D27 -> 374668.55 | E4: =ROUND(C4-D4,2) -> 0
A5: Cost of production: ledger (section COP) vs IS_Annual TOTAL | B5: 2023 | C5: =SUMIFS(Transactions!$Q$2:$Q$1092,Transactions!$J$2:$J$1092,"COP",Transactions!$AA$2:$AA$1092,2023,Transactions!$F$2:$F$1092,"Current",Transactions!$C$2:$C$1092,"<="&DATE(2026,9,30)) -> 233214.89 | D5: =IS_Annual_Enterprise!F27 -> 233214.89 | E5: =ROUND(C5-D5,2) -> 0
A6: Interest: ledger (section INT) vs IS_Annual TOTAL | B6: 2023 | C6: =SUMIFS(Transactions!$Q$2:$Q$1092,Transactions!$J$2:$J$1092,"INT",Transactions!$AA$2:$AA$1092,2023,Transactions!$F$2:$F$1092,"Current",Transactions!$C$2:$C$1092,"<="&DATE(2026,9,30)) -> 41451.19 | D6: =IS_Annual_Enterprise!L27 -> 41451.19 | E6: =ROUND(C6-D6,2) -> 0
A7: Revenue: ledger (section REV) vs IS_Annual TOTAL | B7: 2024 | C7: =SUMIFS(Transactions!$Q$2:$Q$1092,Transactions!$J$2:$J$1092,"REV",Transactions!$AA$2:$AA$1092,2024,Transactions!$F$2:$F$1092,"Current",Transactions!$C$2:$C$1092,"<="&DATE(2026,9,30)) -> 429071.06 | D7: =IS_Annual_Enterprise!D28 -> 429071.06 | E7: =ROUND(C7-D7,2) -> 0
A8: Cost of production: ledger (section COP) vs IS_Annual TOTAL | B8: 2024 | C8: =SUMIFS(Transactions!$Q$2:$Q$1092,Transactions!$J$2:$J$1092,"COP",Transactions!$AA$2:$AA$1092,2024,Transactions!$F$2:$F$1092,"Current",Transactions!$C$2:$C$1092,"<="&DATE(2026,9,30)) -> 194297.69 | D8: =IS_Annual_Enterprise!F28 -> 194297.69 | E8: =ROUND(C8-D8,2) -> 0
A9: Interest: ledger (section INT) vs IS_Annual TOTAL | B9: 2024 | C9: =SUMIFS(Transactions!$Q$2:$Q$1092,Transactions!$J$2:$J$1092,"INT",Transactions!$AA$2:$AA$1092,2024,Transactions!$F$2:$F$1092,"Current",Transactions!$C$2:$C$1092,"<="&DATE(2026,9,30)) -> 41973.14 | D9: =IS_Annual_Enterprise!L28 -> 41973.14 | E9: =ROUND(C9-D9,2) -> 0
A10: Revenue: ledger (section REV) vs IS_Annual TOTAL | B10: 2025 | C10: =SUMIFS(Transactions!$Q$2:$Q$1092,Transactions!$J$2:$J$1092,"REV",Transactions!$AA$2:$AA$1092,2025,Transactions!$F$2:$F$1092,"Current",Transactions!$C$2:$C$1092,"<="&DATE(2026,9,30)) -> 443445.2 | D10: =IS_Annual_Enterprise!D29 -> 443445.2 | E10: =ROUND(C10-D10,2) -> 0
A11: Cost of production: ledger (section COP) vs IS_Annual TOTAL | B11: 2025 | C11: =SUMIFS(Transactions!$Q$2:$Q$1092,Transactions!$J$2:$J$1092,"COP",Transactions!$AA$2:$AA$1092,2025,Transactions!$F$2:$F$1092,"Current",Transactions!$C$2:$C$1092,"<="&DATE(2026,9,30)) -> 247894.11 | D11: =IS_Annual_Enterprise!F29 -> 247894.11 | E11: =ROUND(C11-D11,2) -> 0
A12: Interest: ledger (section INT) vs IS_Annual TOTAL | B12: 2025 | C12: =SUMIFS(Transactions!$Q$2:$Q$1092,Transactions!$J$2:$J$1092,"INT",Transactions!$AA$2:$AA$1092,2025,Transactions!$F$2:$F$1092,"Current",Transactions!$C$2:$C$1092,"<="&DATE(2026,9,30)) -> 44597.46 | D12: =IS_Annual_Enterprise!L29 -> 44597.46 | E12: =ROUND(C12-D12,2) -> 0
A13: Revenue: ledger (section REV) vs IS_Annual TOTAL | B13: 2026 | C13: =SUMIFS(Transactions!$Q$2:$Q$1092,Transactions!$J$2:$J$1092,"REV",Transactions!$AA$2:$AA$1092,2026,Transactions!$F$2:$F$1092,"Current",Transactions!$C$2:$C$1092,"<="&DATE(2026,9,30)) -> 234120.21 | D13: =IS_Annual_Enterprise!D30 -> 234120.21 | E13: =ROUND(C13-D13,2) -> 0
A14: Cost of production: ledger (section COP) vs IS_Annual TOTAL | B14: 2026 | C14: =SUMIFS(Transactions!$Q$2:$Q$1092,Transactions!$J$2:$J$1092,"COP",Transactions!$AA$2:$AA$1092,2026,Transactions!$F$2:$F$1092,"Current",Transactions!$C$2:$C$1092,"<="&DATE(2026,9,30)) -> 161688.09 | D14: =IS_Annual_Enterprise!F30 -> 161688.09 | E14: =ROUND(C14-D14,2) -> 0
A15: Interest: ledger (section INT) vs IS_Annual TOTAL | B15: 2026 | C15: =SUMIFS(Transactions!$Q$2:$Q$1092,Transactions!$J$2:$J$1092,"INT",Transactions!$AA$2:$AA$1092,2026,Transactions!$F$2:$F$1092,"Current",Transactions!$C$2:$C$1092,"<="&DATE(2026,9,30)) -> 34762.64 | D15: =IS_Annual_Enterprise!L30 -> 34762.64 | E15: =ROUND(C15-D15,2) -> 0
A16: Balance sheet: max |assets - liabilities - equity| across all month-ends | C16: =MAX(BS_Monthly!B38:AU38) -> 0 | D16: =MIN(BS_Monthly!B38:AU38) -> 0 | E16: =ROUND(MAX(ABS(C16),ABS(D16)),2) -> 0
A17: Cash: BS_Monthly cash at 9/30/2026 vs CF_Monthly ending cash | C17: =BS_Monthly!AU4 -> 28343.6 | D17: =CF_Monthly!AJ47 -> 28343.6 | E17: =ROUND(C17-D17,2) -> 0
A18: Cash: opening cash + SUM(ledger cash_effect) vs BS cash at 9/30/2026 | C18: =BS_Monthly!B4+SUMIFS(Transactions!$R$2:$R$1092,Transactions!$D$2:$D$1092,">="&DATE(2023,1,1)) -> 28343.6 | D18: =BS_Monthly!AU4 -> 28343.6 | E18: =ROUND(C18-D18,2) -> 0
A19: Accounts receivable: open AR invoices vs BS AR at 9/30/2026 (BS also includes small non-invoiced items) | C19: =SUM(AR_Invoices!J2:J108) -> 17457.23 | D19: =BS_Monthly!AU5 -> 17457.23 | E19: =ROUND(C19-D19,2) -> 0
A20: Debt: Loans principal at 9/30/2026 (term + line) vs BS term debt + operating line | C20: =SUM(Loans!Q2:Q7) -> 834842.73 | D20: =BS_Monthly!AU26+BS_Monthly!AU27+BS_Monthly!AU29+BS_Monthly!AU30+BS_Monthly!AU31+BS_Monthly!AU32 -> 834842.73 | E20: =ROUND(C20-D20,2) -> 0
A22: All checks pass | E22: =IF(SUMPRODUCT(ABS(E4:E20))<1,"PASS","REVIEW") -> PASS

Sheet AI_Insights
A1: AcreFlow financial-intelligence output for this account. Every figure is computed from the tables in this workbook.
A2: insight_id | B2: severity | C2: category | D2: title | E2: finding | F2: recommendation | G2: key_metrics | H2: source_tables
A3: INS-SAM-01 | B3: Positive | C3: Enterprise profitability | D3: Custom harvesting carries the whole business | E3: Custom combining & hauling earned $126,969 in 2025 (after its 85% share of combine depreciation, combine-loan interest, labor and repairs) on $265,688 of revenue - 60% of farm revenue. Total farm operating income was $42,941; without custom work the farm would have lost money in every year 2023-2025. | F3: Protect this enterprise: lock in 2027 client acres early, keep the combine reliable, and price fall corn at the KSU survey's upper range ($49-50/ac). | G3: {"custom_ni_2025": 126968.72, "custom_rev_share_2025": 0.599} | H3: income_statement_annual_by_enterprise
A4: INS-SAM-02 | B4: Warning | C4: Unprofitable crop | D4: Texas cotton has lost money every year, even with emergency aid | E4: Cotton profit per acre (including insurance and government payments, but no land charge): 2023 -$133, 2024 -$96, 2025 -$85; 2026 projects -$47. Break-even pool price ran $0.99-$1.39/lb against pool prices of $0.62-0.73. Custom costs alone ($210+/ac including stripping) consume most of the revenue. | F4: Compare against cash-renting the 100 ac (~$35-45/ac dryland Panhandle) or a crop-share lease; at the 2026 base price ($0.82) cotton only approaches break-even. | G4: {"cotton_profit_per_acre_2023": -133.39, "cotton_profit_per_acre_2024": -96.28, "cotton_profit_per_acre_2025": -85.34, "cotton_profit_per_acre_2026": -46.84} | H4: unit_economics_crops
A5: INS-SAM-03 | B5: Critical | C5: Upcoming cash shortage | D5: Profitable on paper, but the line can't carry next summer | E5: Year-end operating-line balances have ratcheted up: $92,000 (2023), $124,000 (2024), $175,000 (2025). The line reached its $250,000 limit in Aug-2026. The base-case 12-month forecast earns $72,263 of net farm income but still shows a cash shortfall of $44,510 in Jul-2027 with the line maxed - driven by Jan combine + Mar tractor payments, Dec prepaid inputs and slow cotton-pool cash. | F5: Before Jan-2027: term out ~$100k of the line over 5 years, renegotiate combine payment timing to Sep (after wheat custom season), and stop prepaying 2027 inputs in December. | G5: {"line_ye_2023": 92000.0, "line_ye_2025": 175000.0, "forecast_min_cash": -44509.53} | H5: operating_line_monthly; forecast_12_month; cash_forecast_13_week
A6: INS-SAM-04 | B6: Warning | C6: Liquidity & repayment capacity | D6: Working capital is eroding as the line funds term payments | E6: Year-end working capital went -$11,631, -$34,490, -$67,673 (2023-2025). Term debt coverage was FY2023 0.59, FY2024 1.19, FY2025 1.39, TTM Sep-2026 0.85 - below the 1.25 most lenders want in 2023 and TTM. | F6: Treat the TDCR as the binding constraint: no new term debt until it holds above 1.25; ask the lender to re-amortize the remaining combine and tractor balances together over 6 years. | G6: {"wc_FY2023": -11630.71, "wc_FY2024": -34489.54, "wc_FY2025": -67672.96, "tdcr_FY2023": 0.5947, "tdcr_FY2024": 1.1903, "tdcr_FY2025": 1.3923, "tdcr_TTM Sep-2026": 0.847} | H6: financial_ratios
A7: INS-SAM-05 | B7: Watch | C7: Equipment | D7: The combine is wearing out quickly | E7: The 2019 S770 logged about 469 separator hours in 2025 (~88% custom work) and has roughly 3,810 total hours. Combine repairs & pre-season service ran 2023 $20,101, 2024 $25,381, 2025 $38,495, 2026 $25,330 (2026 YTD), including the Aug-2025 rotor-gearbox/feeder-house failure ($18,420). The combine note ($45,115/yr) runs to Jan-2029. | F7: Run the repair-vs-replace model now: trading to a lower-hour S780 (~$520k) only pays if 2027+ custom acres hold above ~4,000. Otherwise budget ~$25k/yr in repairs and a backup-combine arrangement. | G7: {"combine_repairs": {"2023": 20101.0, "2024": 25380.56, "2025": 38495.04, "2026": 25330.4}, "separator_hours_2025": 469} | H7: assets; production_records; transactions
A8: INS-SAM-06 | B8: Warning | C8: Receivables | D8: One custom client owes for last fall's corn harvest | E8: Rudd Brothers Partnership owes $12,843 for Nov-2025 corn harvesting, now 354 days outstanding (324 past due; the acre count is disputed). Ostrander Farms pays in 91 days on average against net-30 terms. | F8: Require a 25% deposit or same-week payment from Rudd before fall-2026 work; reserve or write off the balance; add a 1.5%/month late fee to custom invoices. | G8: {"rudd_balance": 12843.25, "ostrander_avg_days": 91} | H8: ar_invoices
A9: INS-SAM-07 | B9: Watch | C9: Customer concentration | D9: 26% of custom revenue comes from one client | E9: Heartland Land & Cattle (CUS-SAM-101) provided $69,145 of $265,688 custom revenue in 2025 (26%). | F9: Sign a multi-year custom agreement with Heartland and add 1-2 smaller clients to diversify. | G9: {"top_client_share": 0.26} | H9: transactions; customers
A10: INS-SAM-08 | B10: Watch | C10: Commodity price risk | D10: Storing corn has cut both ways | E10: Holding 60% of the 2023 pivot corn crop past harvest ($4.65) and selling it in Mar-May 2024 ($4.25-4.30) cost about $5,744 versus harvest-time sale. In 2025 the same strategy gained (harvest $3.85, stored sales $4.20-4.30, average $4.12). Unpriced grain in the bin is a speculative position funded by the operating line. | F10: Store only with a positive carry captured by a forward or HTA contract (as done with the 4,000 bu soybean contract @ $10.45 for Nov-2026). | G10: {"corn23_avg_price": 4.41, "corn25_avg_price": 4.12} | H10: crop_seasons; transactions
A11: INS-SAM-09 | B11: Watch | C11: Input-cost sensitivity | D11: A 20% fertilizer increase would take 6% of 2025 profit | E11: Fertilizer spend was $28,491 in 2025; +20% (anhydrous was already +34% year over year in July 2026) costs $5,698, or 6% of 2025 net farm income ($101,633). | F11: Book fall-2026 anhydrous needs on the dip and use variable-rate N on the dryland corn ground. | G11: {"fertilizer_2025": 28491.2, "impact_plus_20pct": 5698.240000000001} | H11: transactions (5020); scenario_levers
A12: INS-SAM-10 | B12: Watch | C12: Government dependence | D12: Ad-hoc federal aid supplied a large share of recent profit | E12: Government program payments were $1,388 (2024), $25,850 (2025) and $22,429 (2026 YTD, mostly the Farmer Bridge Assistance payment). 2025's $25,850 equals 25% of that year's net farm income. | F12: Build budgets without ad-hoc programs (ECAP/FBA/SDRP); count only enrolled ARC/PLC with OBBBA reference prices. | G12: {"2024": 1388.0, "2025": 25850.04, "2026": 22429.0} | H12: transactions (4210)

Sheet Enterprises
A1: enterprise_id | B1: business_id | C1: enterprise_name | D1: enterprise_type | E1: parent_enterprise_id | F1: notes
A2: ENT-SAM-COT | B2: BIZ-SAM | C2: Texas dryland cotton (Carson Co.) | D2: Crop | F2: 96 planted ac, all field work contracted
A3: ENT-SAM-CORN | B3: BIZ-SAM | C3: Kansas corn | D3: Crop | F3: Pivot-irrigated and dryland
A4: ENT-SAM-SOY | B4: BIZ-SAM | C4: Kansas soybeans | D4: Crop | F4: Pivot-irrigated and dryland
A5: ENT-SAM-WHT | B5: BIZ-SAM | C5: Kansas hard red winter wheat | D5: Crop | F5: Dryland
A6: ENT-SAM-CUS | B6: BIZ-SAM | C6: Custom harvesting & grain hauling | D6: Service | F6: ~3,800-4,800 ac/yr for 8 neighbors
A7: ENT-SAM-OVH | B7: BIZ-SAM | C7: Kansas farm overhead & financing | D7: Overhead | F7: Shop, land loan, operating line, insurance

Sheet Land
A1: parcel_id | B1: business_id | C1: parcel_name | D1: acres | E1: use | F1: tenure | G1: enterprise_id
A2: LP-SAM-P1 | B2: BIZ-SAM | C2: KS-P1 center pivot | D2: 125 | E2: Irrigated corn/soy rotation | F2: Owned
A3: LP-SAM-D1 | B3: BIZ-SAM | C3: KS-D1 dryland | D3: 80 | E3: Wheat / soy / corn rotation | F3: Owned (2019 purchase)
A4: LP-SAM-D2 | B4: BIZ-SAM | C4: KS-D2 dryland | D4: 80 | E4: Wheat / soy / corn rotation | F4: Owned
A5: LP-SAM-HQ | B5: BIZ-SAM | C5: KS homestead, bins, shop, waterways | D5: 15 | E5: Headquarters | F5: Owned | G5: ENT-SAM-OVH
A6: LP-SAM-TX | B6: BIZ-SAM | C6: TX-C1 Carson Co. dryland | D6: 100 | E6: Cotton (96 planted + 4 turnrows) | F6: Owned (inherited 2017) | G6: ENT-SAM-COT

Sheet IS_Monthly
A1: Monthly income statement (accrual). Subtotals are formulas. Source: income_statement_monthly_summary / _detail.
A2: Line item | B2: 44957 | C2: 44985 | D2: 45016 | E2: 45046 | F2: 45077 | G2: 45107 | H2: 45138 | I2: 45169 | J2: 45199 | K2: 45230 | L2: 45260 | M2: 45291 | N2: 45322 | O2: 45351 | P2: 45382 | Q2: 45412 | R2: 45443 | S2: 45473 | T2: 45504 | U2: 45535 | V2: 45565 | W2: 45596 | X2: 45626 | Y2: 45657 | Z2: 45688 | AA2: 45716 | AB2: 45747 | AC2: 45777 | AD2: 45808 | AE2: 45838 | AF2: 45869 | AG2: 45900 | AH2: 45930 | AI2: 45961 | AJ2: 45991 | AK2: 46022 | AL2: 46053 | AM2: 46081 | AN2: 46112 | AO2: 46142 | AP2: 46173 | AQ2: 46203 | AR2: 46234 | AS2: 46265 | AT2: 46295
A3: Revenue | B3: 54644 | C3: 0 | D3: 0 | E3: 0 | F3: 0 | G3: 62275.88 | H3: 16027.87 | I3: 0 | J3: 32814 | K3: 157506.62 | L3: 27408.06 | M3: 23992.12 | N3: 8312.4 | O3: 3609.6 | P3: 38578.56 | Q3: 0 | R3: 27493.25 | S3: 44284.8 | T3: 52272.86 | U3: 0 | V3: 0 | W3: 134296.76 | X3: 85024 | Y3: 35198.83 | Z3: 47443.84 | AA3: 0 | AB3: 0 | AC3: 16691.04 | AD3: 0 | AE3: 51285.4 | AF3: 56376 | AG3: 6215 | AH3: 0 | AI3: 227216.68 | AJ3: 0 | AK3: 38217.24 | AL3: 17371.2 | AM3: 65177.38 | AN3: 11087.6 | AO3: 37073.36 | AP3: 0 | AQ3: 38039.51 | AR3: 33619.16 | AS3: 0 | AT3: 31752
A4: Cost of production | B4: 1344 | C4: 0 | D4: 23073.48 | E4: 62992.87 | F4: 17557.85 | G4: 20088.03 | H4: 25384.42 | I4: 13492.53 | J4: 23033.14 | K4: 22982.73 | L4: 19688.88 | M4: 3576.96 | N4: 1384.32 | O4: 0 | P4: 12626.47 | Q4: 10098.18 | R4: 42314.84 | S4: 22813.85 | T4: 22504.51 | U4: 8059.37 | V4: 19540.7 | W4: 27225.91 | X4: 21529.48 | Y4: 6200.06 | Z4: 1424.64 | AA4: 0 | AB4: 14026.88 | AC4: 48209.05 | AD4: 27808 | AE4: 23974.73 | AF4: 26395.34 | AG4: 27019.32 | AH4: 21109.15 | AI4: 31858.34 | AJ4: 18966.39 | AK4: 7102.27 | AL4: 1464.96 | AM4: 0 | AN4: 14095.04 | AO4: 40132.09 | AP4: 28050.68 | AQ4: 21452.28 | AR4: 21875.63 | AS4: 9704.72 | AT4: 24912.69
A5: Gross profit | B5: =B3-B4 -> 53300 | C5: =C3-C4 -> 0 | D5: =D3-D4 -> -23073.48 | E5: =E3-E4 -> -62992.87 | F5: =F3-F4 -> -17557.85 | G5: =G3-G4 -> 42187.85 | H5: =H3-H4 -> -9356.55 | I5: =I3-I4 -> -13492.53 | ... AT5: =AT3-AT4 -> 6839.31
A6: Gross margin % | B6: =IF(B3=0,0,B5/B3) -> 0.97540444 | C6: =IF(C3=0,0,C5/C3) -> 0 | D6: =IF(D3=0,0,D5/D3) -> 0 | E6: =IF(E3=0,0,E5/E3) -> 0 | F6: =IF(F3=0,0,F5/F3) -> 0 | G6: =IF(G3=0,0,G5/G3) -> 0.67743483 | H6: =IF(H3=0,0,H5/H3) -> -0.58376752 | I6: =IF(I3=0,0,I5/I3) -> 0 | ... AT6: =IF(AT3=0,0,AT5/AT3) -> 0.21539777
A7: Overhead / operating expenses | B7: 13265 | C7: 4387.28 | D7: 791.97 | E7: 1172.94 | F7: 700 | G7: 775.99 | H7: 688.03 | I7: 617.32 | J7: 728.81 | K7: 811.76 | L7: 774.48 | M7: 8122.02 | N7: 14191.72 | O7: 4527.16 | P7: 821.37 | Q7: 1164.19 | R7: 765.78 | S7: 707.41 | T7: 819.6 | U7: 687.89 | V7: 712.39 | W7: 851.23 | X7: 756.79 | Y7: 8388.47 | Z7: 19217.27 | AA7: 4601.49 | AB7: 776.79 | AC7: 1241.86 | AD7: 792.26 | AE7: 817.12 | AF7: 815.05 | AG7: 691.42 | AH7: 756.49 | AI7: 798.5 | AJ7: 739.97 | AK7: 8577.98 | AL7: 20275.3 | AM7: 4649.37 | AN7: 729.5 | AO7: 1199.26 | AP7: 674.3 | AQ7: 743.04 | AR7: 775.15 | AS7: 797.53 | AT7: 787.39
A8: EBITDA | B8: =B5-B7 -> 40035 | C8: =C5-C7 -> -4387.28 | D8: =D5-D7 -> -23865.45 | E8: =E5-E7 -> -64165.81 | F8: =F5-F7 -> -18257.85 | G8: =G5-G7 -> 41411.86 | H8: =H5-H7 -> -10044.58 | I8: =I5-I7 -> -14109.85 | ... AT8: =AT5-AT7 -> 6051.92
A9: Depreciation | B9: 5603.83 | C9: 5603.81 | D9: 5603.84 | E9: 5603.81 | F9: 5603.82 | G9: 5603.8 | H9: 5603.83 | I9: 5603.83 | J9: 5603.81 | K9: 5603.83 | L9: 5603.81 | M9: 5603.83 | N9: 5603.81 | O9: 5603.82 | P9: 5603.81 | Q9: 5603.83 | R9: 5603.82 | S9: 5603.81 | T9: 5603.83 | U9: 6132.99 | V9: 6132.99 | W9: 6132.98 | X9: 6132.99 | Y9: 6132.96 | Z9: 6133 | AA9: 6132.99 | AB9: 6414.23 | AC9: 6414.25 | AD9: 6414.23 | AE9: 6414.24 | AF9: 6414.22 | AG9: 6414.25 | AH9: 6414.22 | AI9: 6414.25 | AJ9: 6414.24 | AK9: 6414.22 | AL9: 6414.25 | AM9: 6414.23 | AN9: 6414.25 | AO9: 6414.22 | AP9: 6414.24 | AQ9: 6414.22 | AR9: 6414.25 | AS9: 6414.25 | AT9: 6414.22
A10: Operating profit | B10: =B8-B9 -> 34431.17 | C10: =C8-C9 -> -9991.09 | D10: =D8-D9 -> -29469.29 | E10: =E8-E9 -> -69769.62 | F10: =F8-F9 -> -23861.67 | G10: =G8-G9 -> 35808.06 | H10: =H8-H9 -> -15648.41 | I10: =I8-I9 -> -19713.68 | ... AT10: =AT8-AT9 -> -362.3
A11: Interest | B11: 13566.98 | C11: 501.3 | D11: 612.53 | E11: 707.77 | F11: 969.3 | G11: 1215.74 | H11: 1503.85 | I11: 1620.09 | J11: 1415.67 | K11: 1457.45 | L11: 965.67 | M11: 16914.84 | N11: 12266.85 | O11: 1125.05 | P11: 1194.91 | Q11: 921.99 | R11: 1039.45 | S11: 1083.51 | T11: 1325.64 | U11: 1628.4 | V11: 1802.54 | W11: 1682.9 | X11: 1299.42 | Y11: 16602.48 | Z11: 11002.53 | AA11: 1177.5 | AB11: 1490.29 | AC11: 1620.91 | AD11: 1698.62 | AE11: 1838.66 | AF11: 2125.37 | AG11: 2176.82 | AH11: 1863.28 | AI11: 1855.23 | AJ11: 1677.28 | AK11: 16070.97 | AL11: 9474.16 | AM11: 1479.91 | AN11: 13781.36 | AO11: 1413.34 | AP11: 1448.96 | AQ11: 1587.71 | AR11: 1863.79 | AS11: 1887.75 | AT11: 1825.66
A12: Gain (loss) on asset sales | B12: 0 | C12: 0 | D12: 0 | E12: 0 | F12: 0 | G12: 0 | H12: 0 | I12: 0 | J12: 0 | K12: 0 | L12: 0 | M12: 0 | N12: 0 | O12: 0 | P12: 0 | Q12: 0 | R12: 0 | S12: 0 | T12: 0 | U12: 0 | V12: 9500 | W12: 0 | X12: 0 | Y12: 0 | Z12: 0 | AA12: 0 | AB12: 8222.22 | AC12: 0 | AD12: 0 | AE12: 0 | AF12: 0 | AG12: 0 | AH12: 0 | AI12: 0 | AJ12: 0 | AK12: 0 | AL12: 0 | AM12: 0 | AN12: 0 | AO12: 0 | AP12: 0 | AQ12: 0 | AR12: 0 | AS12: 0 | AT12: 0
A13: Net income (operating basis) | B13: =B10-B11+B12 -> 20864.19 | C13: =C10-C11+C12 -> -10492.39 | D13: =D10-D11+D12 -> -30081.82 | E13: =E10-E11+E12 -> -70477.39 | F13: =F10-F11+F12 -> -24830.97 | G13: =G10-G11+G12 -> 34592.32 | H13: =H10-H11+H12 -> -17152.26 | I13: =I10-I11+I12 -> -21333.77 | ... AT13: =AT10-AT11+AT12 -> -2187.96
A14: Change in crop/hay/feed/supply inventories | B14: -52768 | C14: 0 | D14: 8960 | E14: 75815.37 | F14: 15166.5 | G14: 4825.45 | H14: 11064.21 | I14: 6302.54 | J14: -21149.28 | K14: -4454.59 | L14: -27277.05 | M14: -1552.5 | N14: -168.18 | O14: -1397.25 | P14: -30352.75 | Q14: 6729.75 | R14: 11229.12 | S14: 4203.2 | T14: 9073.27 | U14: 5443.48 | V14: 153.04 | W14: 4507.51 | X14: -31142.32 | Y14: 198.08 | Z14: -46029.76 | AA14: 0 | AB14: 8066.24 | AC14: 50374.24 | AD14: 25948.94 | AE14: 5773.28 | AF14: 12381.68 | AG14: 5726.72 | AH14: 169.6 | AI14: 24302.07 | AJ14: -29509.8 | AK14: 1488.54 | AL14: -14857.39 | AM14: -41992.68 | AN14: -1253.66 | AO14: -10385.14 | AP14: 32626.83 | AQ14: 476 | AR14: 10394.66 | AS14: 6557.61 | AT14: -21278.48
A15: Change in livestock values | B15: 0 | C15: 0 | D15: 0 | E15: 0 | F15: 0 | G15: 0 | H15: 0 | I15: 0 | J15: 0 | K15: 0 | L15: 0 | M15: 0 | N15: 0 | O15: 0 | P15: 0 | Q15: 0 | R15: 0 | S15: 0 | T15: 0 | U15: 0 | V15: 0 | W15: 0 | X15: 0 | Y15: 0 | Z15: 0 | AA15: 0 | AB15: 0 | AC15: 0 | AD15: 0 | AE15: 0 | AF15: 0 | AG15: 0 | AH15: 0 | AI15: 0 | AJ15: 0 | AK15: 0 | AL15: 0 | AM15: 0 | AN15: 0 | AO15: 0 | AP15: 0 | AQ15: 0 | AR15: 0 | AS15: 0 | AT15: 0
A16: Net farm income (accrual) | B16: =B13+B14+B15 -> -31903.81 | C16: =C13+C14+C15 -> -10492.39 | D16: =D13+D14+D15 -> -21121.82 | E16: =E13+E14+E15 -> 5337.98 | F16: =F13+F14+F15 -> -9664.47 | G16: =G13+G14+G15 -> 39417.77 | H16: =H13+H14+H15 -> -6088.05 | I16: =I13+I14+I15 -> -15031.23 | ... AT16: =AT13+AT14+AT15 -> -23466.44

Sheet IS_Annual_Enterprise
A1: Annual P&L by enterprise (2026 = YTD Sep). Enterprise rows include internal transfers at market; TOTAL excludes them.
A2: business_id | B2: period | C2: enterprise_id | D2: revenue | E2: internal_transfers_net | F2: cost_of_production | G2: gross_profit | H2: gross_margin_pct | I2: overhead | J2: ebitda | K2: depreciation | L2: interest | M2: gain_on_asset_sales | N2: net_income_operating_basis | O2: inventory_change | P2: livestock_value_change | Q2: net_farm_income_accrual
A3: BIZ-SAM | B3: 2023 | C3: ENT-SAM-CORN | D3: 75862.9 | E3: 0 | F3: 104128.88 | G3: -28265.98 | H3: -0.3726 | I3: 0 | J3: -28265.98 | K3: 18546.99 | L3: 0 | M3: 0 | N3: -46812.97 | O3: 69086.25 | P3: 0 | Q3: 22273.28
A4: BIZ-SAM | B4: 2023 | C4: ENT-SAM-COT | D4: 23992.12 | E4: 0 | F4: 36797.76 | G4: -12805.64 | H4: -0.5337 | I4: 431 | J4: -13236.64 | K4: 0 | L4: 0 | M4: 0 | N4: -13236.64 | O4: 0 | P4: 0 | Q4: -13236.64
A5: BIZ-SAM | B5: 2023 | C5: ENT-SAM-CUS | D5: 196886.41 | E5: 0 | F5: 66547.69 | G5: 130338.72 | H5: 0.662 | I5: 4540 | J5: 125798.72 | K5: 21035.26 | L5: 12838 | M5: 0 | N5: 91925.46 | O5: 0 | P5: 0 | Q5: 91925.46
A6: BIZ-SAM | B6: 2023 | C6: ENT-SAM-OVH | D6: 0 | E6: 0 | F6: 12366.52 | G6: -12366.52 | I6: 27864.6 | J6: -40231.12 | K6: 9120.84 | L6: 28613.19 | M6: 0 | N6: -77965.15 | O6: 0 | P6: 0 | Q6: -77965.15
A7: BIZ-SAM | B7: 2023 | C7: ENT-SAM-SOY | D7: 54644 | E7: 0 | F7: 0 | G7: 54644 | H7: 1 | I7: 0 | J7: 54644 | K7: 11623.04 | L7: 0 | M7: 0 | N7: 43020.96 | O7: -54112 | P7: 0 | Q7: -11091.04
A8: BIZ-SAM | B8: 2023 | C8: ENT-SAM-WHT | D8: 23283.12 | E8: 0 | F8: 13374.04 | G8: 9909.08 | H8: 0.4256 | I8: 0 | J8: 9909.08 | K8: 6919.72 | L8: 0 | M8: 0 | N8: 2989.36 | O8: -41.6 | P8: 0 | Q8: 2947.76
A9: BIZ-SAM | B9: 2024 | C9: ENT-SAM-CORN | D9: 74384.21 | E9: 0 | F9: 825.6 | G9: 73558.61 | H9: 0.9889 | I9: 0 | J9: 73558.61 | K9: 18943.87 | L9: 0 | M9: 1900 | N9: 56514.74 | O9: -69086.25 | P9: 0 | Q9: -12571.51
A10: BIZ-SAM | B10: 2024 | C10: ENT-SAM-COT | D10: 40196.43 | E10: 0 | F10: 44441.9 | G10: -4245.47 | H10: -0.1056 | I10: 443.93 | J10: -4689.4 | K10: 0 | L10: 0 | M10: 0 | N10: -4689.4 | O10: 0 | P10: 0 | Q10: -4689.4
A11: BIZ-SAM | B11: 2024 | C11: ENT-SAM-CUS | D11: 235377.78 | E11: 0 | F11: 75515.76 | G11: 159862.02 | H11: 0.6792 | I11: 4790 | J11: 155072.02 | K11: 23019.63 | L11: 12949.2 | M11: 5700 | N11: 124803.19 | O11: 0 | P11: 0 | Q11: 124803.19
A12: BIZ-SAM | B12: 2024 | C12: ENT-SAM-OVH | D12: 0 | E12: 0 | F12: 13424.82 | G12: -13424.82 | I12: 29160.07 | J12: -42584.89 | K12: 9120.83 | L12: 29023.94 | M12: 0 | N12: -80729.66 | O12: 0 | P12: 0 | Q12: -80729.66
A13: BIZ-SAM | B13: 2024 | C13: ENT-SAM-SOY | D13: 66902.4 | E13: 0 | F13: 47503.25 | G13: 19399.15 | H13: 0.29 | I13: 0 | J13: 19399.15 | K13: 11755.33 | L13: 0 | M13: 950 | N13: 8593.82 | O13: 39800 | P13: 0 | Q13: 48393.82
A14: BIZ-SAM | B14: 2024 | C14: ENT-SAM-WHT | D14: 12210.24 | E14: 0 | F14: 12586.36 | G14: -376.12 | H14: -0.0308 | I14: 0 | J14: -376.12 | K14: 7051.98 | L14: 0 | M14: 950 | N14: -6478.1 | O14: 7763.2 | P14: 0 | Q14: 1285.1
A15: BIZ-SAM | B15: 2025 | C15: ENT-SAM-CORN | D15: 39211.28 | E15: 0 | F15: 72982.28 | G15: -33771 | H15: -0.8613 | I15: 0 | J15: -33771 | K15: 20180.09 | L15: 0 | M15: 3700 | N15: -50251.09 | O15: 77891.35 | P15: 0 | Q15: 27640.26
A16: BIZ-SAM | B16: 2025 | C16: ENT-SAM-COT | D16: 49296.28 | E16: 0 | F16: 46409.95 | G16: 2886.33 | H16: 0.0586 | I16: 457.25 | J16: 2429.08 | K16: 0 | L16: 0 | M16: 0 | N16: 2429.08 | O16: 0 | P16: 0 | Q16: 2429.08
A17: BIZ-SAM | B17: 2025 | C17: ENT-SAM-CUS | D17: 265687.6 | E17: 0 | F17: 88849.14 | G17: 176838.46 | H17: 0.6656 | I17: 9005 | J17: 167833.46 | K17: 26967.87 | L17: 13896.87 | M17: 0 | N17: 126968.72 | O17: 0 | P17: 0 | Q17: 126968.72
A18: BIZ-SAM | B18: 2025 | C18: ENT-SAM-OVH | D18: 6215 | E18: 0 | F18: 13253.06 | G18: -7038.06 | H18: -1.1324 | I18: 30363.95 | J18: -37402.01 | K18: 9120.83 | L18: 30700.59 | M18: 0 | N18: -77223.43 | O18: 0 | P18: 0 | Q18: -77223.43
A19: BIZ-SAM | B19: 2025 | C19: ENT-SAM-SOY | D19: 62677.6 | E19: 0 | F19: 12280.8 | G19: 50396.8 | H19: 0.8041 | I19: 0 | J19: 50396.8 | K19: 12784.28 | L19: 0 | M19: 2466.67 | N19: 40079.19 | O19: -22412 | P19: 0 | Q19: 17667.19
A20: BIZ-SAM | B20: 2025 | C20: ENT-SAM-WHT | D20: 20357.44 | E20: 0 | F20: 14118.88 | G20: 6238.56 | H20: 0.3065 | I20: 0 | J20: 6238.56 | K20: 7355.27 | L20: 0 | M20: 2055.55 | N20: 938.84 | O20: 3212.4 | P20: 0 | Q20: 4151.24
A21: BIZ-SAM | B21: 2026 | C21: ENT-SAM-CORN | D21: 117118.74 | E21: 0 | F21: 25355.2 | G21: 91763.54 | H21: 0.7835 | I21: 0 | J21: 91763.54 | K21: 15237.16 | L21: 0 | M21: 0 | N21: 76526.38 | O21: -77887.3 | P21: 0 | Q21: -1360.92
A22: BIZ-SAM | B22: 2026 | C22: ENT-SAM-COT | D22: 11265.6 | E22: 0 | F22: 30800.4 | G22: -19534.8 | H22: -1.734 | I22: 0 | J22: -19534.8 | K22: 0 | L22: 0 | M22: 0 | N22: -19534.8 | O22: 30800.4 | P22: 0 | Q22: 11265.6
A23: BIZ-SAM | B23: 2026 | C23: ENT-SAM-CUS | D23: 60106.99 | E23: 0 | F23: 52364.37 | G23: 7742.62 | H23: 0.1288 | I23: 9545 | J23: -1802.38 | K23: 20401.42 | L23: 10275.41 | M23: 0 | N23: -32479.21 | O23: 0 | P23: 0 | Q23: -32479.21
A24: BIZ-SAM | B24: 2026 | C24: ENT-SAM-OVH | D24: 0 | E24: 0 | F24: 8675.31 | G24: -8675.31 | I24: 21085.84 | J24: -29761.15 | K24: 6840.63 | L24: 24487.23 | M24: 0 | N24: -61089.01 | O24: 0 | P24: 0 | Q24: -61089.01
A25: BIZ-SAM | B25: 2026 | C25: ENT-SAM-SOY | D25: 19841.6 | E25: 0 | F25: 35850.25 | G25: -16008.65 | H25: -0.8068 | I25: 0 | J25: -16008.65 | K25: 9714.76 | L25: 0 | M25: 0 | N25: -25723.41 | O25: 18462.25 | P25: 0 | Q25: -7261.16
A26: BIZ-SAM | B26: 2026 | C26: ENT-SAM-WHT | D26: 25787.28 | E26: 0 | F26: 8642.56 | G26: 17144.72 | H26: 0.6649 | I26: 0 | J26: 17144.72 | K26: 5534.16 | L26: 0 | M26: 0 | N26: 11610.56 | O26: -11087.6 | P26: 0 | Q26: 522.96
A27: BIZ-SAM | B27: 2023 | C27: TOTAL | D27: 374668.55 | E27: 0 | F27: 233214.89 | G27: 141453.66 | H27: 0.3775 | I27: 32835.6 | J27: 108618.06 | K27: 67245.85 | L27: 41451.19 | M27: 0 | N27: -78.98 | O27: 14932.65 | P27: 0 | Q27: 14853.67
A28: BIZ-SAM | B28: 2024 | C28: TOTAL | D28: 429071.06 | E28: 0 | F28: 194297.69 | G28: 234773.37 | H28: 0.5472 | I28: 34394 | J28: 200379.37 | K28: 69891.64 | L28: 41973.14 | M28: 9500 | N28: 98014.59 | O28: -21523.05 | P28: 0 | Q28: 76491.54
A29: BIZ-SAM | B29: 2025 | C29: TOTAL | D29: 443445.2 | E29: 0 | F29: 247894.11 | G29: 195551.09 | H29: 0.441 | I29: 39826.2 | J29: 155724.89 | K29: 76408.34 | L29: 44597.46 | M29: 8222.22 | N29: 42941.31 | O29: 58691.75 | P29: 0 | Q29: 101633.06
A30: BIZ-SAM | B30: 2026 | C30: TOTAL | D30: 234120.21 | E30: 0 | F30: 161688.09 | G30: 72432.12 | H30: 0.3094 | I30: 30630.84 | J30: 41801.28 | K30: 57728.13 | L30: 34762.64 | M30: 0 | N30: -50689.49 | O30: -39712.25 | P30: 0 | Q30: -90401.74

Sheet IS_Detail
A1: business_id | B1: month_end | C1: year | D1: enterprise_id | E1: section | F1: line_item | G1: account_code | H1: account_name | I1: amount
A2: BIZ-SAM | B2: 44957 | C2: 2023 | D2: ENT-SAM-CORN | E2: DEP | F2: Depreciation | G2: 7010 | H2: Depreciation | I2: -1545.59
A3: BIZ-SAM | B3: 44957 | C3: 2023 | D3: ENT-SAM-COT | E3: COP | F3: Contractors & custom hire | G3: 5050 | H3: Custom hire - field operations | I3: -1344
A4: BIZ-SAM | B4: 44957 | C4: 2023 | D4: ENT-SAM-COT | E4: INVCHG | F4: Change in inventories | G4: 7040 | H4: Change in crop, hay, feed & supply inventory | I4: 1344
A5: BIZ-SAM | B5: 44957 | C5: 2023 | D5: ENT-SAM-CUS | E5: OVH | F5: Insurance | G5: 6010 | H5: Insurance - property & liability | I5: -3900
A6: BIZ-SAM | B6: 44957 | C6: 2023 | D6: ENT-SAM-CUS | E6: OVH | F6: Professional & admin | G6: 6090 | H6: Dues, licenses & subscriptions | I6: -640
A7: BIZ-SAM | B7: 44957 | C7: 2023 | D7: ENT-SAM-CUS | E7: DEP | F7: Depreciation | G7: 7010 | H7: Depreciation | I7: -1752.94
A8: BIZ-SAM | B8: 44957 | C8: 2023 | D8: ENT-SAM-CUS | E8: INT | F8: Interest | G8: 7020 | H8: Interest - term debt | I8: -12838
A9: BIZ-SAM | B9: 44957 | C9: 2023 | D9: ENT-SAM-OVH | E9: OVH | F9: Insurance | G9: 6010 | H9: Insurance - property & liability | I9: -7880
A10: BIZ-SAM | B10: 44957 | C10: 2023 | D10: ENT-SAM-OVH | E10: OVH | F10: Utilities | G10: 6030 | H10: Utilities | I10: -395.26
A11: BIZ-SAM | B11: 44957 | C11: 2023 | D11: ENT-SAM-OVH | E11: OVH | F11: Vehicles | G11: 6050 | H11: Vehicle expense | I11: -284.74
A12: BIZ-SAM | B12: 44957 | C12: 2023 | D12: ENT-SAM-OVH | E12: OVH | F12: Professional & admin | G12: 6100 | H12: Office, phone & software | I12: -165
A13: BIZ-SAM | B13: 44957 | C13: 2023 | D13: ENT-SAM-OVH | E13: DEP | F13: Depreciation | G13: 7010 | H13: Depreciation | I13: -760.07
... A969: BIZ-SAM | B969: 46295 | C969: 2026 | D969: ENT-SAM-WHT | E969: DEP | F969: Depreciation | G969: 7010 | H969: Depreciation | I969: -614.92

Sheet BS_Monthly
A1: Month-end balance sheets. Inventories & livestock at market; land at cost. Totals and balance check are formulas (check row must be 0).
A2: Line item | B2: 44926 | C2: 44957 | D2: 44985 | E2: 45016 | F2: 45046 | G2: 45077 | H2: 45107 | I2: 45138 | J2: 45169 | K2: 45199 | L2: 45230 | M2: 45260 | N2: 45291 | O2: 45322 | P2: 45351 | Q2: 45382 | R2: 45412 | S2: 45443 | T2: 45473 | U2: 45504 | V2: 45535 | W2: 45565 | X2: 45596 | Y2: 45626 | Z2: 45657 | AA2: 45688 | AB2: 45716 | AC2: 45747 | AD2: 45777 | AE2: 45808 | AF2: 45838 | AG2: 45869 | AH2: 45900 | AI2: 45930 | AJ2: 45961 | AK2: 45991 | AL2: 46022 | AM2: 46053 | AN2: 46081 | AO2: 46112 | AP2: 46142 | AQ2: 46173 | AR2: 46203 | AS2: 46234 | AT2: 46265 | AU2: 46295
A3: ASSETS
A4: Cash | B4: 38650 | C4: 28757.98 | D4: 17890.12 | E4: 19009.7 | F4: 18481.95 | G4: 8639.32 | H4: 12293.77 | I4: 18396.44 | J4: 28907.7 | K4: 44674.04 | L4: 28239.45 | M4: 34702.95 | N4: 28484.64 | O4: 18585.91 | P4: 31138.38 | Q4: 28721.14 | R4: 13050.08 | S4: 33488.91 | T4: 10260.45 | U4: 19391.76 | V4: 28610.77 | W4: 28529.64 | X4: 28547.5 | Y4: 19624.15 | Z4: 28016.41 | AA4: 28279.41 | AB4: 28610.56 | AC4: 10619.69 | AD4: 30259.37 | AE4: 7827.54 | AF4: 13192.54 | AG4: 21496.6 | AH4: 28524.04 | AI4: 34337.55 | AJ4: 28015.45 | AK4: 30114.1 | AL4: 28482.26 | AM4: 28472.39 | AN4: 28861.47 | AO4: 22303.58 | AP4: 43716.98 | AQ4: 19174.14 | AR4: 14841.7 | AS4: 11353.71 | AT4: 27970.53 | AU4: 28343.6
A5: Accounts receivable | B5: 29956.8 | C5: 13480.56 | D5: 13480.56 | E5: 13480.56 | F5: 8987.04 | G5: 8987.04 | H5: 71262.92 | I5: 70982.55 | J5: 22693.97 | K5: 14536.56 | L5: 102989.32 | M5: 96530.32 | N5: 43671.65 | O5: 33062.65 | P5: 8680.08 | Q5: 8680.08 | R5: 5786.72 | S5: 5786.72 | T5: 50071.52 | U5: 87240.78 | V5: 28206.25 | W5: 2893.36 | X5: 66006.36 | Y5: 124970.21 | Z5: 77813.6 | AA5: 33100.14 | AB5: 13040.34 | AC5: 13040.34 | AD5: 8693.56 | AE5: 8693.56 | AF5: 59978.96 | AG5: 93576.38 | AH5: 28889.78 | AI5: 4346.78 | AJ5: 168244.6 | AK5: 131052.15 | AL5: 78353.79 | AM5: 34142.58 | AN5: 26685.19 | AO5: 26685.19 | AP5: 22071.21 | AQ5: 22071.21 | AR5: 60110.72 | AS5: 77564.22 | AT5: 35358.34 | AU5: 17457.23
A6: Prepaid expenses | B6: 33200 | C6: 33200 | D6: 33200 | E6: 33200 | F6: 0 | G6: 0 | H6: 0 | I6: 0 | J6: 0 | K6: 0 | L6: 0 | M6: 0 | N6: 8968.75 | O6: 8968.75 | P6: 8968.75 | Q6: 8968.75 | R6: 8968.75 | S6: 0 | T6: 0 | U6: 0 | V6: 0 | W6: 0 | X6: 0 | Y6: 0 | Z6: 28150 | AA6: 28150 | AB6: 28150 | AC6: 28150 | AD6: 0 | AE6: 0 | AF6: 0 | AG6: 0 | AH6: 0 | AI6: 0 | AJ6: 0 | AK6: 0 | AL6: 9406.25 | AM6: 9406.25 | AN6: 9406.25 | AO6: 9406.25 | AP6: 0 | AQ6: 0 | AR6: 0 | AS6: 0 | AT6: 0 | AU6: 0
A7: Crop & hay inventory | B7: 54112 | C7: 0 | D7: 0 | E7: 0 | F7: 0 | G7: 0 | H7: 7886.4 | I7: 7519.36 | J7: 7142.4 | K7: 6765.44 | L7: 71415 | M7: 70638.75 | N7: 69086.25 | O7: 67533.75 | P7: 66136.5 | Q7: 27622.63 | R7: 27816.7 | S7: 0 | T7: 8066.56 | U7: 8051.84 | V7: 8066.56 | W7: 8096 | X7: 47068.8 | Y7: 47256.32 | Z7: 47454.4 | AA7: 0 | AB7: 0 | AC7: 0 | AD7: 0 | AE7: 0 | AF7: 10197.2 | AG7: 10218.4 | AH7: 10239.6 | AI7: 10282 | AJ7: 101856.53 | AK7: 104454.41 | AL7: 105942.95 | AM7: 89620.6 | AN7: 47627.92 | AO7: 37250.9 | AP7: 4.28 | AQ7: 4.25 | AR7: 4937.63 | AS7: 4799.32 | AT7: 4669.65 | AU7: 4669.65
A8: Feed inventory | B8: 0 | C8: 0 | D8: 0 | E8: 0 | F8: 0 | G8: 0 | H8: 0 | I8: 0 | J8: 0 | K8: 0 | L8: 0 | M8: 0 | N8: 0 | O8: 0 | P8: 0 | Q8: 0 | R8: 0 | S8: 0 | T8: 0 | U8: 0 | V8: 0 | W8: 0 | X8: 0 | Y8: 0 | Z8: 0 | AA8: 0 | AB8: 0 | AC8: 0 | AD8: 0 | AE8: 0 | AF8: 0 | AG8: 0 | AH8: 0 | AI8: 0 | AJ8: 0 | AK8: 0 | AL8: 0 | AM8: 0 | AN8: 0 | AO8: 0 | AP8: 0 | AQ8: 0 | AR8: 0 | AS8: 0 | AT8: 0 | AU8: 0
A9: Investment in growing crops | B9: 4819.2 | C9: 6163.2 | D9: 6163.2 | E9: 15123.2 | F9: 90938.57 | G9: 106105.07 | H9: 103044.12 | I9: 114475.37 | J9: 121154.87 | K9: 100382.55 | L9: 31278.4 | M9: 4777.6 | N9: 4777.6 | O9: 6161.92 | P9: 6161.92 | Q9: 14323.04 | R9: 20858.72 | S9: 59904.54 | T9: 56041.18 | U9: 65129.17 | V9: 70557.93 | W9: 70681.53 | X9: 36216.24 | Y9: 4886.4 | Z9: 4886.4 | AA9: 6311.04 | AB9: 6311.04 | AC9: 14377.28 | AD9: 64751.52 | AE9: 90700.46 | AF9: 86276.54 | AG9: 98637.02 | AH9: 104342.54 | AI9: 104469.74 | AJ9: 37197.28 | AK9: 5089.6 | AL9: 5089.6 | AM9: 6554.56 | AN9: 6554.56 | AO9: 15677.92 | AP9: 42539.4 | AQ9: 75166.26 | AR9: 70708.88 | AS9: 81241.85 | AT9: 87929.13 | AU9: 66650.65
A10: Supplies, semen & packaged meat | B10: 0 | C10: 0 | D10: 0 | E10: 0 | F10: 0 | G10: 0 | H10: 0 | I10: 0 | J10: 0 | K10: 0 | L10: 0 | M10: 0 | N10: 0 | O10: 0 | P10: 0 | Q10: 0 | R10: 0 | S10: 0 | T10: 0 | U10: 0 | V10: 0 | W10: 0 | X10: 0 | Y10: 0 | Z10: 0 | AA10: 0 | AB10: 0 | AC10: 0 | AD10: 0 | AE10: 0 | AF10: 0 | AG10: 0 | AH10: 0 | AI10: 0 | AJ10: 0 | AK10: 0 | AL10: 0 | AM10: 0 | AN10: 0 | AO10: 0 | AP10: 0 | AQ10: 0 | AR10: 0 | AS10: 0 | AT10: 0 | AU10: 0
A11: Market livestock | B11: 0 | C11: 0 | D11: 0 | E11: 0 | F11: 0 | G11: 0 | H11: 0 | I11: 0 | J11: 0 | K11: 0 | L11: 0 | M11: 0 | N11: 0 | O11: 0 | P11: 0 | Q11: 0 | R11: 0 | S11: 0 | T11: 0 | U11: 0 | V11: 0 | W11: 0 | X11: 0 | Y11: 0 | Z11: 0 | AA11: 0 | AB11: 0 | AC11: 0 | AD11: 0 | AE11: 0 | AF11: 0 | AG11: 0 | AH11: 0 | AI11: 0 | AJ11: 0 | AK11: 0 | AL11: 0 | AM11: 0 | AN11: 0 | AO11: 0 | AP11: 0 | AQ11: 0 | AR11: 0 | AS11: 0 | AT11: 0 | AU11: 0
A12: Total current assets | B12: =B4+B5+B6+B7+B8+B9+B10+B11 -> 160738 | C12: =C4+C5+C6+C7+C8+C9+C10+C11 -> 81601.74 | D12: =D4+D5+D6+D7+D8+D9+D10+D11 -> 70733.88 | E12: =E4+E5+E6+E7+E8+E9+E10+E11 -> 80813.46 | F12: =F4+F5+F6+F7+F8+F9+F10+F11 -> 118407.56 | G12: =G4+G5+G6+G7+G8+G9+G10+G11 -> 123731.43 | H12: =H4+H5+H6+H7+H8+H9+H10+H11 -> 194487.21 | I12: =I4+I5+I6+I7+I8+I9+I10+I11 -> 211373.72 | ... AU12: =AU4+AU5+AU6+AU7+AU8+AU9+AU10+AU11 -> 117121.13
A13: Breeding livestock (market) | B13: 0 | C13: 0 | D13: 0 | E13: 0 | F13: 0 | G13: 0 | H13: 0 | I13: 0 | J13: 0 | K13: 0 | L13: 0 | M13: 0 | N13: 0 | O13: 0 | P13: 0 | Q13: 0 | R13: 0 | S13: 0 | T13: 0 | U13: 0 | V13: 0 | W13: 0 | X13: 0 | Y13: 0 | Z13: 0 | AA13: 0 | AB13: 0 | AC13: 0 | AD13: 0 | AE13: 0 | AF13: 0 | AG13: 0 | AH13: 0 | AI13: 0 | AJ13: 0 | AK13: 0 | AL13: 0 | AM13: 0 | AN13: 0 | AO13: 0 | AP13: 0 | AQ13: 0 | AR13: 0 | AS13: 0 | AT13: 0 | AU13: 0
A14: Machinery & equipment (net) | B14: 614260.28 | C14: 610356.52 | D14: 606452.78 | E14: 602549.02 | F14: 598645.28 | G14: 594741.52 | H14: 590837.79 | I14: 586934.03 | J14: 583030.28 | K14: 579126.53 | L14: 575222.77 | M14: 571319.03 | N14: 567415.27 | O14: 563511.53 | P14: 559607.77 | Q14: 555704.04 | R14: 551800.28 | S14: 547896.53 | T14: 543992.78 | U14: 540089.02 | V14: 536185.28 | W14: 532281.52 | X14: 528377.78 | Y14: 524474.02 | Z14: 520570.29 | AA14: 516666.53 | AB14: 512762.78 | AC14: 727300 | AD14: 723114.99 | AE14: 718930 | AF14: 714744.99 | AG14: 710560.01 | AH14: 706375 | AI14: 702190.01 | AJ14: 698005 | AK14: 693820 | AL14: 689635 | AM14: 685449.99 | AN14: 681265 | AO14: 677079.99 | AP14: 672895.01 | AQ14: 668710 | AR14: 664525.01 | AS14: 660340 | AT14: 656155 | AU14: 651970
A15: Vehicles (net) | B15: 58286.46 | C15: 57854.17 | D15: 57421.88 | E15: 56989.58 | F15: 56557.29 | G15: 56125 | H15: 55692.71 | I15: 55260.42 | J15: 54828.12 | K15: 54395.83 | L15: 53963.54 | M15: 53531.25 | N15: 53098.96 | O15: 52666.67 | P15: 52234.38 | Q15: 51802.08 | R15: 51369.79 | S15: 50937.5 | T15: 50505.21 | U15: 50072.92 | V15: 147611.45 | W15: 141650 | X15: 140688.54 | Y15: 139727.08 | Z15: 138765.63 | AA15: 137804.17 | AB15: 136842.71 | AC15: 135881.25 | AD15: 134919.79 | AE15: 133958.33 | AF15: 132996.88 | AG15: 132035.42 | AH15: 131073.95 | AI15: 130112.5 | AJ15: 129151.04 | AK15: 128189.58 | AL15: 127228.13 | AM15: 126266.67 | AN15: 125305.21 | AO15: 124343.75 | AP15: 123382.29 | AQ15: 122420.83 | AR15: 121459.38 | AS15: 120497.92 | AT15: 119536.45 | AU15: 118575
A16: Buildings & improvements (net) | B16: 272085.56 | C16: 270817.78 | D16: 269550 | E16: 268282.22 | F16: 267014.44 | G16: 265746.67 | H16: 264478.89 | I16: 263211.11 | J16: 261943.33 | K16: 260675.56 | L16: 259407.78 | M16: 258140 | N16: 256872.22 | O16: 255604.44 | P16: 254336.67 | Q16: 253068.89 | R16: 251801.11 | S16: 250533.33 | T16: 249265.56 | U16: 247997.78 | V16: 246730 | W16: 245462.22 | X16: 244194.44 | Y16: 242926.67 | Z16: 241658.89 | AA16: 240391.11 | AB16: 239123.33 | AC16: 237855.56 | AD16: 236587.78 | AE16: 235320 | AF16: 234052.22 | AG16: 232784.44 | AH16: 231516.67 | AI16: 230248.89 | AJ16: 228981.11 | AK16: 227713.33 | AL16: 226445.56 | AM16: 225177.78 | AN16: 223910 | AO16: 222642.22 | AP16: 221374.44 | AQ16: 220106.67 | AR16: 218838.89 | AS16: 217571.11 | AT16: 216303.33 | AU16: 215035.56
A17: Land (cost basis) | B17: 925000 | C17: 925000 | D17: 925000 | E17: 925000 | F17: 925000 | G17: 925000 | H17: 925000 | I17: 925000 | J17: 925000 | K17: 925000 | L17: 925000 | M17: 925000 | N17: 925000 | O17: 925000 | P17: 925000 | Q17: 925000 | R17: 925000 | S17: 925000 | T17: 925000 | U17: 925000 | V17: 925000 | W17: 925000 | X17: 925000 | Y17: 925000 | Z17: 925000 | AA17: 925000 | AB17: 925000 | AC17: 925000 | AD17: 925000 | AE17: 925000 | AF17: 925000 | AG17: 925000 | AH17: 925000 | AI17: 925000 | AJ17: 925000 | AK17: 925000 | AL17: 925000 | AM17: 925000 | AN17: 925000 | AO17: 925000 | AP17: 925000 | AQ17: 925000 | AR17: 925000 | AS17: 925000 | AT17: 925000 | AU17: 925000
A18: Total non-current assets | B18: =B13+B14+B15+B16+B17 -> 1869632.3 | C18: =C13+C14+C15+C16+C17 -> 1864028.5 | D18: =D13+D14+D15+D16+D17 -> 1858424.7 | E18: =E13+E14+E15+E16+E17 -> 1852820.8 | F18: =F13+F14+F15+F16+F17 -> 1847217 | G18: =G13+G14+G15+G16+G17 -> 1841613.2 | H18: =H13+H14+H15+H16+H17 -> 1836009.4 | I18: =I13+I14+I15+I16+I17 -> 1830405.6 | ... AU18: =AU13+AU14+AU15+AU16+AU17 -> 1910580.6
A19: TOTAL ASSETS | B19: =B12+B18 -> 2030370.3 | C19: =C12+C18 -> 1945630.2 | D19: =D12+D18 -> 1929158.5 | E19: =E12+E18 -> 1933634.3 | F19: =F12+F18 -> 1965624.6 | G19: =G12+G18 -> 1965344.6 | H19: =H12+H18 -> 2030496.6 | I19: =I12+I18 -> 2041779.3 | ... AU19: =AU12+AU18 -> 2027701.7
A20: LIABILITIES
A21: Accounts payable | B21: 3184.55 | C21: 1344 | D21: 0 | E21: 16373.48 | F21: 37355.37 | G21: 15166.5 | H21: 14650.69 | I21: 20725.5 | J21: 9537.5 | K21: 13168.28 | L21: 18454.48 | M21: 17473.33 | N21: 10296.96 | O21: 4961.28 | P21: 0 | Q21: 8476.47 | R21: 10098.18 | S21: 30684.57 | T21: 22247.96 | U21: 18816.24 | V21: 3995 | W21: 11746.8 | X21: 22324.18 | Y21: 17260.42 | Z21: 13112.06 | AA21: 7624.7 | AB21: 0 | AC21: 8126.88 | AD21: 20059.05 | AE21: 24988.94 | AF21: 29527.44 | AG21: 25064.01 | AH21: 22650 | AI21: 31077.6 | AJ21: 24405.3 | AK21: 17662.86 | AL21: 14302.27 | AM21: 8567.23 | AN21: 0 | AO21: 9145.04 | AP21: 30725.84 | AQ21: 31768.61 | AR21: 21712.86 | AS21: 17601.92 | AT21: 5170 | AU21: 15921.44
A22: Credit cards | B22: 0 | C22: 449.74 | D22: 554.28 | E22: 520.59 | F22: 935.65 | G22: 452.8 | H22: 2355.57 | I22: 420.28 | J22: 381.25 | K22: 4198.23 | L22: 557.46 | M22: 512.89 | N22: 450.11 | O22: 464.67 | P22: 507.66 | Q22: 549.84 | R22: 922.27 | S22: 484.23 | T22: 2451.19 | U22: 584.32 | V22: 435.56 | W22: 4445.64 | X22: 557.56 | Y22: 479.89 | Z22: 440.89 | AA22: 466.07 | AB22: 478.01 | AC22: 501.8 | AD22: 951.62 | AE22: 538.52 | AF22: 2705.92 | AG22: 522.06 | AH22: 414.23 | AI22: 4807.47 | AJ22: 497.5 | AK22: 462.26 | AL22: 454.24 | AM22: 484.05 | AN22: 403.75 | AO22: 482.54 | AP22: 957.95 | AQ22: 439.1 | AR22: 2790.93 | AS22: 509.31 | AT22: 534.06 | AU22: 5127.08
A23: Accrued property tax | B23: 3821.32 | C23: 3390.12 | D23: 3390.12 | E23: 3390.12 | F23: 3390.12 | G23: 0 | H23: 0 | I23: 0 | J23: 0 | K23: 0 | L23: 0 | M23: 0 | N23: 3821 | O23: 3390 | P23: 3390 | Q23: 3390 | R23: 3390 | S23: 0 | T23: 0 | U23: 0 | V23: 0 | W23: 0 | X23: 0 | Y23: 0 | Z23: 3952.58 | AA23: 3508.65 | AB23: 3508.65 | AC23: 3508.65 | AD23: 3508.65 | AE23: 0 | AF23: 0 | AG23: 0 | AH23: 0 | AI23: 0 | AJ23: 0 | AK23: 0 | AL23: 4088.7 | AM23: 3631.45 | AN23: 3631.45 | AO23: 3631.45 | AP23: 3631.45 | AQ23: 0 | AR23: 0 | AS23: 0 | AT23: 0 | AU23: 0
A24: Accrued payroll tax | B24: 0 | C24: 0 | D24: 0 | E24: 0 | F24: 0 | G24: 193.42 | H24: 290.16 | I24: 273.29 | J24: 207.31 | K24: 488.92 | L24: 366.26 | M24: 179.2 | N24: 0 | O24: 0 | P24: 0 | Q24: 0 | R24: 0 | S24: 215.27 | T24: 440.48 | U24: 298.31 | V24: 212.77 | W24: 296.86 | X24: 396.46 | Y24: 345.29 | Z24: 0 | AA24: 0 | AB24: 0 | AC24: 0 | AD24: 0 | AE24: 228.01 | AF24: 397.58 | AG24: 296.98 | AH24: 234.05 | AI24: 325.5 | AJ24: 602.82 | AK24: 105.43 | AL24: 0 | AM24: 0 | AN24: 0 | AO24: 0 | AP24: 0 | AQ24: 241.85 | AR24: 410.84 | AS24: 345.66 | AT24: 244.06 | AU24: 344.6
A25: Customer deposits (deferred revenue) | B25: 0 | C25: 0 | D25: 0 | E25: 0 | F25: 0 | G25: 0 | H25: 0 | I25: 0 | J25: 0 | K25: 0 | L25: 0 | M25: 0 | N25: 0 | O25: 0 | P25: 0 | Q25: 0 | R25: 0 | S25: 0 | T25: 0 | U25: 0 | V25: 0 | W25: 0 | X25: 0 | Y25: 0 | Z25: 0 | AA25: 0 | AB25: 0 | AC25: 0 | AD25: 0 | AE25: 0 | AF25: 0 | AG25: 0 | AH25: 0 | AI25: 0 | AJ25: 0 | AK25: 0 | AL25: 0 | AM25: 0 | AN25: 0 | AO25: 0 | AP25: 0 | AQ25: 0 | AR25: 0 | AS25: 0 | AT25: 0 | AU25: 0
A26: Operating line | B26: 70000 | C26: 59000 | D26: 59000 | E26: 73000 | F26: 86000 | G26: 126000 | H26: 158000 | I26: 176000 | J26: 170000 | K26: 170000 | L26: 113000 | M26: 113000 | N26: 92000 | O26: 139000 | P26: 139000 | Q26: 109000 | R26: 109000 | S26: 125000 | T26: 141000 | U26: 170000 | V26: 177000 | W26: 157000 | X26: 115000 | Y26: 115000 | Z26: 124000 | AA26: 113000 | AB26: 113000 | AC26: 155000 | AD26: 172000 | AE26: 185000 | AF26: 218000 | AG26: 246000 | AH26: 221000 | AI26: 221000 | AJ26: 203000 | AK26: 203000 | AL26: 175000 | AM26: 197000 | AN26: 146000 | AO26: 177000 | AP26: 177000 | AQ26: 192000 | AR26: 228000 | AS26: 245000 | AT26: 250000 | AU26: 221000
A27: Current portion of term debt | B27: 57410.83 | C27: 59021.68 | D27: 59051.06 | E27: 59080.53 | F27: 59110.09 | G27: 59139.75 | H27: 59169.51 | I27: 59199.37 | J27: 59229.32 | K27: 59259.37 | L27: 59289.52 | M27: 59319.76 | N27: 60051.53 | O27: 61741.03 | P27: 61771.57 | Q27: 61802.21 | R27: 61832.95 | S27: 61863.79 | T27: 61894.73 | U27: 61925.77 | V27: 78054.73 | W27: 78183.23 | X27: 78312.41 | Y27: 78442.29 | Z27: 79304.82 | AA27: 81176.45 | AB27: 81308.43 | AC27: 104224.27 | AD27: 104357.67 | AE27: 104491.79 | AF27: 104626.31 | AG27: 103916.78 | AH27: 103205.24 | AI27: 102491.68 | AJ27: 101776.09 | AK27: 101058.47 | AL27: 101102.6 | AM27: 102206.54 | AN27: 101482.8 | AO27: 102463.46 | AP27: 101735.61 | AQ27: 101005.7 | AR27: 100274.04 | AS27: 100385.08 | AT27: 100496.79 | AU27: 100609.17
A28: Total current liabilities | B28: =B21+B22+B23+B24+B25+B26+B27 -> 134416.7 | C28: =C21+C22+C23+C24+C25+C26+C27 -> 123205.54 | D28: =D21+D22+D23+D24+D25+D26+D27 -> 121995.46 | E28: =E21+E22+E23+E24+E25+E26+E27 -> 152364.72 | F28: =F21+F22+F23+F24+F25+F26+F27 -> 186791.23 | G28: =G21+G22+G23+G24+G25+G26+G27 -> 200952.47 | H28: =H21+H22+H23+H24+H25+H26+H27 -> 234465.93 | I28: =I21+I22+I23+I24+I25+I26+I27 -> 256618.44 | ... AU28: =AU21+AU22+AU23+AU24+AU25+AU26+AU27 -> 343002.29
A29: Land loans (non-current) | B29: 330323.13 | C29: 327715.84 | D29: 327658.15 | E29: 327600.14 | F29: 327541.8 | G29: 327483.14 | H29: 327424.13 | I29: 327364.79 | J29: 327305.12 | K29: 327245.1 | L29: 327184.74 | M29: 327124.04 | N29: 311191.39 | O29: 308035.18 | P29: 307964.95 | Q29: 307894.3 | R29: 307823.23 | S29: 307751.73 | T29: 307679.79 | U29: 307607.43 | V29: 303085.22 | W29: 302873.13 | X29: 302658.53 | Y29: 302441.39 | Z29: 285968.57 | AA29: 282037.92 | AB29: 281784.18 | AC29: 281988.98 | AD29: 281789.13 | AE29: 281587.06 | AF29: 281382.89 | AG29: 281562.03 | AH29: 281742.47 | AI29: 281924.22 | AJ29: 282107.3 | AK29: 282291.73 | AL29: 265940.94 | AM29: 262659.01 | AN29: 262835.43 | AO29: 260398.6 | AP29: 260574.72 | AQ29: 260752.24 | AR29: 260931.04 | AS29: 260753.69 | AT29: 260574.39 | AU29: 260393.14
A30: Equipment loans (non-current) | B30: 239108.19 | C30: 207996.68 | D30: 207960.06 | E30: 207923.24 | F30: 207886.22 | G30: 207848.98 | H30: 207811.53 | I30: 207773.87 | J30: 207735.99 | K30: 207697.9 | L30: 207659.59 | M30: 207621.07 | N30: 206718.24 | O30: 174462.89 | P30: 174423.11 | Q30: 174383.1 | R30: 174342.84 | S30: 174302.35 | T30: 174261.61 | U30: 174220.62 | V30: 234761.45 | W30: 233460.82 | X30: 232153 | Y30: 230837.95 | Z30: 228279.82 | AA30: 193554.7 | AB30: 192235.3 | AC30: 332646.59 | AD30: 331251.67 | AE30: 329848.8 | AF30: 328438.1 | AG30: 327467.83 | AH30: 326490.44 | AI30: 325505.87 | AJ30: 324514.06 | AK30: 323514.97 | AL30: 320746.52 | AM30: 284160.95 | AN30: 283138.74 | AO30: 260255.21 | AP30: 259214.02 | AQ30: 258165.21 | AR30: 257108.58 | AS30: 255693.55 | AT30: 254270.85 | AU30: 252840.42
A31: Vehicle loans (non-current) | B31: 30232.97 | C31: 29326.65 | D31: 28651.75 | E31: 27974.89 | F31: 27296.05 | G31: 26615.23 | H31: 25932.44 | I31: 25247.66 | J31: 24560.89 | K31: 23872.13 | L31: 23181.37 | M31: 22488.61 | N31: 21703.13 | O31: 20800.07 | P31: 20110.34 | Q31: 19418.66 | R31: 18725.05 | S31: 18029.49 | T31: 17331.97 | U31: 16632.51 | V31: 15700.6 | W31: 15000.46 | X31: 14298.94 | Y31: 13596.04 | Z31: 12822.36 | AA31: 11962.75 | AB31: 11267.01 | AC31: 10587.5 | AD31: 9890.56 | AE31: 9192.28 | AF31: 8492.67 | AG31: 7802.45 | AH31: 7109.12 | AI31: 6412.65 | AJ31: 5713.02 | AK31: 5010.21 | AL31: 4280.69 | AM31: 3528.87 | AN31: 2829.52 | AO31: 2105.8 | AP31: 1407.01 | AQ31: 704.99 | AR31: 0 | AS31: 0 | AT31: 0 | AU31: 0
A32: Other term debt (non-current) | B32: 0 | C32: 0 | D32: 0.01 | E32: 0 | F32: 0 | G32: 0 | H32: 0 | I32: 0 | J32: 0 | K32: 0 | L32: 0 | M32: -0.01 | N32: 0 | O32: 0 | P32: 0 | Q32: 0 | R32: 0 | S32: -0.01 | T32: 0 | U32: -0.01 | V32: 0 | W32: 0 | X32: 0 | Y32: 0 | Z32: 0 | AA32: 0 | AB32: 0 | AC32: 0 | AD32: 0 | AE32: 0 | AF32: 0 | AG32: 0.01 | AH32: 0 | AI32: -0.01 | AJ32: 0 | AK32: 0 | AL32: 0 | AM32: 0 | AN32: 0 | AO32: 0 | AP32: 0 | AQ32: 0 | AR32: 0 | AS32: 0 | AT32: 0 | AU32: 0
A33: TOTAL LIABILITIES | B33: =B28+B29+B30+B31+B32 -> 734080.99 | C33: =C28+C29+C30+C31+C32 -> 688244.71 | D33: =D28+D29+D30+D31+D32 -> 686265.43 | E33: =E28+E29+E30+E31+E32 -> 715862.99 | F33: =F28+F29+F30+F31+F32 -> 749515.3 | G33: =G28+G29+G30+G31+G32 -> 762899.82 | H33: =H28+H29+H30+H31+H32 -> 795634.03 | I33: =I28+I29+I30+I31+I32 -> 817004.76 | ... AU33: =AU28+AU29+AU30+AU31+AU32 -> 856235.85
A34: EQUITY
A35: Owner contributed capital | B35: 529000 | C35: 529000 | D35: 529000 | E35: 529000 | F35: 529000 | G35: 529000 | H35: 529000 | I35: 529000 | J35: 529000 | K35: 529000 | L35: 529000 | M35: 529000 | N35: 529000 | O35: 529000 | P35: 529000 | Q35: 529000 | R35: 529000 | S35: 529000 | T35: 529000 | U35: 529000 | V35: 529000 | W35: 529000 | X35: 529000 | Y35: 529000 | Z35: 529000 | AA35: 529000 | AB35: 529000 | AC35: 529000 | AD35: 529000 | AE35: 529000 | AF35: 529000 | AG35: 529000 | AH35: 529000 | AI35: 529000 | AJ35: 529000 | AK35: 529000 | AL35: 529000 | AM35: 529000 | AN35: 529000 | AO35: 529000 | AP35: 529000 | AQ35: 529000 | AR35: 529000 | AS35: 529000 | AT35: 529000 | AU35: 529000
A36: Retained earnings | B36: 767289.31 | C36: 728385.5 | D36: 713893.11 | E36: 688771.29 | F36: 687109.27 | G36: 673444.8 | H36: 705862.57 | I36: 695774.52 | J36: 676743.29 | K36: 650626.58 | L36: 768822.84 | M36: 737921.01 | N36: 722142.98 | O36: 689240.5 | P36: 676096.82 | Q36: 659976.07 | R36: 641317.63 | S36: 626216.11 | T36: 636895.53 | U36: 663888.08 | V36: 648722.91 | W36: 622587.33 | X36: 721398.58 | Y36: 741461.58 | Z36: 735434.52 | AA36: 693371.16 | AB36: 677259.18 | AC36: 666639.45 | AD36: 670518.66 | AE36: 655554.49 | AF36: 673868.42 | AG36: 702676.12 | AH36: 674116.03 | AI36: 638442.49 | AJ36: 844834.92 | AK36: 783327.24 | AL36: 780667.58 | AM36: 738852.72 | AN36: 745293.91 | AO36: 715907.7 | AP36: 686737.01 | AQ36: 678575.66 | AR36: 680193.92 | AS36: 689078.92 | AT36: 672632.28 | AU36: 642465.84
A37: TOTAL EQUITY | B37: =B35+B36 -> 1296289.3 | C37: =C35+C36 -> 1257385.5 | D37: =D35+D36 -> 1242893.1 | E37: =E35+E36 -> 1217771.3 | F37: =F35+F36 -> 1216109.3 | G37: =G35+G36 -> 1202444.8 | H37: =H35+H36 -> 1234862.6 | I37: =I35+I36 -> 1224774.5 | ... AU37: =AU35+AU36 -> 1171465.8
A38: Balance check (assets - liabilities - equity) | B38: =B19-B33-B37 -> 0 | C38: =C19-C33-C37 -> 0 | D38: =D19-D33-D37 -> 0 | E38: =E19-E33-E37 -> 0 | F38: =F19-F33-F37 -> 0 | G38: =G19-G33-G37 -> 0 | H38: =H19-H33-H37 -> 0 | I38: =I19-I33-I37 -> 0 | ... AU38: =AU19-AU33-AU37 -> 0
A39: memo: cumulative owner distributions since 1/2023 | B39: 0 | C39: 7000 | D39: 11000 | E39: 15000 | F39: 22000 | G39: 26000 | H39: 33000 | I39: 37000 | J39: 41000 | K39: 48000 | L39: 52000 | M39: 56000 | N39: 60000 | O39: 67600 | P39: 71700 | Q39: 75800 | R39: 83400 | S39: 87500 | T39: 95100 | U39: 99200 | V39: 103300 | W39: 110900 | X39: 115000 | Y39: 119100 | Z39: 123200 | AA39: 128900 | AB39: 133100 | AC39: 137300 | AD39: 143000 | AE39: 147200 | AF39: 152900 | AG39: 157100 | AH39: 161300 | AI39: 167000 | AJ39: 171200 | AK39: 175400 | AL39: 179600 | AM39: 186300 | AN39: 190500 | AO39: 194700 | AP39: 201400 | AQ39: 205600 | AR39: 212300 | AS39: 216500 | AT39: 220700 | AU39: 227400
A40: memo: land at market value | B40: 1695000 | C40: 1850000 | D40: 1850000 | E40: 1850000 | F40: 1850000 | G40: 1850000 | H40: 1850000 | I40: 1850000 | J40: 1850000 | K40: 1850000 | L40: 1850000 | M40: 1850000 | N40: 1850000 | O40: 1975000 | P40: 1975000 | Q40: 1975000 | R40: 1975000 | S40: 1975000 | T40: 1975000 | U40: 1975000 | V40: 1975000 | W40: 1975000 | X40: 1975000 | Y40: 1975000 | Z40: 1975000 | AA40: 2052500 | AB40: 2052500 | AC40: 2052500 | AD40: 2052500 | AE40: 2052500 | AF40: 2052500 | AG40: 2052500 | AH40: 2052500 | AI40: 2052500 | AJ40: 2052500 | AK40: 2052500 | AL40: 2052500 | AM40: 2085000 | AN40: 2085000 | AO40: 2085000 | AP40: 2085000 | AQ40: 2085000 | AR40: 2085000 | AS40: 2085000 | AT40: 2085000 | AU40: 2085000
A41: memo: market-value net worth | B41: 2066289.3 | C41: 2182385.5 | D41: 2167893.1 | E41: 2142771.3 | F41: 2141109.3 | G41: 2127444.8 | H41: 2159862.6 | I41: 2149774.5 | J41: 2130743.3 | K41: 2104626.6 | L41: 2222822.8 | M41: 2191921 | N41: 2176143 | O41: 2268240.5 | P41: 2255096.8 | Q41: 2238976.1 | R41: 2220317.6 | S41: 2205216.1 | T41: 2215895.5 | U41: 2242888.1 | V41: 2227722.9 | W41: 2201587.3 | X41: 2300398.6 | Y41: 2320461.6 | Z41: 2314434.5 | AA41: 2349871.2 | AB41: 2333759.2 | AC41: 2323139.5 | AD41: 2327018.7 | AE41: 2312054.5 | AF41: 2330368.4 | AG41: 2359176.1 | AH41: 2330616 | AI41: 2294942.5 | AJ41: 2501334.9 | AK41: 2439827.2 | AL41: 2437167.6 | AM41: 2427852.7 | AN41: 2434293.9 | AO41: 2404907.7 | AP41: 2375737 | AQ41: 2367575.7 | AR41: 2369193.9 | AS41: 2378078.9 | AT41: 2361632.3 | AU41: 2331465.8

Sheet CF_Monthly
A1: Monthly cash flow by class (signed: + inflow).
A2: business_id | B2: month_end | C2: beginning_cash | D2: Asset sale proceeds | E2: Chemical purchases | F2: Commodity-sale receipts | G2: Contractor payments | H2: Customer collections | I2: Debt payments - interest | J2: Debt payments - principal | K2: Equipment & capital purchases | L2: Feed purchases | M2: Fertilizer purchases | N2: Fuel | O2: Genetics payments | P2: Insurance | Q2: Insurance & government payments | R2: Lease receipts | S2: Livestock purchases | T2: Livestock-sale receipts | U2: Loan proceeds | V2: Operating line draws | W2: Operating line repayments | X2: Other operating payments | Y2: Other receipts | Z2: Owner contributions | AA2: Owner distributions | AB2: Payroll | AC2: Processing payments | AD2: Repairs | AE2: Seed purchases | AF2: Taxes | AG2: Taxes (owner estimated income tax) | AH2: Veterinary payments | AI2: net_cash_flow | AJ2: ending_cash | AK2: operating_line_balance
A3: BIZ-SAM | B3: 44957 | C3: 38650 | D3: 0 | E3: 0 | F3: 71120.24 | G3: 0 | H3: 0 | I3: -13566.98 | J3: -33014.27 | K3: 0 | L3: 0 | M3: 0 | N3: -3184.55 | O3: 0 | P3: -11780 | Q3: 0 | R3: 0 | S3: 0 | T3: 0 | U3: 0 | V3: 31000 | W3: -42000 | X3: -1035.26 | Y3: 0 | Z3: 0 | AA3: -4000 | AB3: 0 | AC3: 0 | AD3: 0 | AE3: 0 | AF3: -431.2 | AG3: -3000 | AH3: 0 | AI3: -9892.02 | AJ3: 28757.98 | AK3: 59000
A4: BIZ-SAM | B4: 44985 | C4: 28757.98 | D4: 0 | E4: 0 | F4: 0 | G4: -1344 | H4: 0 | I4: -501.3 | J4: -739.82 | K4: 0 | L4: 0 | M4: 0 | N4: 0 | O4: 0 | P4: 0 | Q4: 0 | R4: 0 | S4: 0 | T4: 0 | U4: 0 | V4: 0 | W4: 0 | X4: -4282.74 | Y4: 0 | Z4: 0 | AA4: -4000 | AB4: 0 | AC4: 0 | AD4: 0 | AE4: 0 | AF4: 0 | AG4: 0 | AH4: 0 | AI4: -10867.86 | AJ4: 17890.12 | AK4: 59000
A5: BIZ-SAM | B5: 45016 | C5: 17890.12 | D5: 0 | E5: 0 | F5: 0 | G5: 0 | H5: 0 | I5: -612.53 | J5: -742.23 | K5: 0 | L5: 0 | M5: 0 | N5: 0 | O5: 0 | P5: -6700 | Q5: 0 | R5: 0 | S5: 0 | T5: 0 | U5: 0 | V5: 14000 | W5: 0 | X5: -825.66 | Y5: 0 | Z5: 0 | AA5: -4000 | AB5: 0 | AC5: 0 | AD5: 0 | AE5: 0 | AF5: 0 | AG5: 0 | AH5: 0 | AI5: 1119.58 | AJ5: 19009.7 | AK5: 73000
A6: BIZ-SAM | B6: 45046 | C6: 19009.7 | D6: 0 | E6: -1120 | F6: 4493.52 | G6: -2304 | H6: 0 | I6: -707.77 | J6: -744.64 | K6: 0 | L6: 0 | M6: -4096 | N6: 0 | O6: 0 | P6: 0 | Q6: 0 | R6: 0 | S6: 0 | T6: 0 | U6: 0 | V6: 13000 | W6: 0 | X6: -757.88 | Y6: 0 | Z6: 0 | AA6: -4000 | AB6: 0 | AC6: 0 | AD6: -1290.98 | AE6: 0 | AF6: 0 | AG6: -3000 | AH6: 0 | AI6: -527.75 | AJ6: 18481.95 | AK6: 86000
A7: BIZ-SAM | B7: 45077 | C7: 18481.95 | D7: 0 | E7: -8299.5 | F7: 0 | G7: -864 | H7: 0 | I7: -969.3 | J7: -747.06 | K7: 0 | L7: 0 | M7: -19911.3 | N7: -2040.57 | O7: 0 | P7: 0 | Q7: 0 | R7: 0 | S7: 0 | T7: 0 | U7: 0 | V7: 40000 | W7: 0 | X7: -1182.85 | Y7: 0 | Z7: 0 | AA7: -4000 | AB7: -2197.93 | AC7: 0 | AD7: 0 | AE7: -6240 | AF7: -3390.12 | AG7: 0 | AH7: 0 | AI7: -9842.63 | AJ7: 8639.32 | AK7: 126000
A8: BIZ-SAM | B8: 45107 | C8: 8639.32 | D8: 0 | E8: -4990.5 | F8: 0 | G8: -2304 | H8: 0 | I8: -1215.74 | J8: -749.49 | K8: 0 | L8: 0 | M8: 0 | N8: 0 | O8: 0 | P8: 0 | Q8: 0 | R8: 0 | S8: 0 | T8: 0 | U8: 0 | V8: 32000 | W8: 0 | X8: -723.22 | Y8: 0 | Z8: 0 | AA8: -4000 | AB8: -3490.6 | AC8: 0 | AD8: 0 | AE8: -7872 | AF8: 0 | AG8: -3000 | AH8: 0 | AI8: 3654.45 | AJ8: 12293.77 | AK8: 158000
A9: BIZ-SAM | B9: 45138 | C9: 12293.77 | D9: 0 | E9: -3144 | F9: 16308.24 | G9: -864 | H9: 0 | I9: -1503.85 | J9: -751.92 | K9: 0 | L9: 0 | M9: 0 | N9: -660.44 | O9: 0 | P9: 0 | Q9: 0 | R9: 0 | S9: 0 | T9: 0 | U9: 0 | V9: 18000 | W9: 0 | X9: -7029.57 | Y9: 0 | Z9: 0 | AA9: -4000 | AB9: -3395.79 | AC9: 0 | AD9: -6856 | AE9: 0 | AF9: 0 | AG9: 0 | AH9: 0 | AI9: 6102.67 | AJ9: 18396.44 | AK9: 176000
A10: BIZ-SAM | B10: 45169 | C10: 18396.44 | D10: 0 | E10: -3500 | F10: 0 | G10: 0 | H10: 48288.58 | I10: -1620.09 | J10: -754.37 | K10: 0 | L10: 0 | M10: 0 | N10: -9294.25 | O10: 0 | P10: -1392 | Q10: 0 | R10: 0 | S10: 0 | T10: 0 | U10: 0 | V10: 14000 | W10: -20000 | X10: -8587.6 | Y10: 0 | Z10: 0 | AA10: -4000 | AB10: -2629.01 | AC10: 0 | AD10: 0 | AE10: 0 | AF10: 0 | AG10: 0 | AH10: 0 | AI10: 10511.26 | AJ10: 28907.7 | AK10: 170000
A11: BIZ-SAM | B11: 45199 | C11: 28907.7 | D11: 0 | E11: 0 | F11: 27942.4 | G11: -120 | H11: 8157.41 | I11: -1415.67 | J11: -756.82 | K11: 0 | L11: 0 | M11: 0 | N11: 0 | O11: 0 | P11: 0 | Q11: 4871.6 | R11: 0 | S11: 0 | T11: 0 | U11: 0 | V11: 0 | W11: 0 | X11: -5899.33 | Y11: 0 | Z11: 0 | AA11: -4000 | AB11: -5763.25 | AC11: 0 | AD11: -4250 | AE11: 0 | AF11: 0 | AG11: -3000 | AH11: 0 | AI11: 15766.34 | AJ11: 44674.04 | AK11: 170000
A12: BIZ-SAM | B12: 45230 | C12: 44674.04 | D12: 0 | E12: 0 | F12: 59010.82 | G12: 0 | H12: 10043.04 | I12: -1457.45 | J12: -759.28 | K12: 0 | L12: 0 | M12: 0 | N12: -973.28 | O12: 0 | P12: 0 | Q12: 0 | R12: 0 | S12: 0 | T12: 0 | U12: 0 | V12: 0 | W12: -57000 | X12: -4452.53 | Y12: 0 | Z12: 0 | AA12: -4000 | AB12: -4650.91 | AC12: 0 | AD12: -12195 | AE12: 0 | AF12: 0 | AG12: 0 | AH12: 0 | AI12: -16434.59 | AJ12: 28239.45 | AK12: 113000
A13: BIZ-SAM | B13: 45260 | C13: 28239.45 | D13: 0 | E13: 0 | F13: 0 | G13: 0 | H13: 33867.06 | I13: -965.67 | J13: -761.75 | K13: 0 | L13: 0 | M13: -1976 | N13: -9751.7 | O13: 0 | P13: 0 | Q13: 0 | R13: 0 | S13: 0 | T13: 0 | U13: 0 | V13: 0 | W13: 0 | X13: -819.05 | Y13: 0 | Z13: 0 | AA13: -4000 | AB13: -2402.61 | AC13: 0 | AD13: -4430.78 | AE13: -2296 | AF13: 0 | AG13: 0 | AH13: 0 | AI13: 6463.5 | AJ13: 34702.95 | AK13: 113000
A14: BIZ-SAM | B14: 45291 | C14: 34702.95 | D14: 0 | E14: 0 | F14: 0 | G14: 0 | H14: 76850.79 | I14: -16914.84 | J14: -16889.18 | K14: 0 | L14: 0 | M14: 0 | N14: -8762.09 | O14: 0 | P14: 0 | Q14: 0 | R14: 0 | S14: 0 | T14: 0 | U14: 0 | V14: 22000 | W14: -43000 | X14: -973.8 | Y14: 0 | Z14: 0 | AA14: -4000 | AB14: -179.2 | AC14: 0 | AD14: -1991.24 | AE14: -8968.75 | AF14: -3390 | AG14: 0 | AH14: 0 | AI14: -6218.31 | AJ14: 28484.64 | AK14: 92000
... A47: BIZ-SAM | B47: 46295 | C47: 27970.53 | D47: 0 | E47: 0 | F47: 31752 | G47: -130.8 | H47: 17901.11 | I47: -1825.66 | J47: -1499.3 | K47: 0 | L47: 0 | M47: 0 | N47: 0 | O47: 0 | P47: 0 | Q47: 0 | R47: 0 | S47: 0 | T47: 0 | U47: 0 | V47: 0 | W47: -29000 | X47: -5964.37 | Y47: 0 | Z47: 0 | AA47: -4200 | AB47: -4159.91 | AC47: 0 | AD47: 0 | AE47: 0 | AF47: 0 | AG47: -2500 | AH47: 0 | AI47: 373.07 | AJ47: 28343.6 | AK47: 221000

Sheet Ratios
A1: business_id | B1: period | C1: period_start | D1: period_end | E1: gross_revenue_accrual | F1: revenue | G1: ebitda | H1: net_farm_income | I1: current_ratio | J1: working_capital | K1: working_capital_to_gross_revenue | L1: debt_to_asset | M1: equity_to_asset | N1: debt_to_equity | O1: debt_to_asset_market | P1: owner_labor_mgmt_charge | Q1: rate_of_return_on_assets_cost | R1: rate_of_return_on_assets_market | S1: rate_of_return_on_equity | T1: operating_profit_margin | U1: asset_turnover | V1: operating_expense_ratio | W1: depreciation_expense_ratio | X1: interest_expense_ratio | Y1: net_farm_income_ratio | Z1: term_interest_paid | AA1: term_principal_paid | AB1: scheduled_term_debt_payments | AC1: owner_withdrawals | AD1: owner_contributions | AE1: capital_debt_repayment_capacity | AF1: repayment_margin | AG1: term_debt_coverage_ratio | AH1: total_debt | AI1: operating_line_end | AJ1: cash_end | AK1: note
A2: BIZ-SAM | B2: FY2023 | C2: 44927 | D2: 45291 | E2: 389601.2 | F2: 374668.55 | G2: 108618.06 | H2: 14853.67 | I2: 0.9302 | J2: -11630.71 | K2: -0.0299 | L2: 0.3608 | M2: 0.6392 | N2: 0.5645 | O2: 0.245 | P2: 54962.35 | Q2: 0.0007 | R2: 0.0005 | S2: -0.0315 | T2: 0.0034 | U2: 0.1954 | V2: 0.6829 | W2: 0.1726 | X2: 0.1064 | Y2: 0.0381 | Z2: 29714.77 | AA2: 57410.83 | AB2: 87125.6 | AC2: 60000 | AD2: 0 | AE2: 51814.29 | AF2: -35311.31 | AG2: 0.5947 | AH2: 691664.29 | AI2: 92000 | AJ2: 28484.64 | AK2: Gross revenue = revenue + inventory & livestock value changes + gains (FFSC accrual). YTD ratios not annualized except WC/GR.
A3: BIZ-SAM | B3: FY2024 | C3: 45292 | D3: 45657 | E3: 417048.01 | F3: 429071.06 | G3: 200379.37 | H3: 76491.54 | I3: 0.8438 | J3: -34489.54 | K3: -0.0827 | L3: 0.3717 | M3: 0.6283 | N3: 0.5915 | O3: 0.2442 | P3: 55112.94 | Q3: 0.0319 | R3: 0.0213 | S3: 0.017 | T3: 0.1519 | U3: 0.2101 | V3: 0.5484 | W3: 0.1676 | X3: 0.1006 | Y3: 0.1834 | Z3: 28766.84 | AA3: 65288.72 | AB3: 94055.56 | AC3: 63200 | AD3: 0 | AE3: 111950.02 | AF3: 17894.46 | AG3: 1.1903 | AH3: 730375.57 | AI3: 124000 | AJ3: 28016.41 | AK3: Gross revenue = revenue + inventory & livestock value changes + gains (FFSC accrual). YTD ratios not annualized except WC/GR.
A4: BIZ-SAM | B4: FY2025 | C4: 45658 | D4: 46022 | E4: 510359.17 | F4: 443445.2 | G4: 155724.89 | H4: 101633.06 | I4: 0.7706 | J4: -67672.96 | K4: -0.1326 | L4: 0.4035 | M4: 0.5965 | N4: 0.6764 | O4: 0.2666 | P4: 54962.35 | Q4: 0.0434 | R4: 0.0286 | S4: 0.0363 | T4: 0.1788 | U4: 0.2426 | V4: 0.5638 | W4: 0.1497 | X4: 0.0874 | Y4: 0.1991 | Z4: 28610.66 | AA4: 79304.82 | AB4: 107915.48 | AC4: 56400 | AD4: 0 | AE4: 150252.06 | AF4: 42336.58 | AG4: 1.3923 | AH4: 867070.75 | AI4: 175000 | AJ4: 28482.26 | AK4: Gross revenue = revenue + inventory & livestock value changes + gains (FFSC accrual). YTD ratios not annualized except WC/GR.
A5: BIZ-SAM | B5: TTM Sep-2026 | C5: 45931 | D5: 46295 | E5: 456122.69 | F5: 499554.13 | G5: 239191.75 | H5: 64423.35 | I5: 0.3415 | J5: -225881.16 | K5: -0.4952 | L5: 0.4223 | M5: 0.5777 | N5: 0.7309 | O5: 0.2686 | P5: 54962.35 | Q5: 0.0306 | R5: 0.0198 | S5: 0.0081 | T5: 0.1399 | U5: 0.2188 | V5: 0.5708 | W5: 0.1688 | X5: 0.1192 | Y5: 0.1412 | Z5: 38029.86 | AA5: 102491.68 | AB5: 140521.54 | AC5: 60400 | AD5: 0 | AE5: 119024.05 | AF5: -21497.49 | AG5: 0.847 | AH5: 834842.73 | AI5: 221000 | AJ5: 28343.6 | AK5: Gross revenue = revenue + inventory & livestock value changes + gains (FFSC accrual). YTD ratios not annualized except WC/GR.
A6: BIZ-SAM | B6: YTD Sep-2026 (not annualized) | C6: 46023 | D6: 46295 | E6: 194407.96 | F6: 234120.21 | G6: 41801.28 | H6: -90401.74 | I6: 0.3415 | J6: -225881.16 | K6: -0.8684 | L6: 0.4223 | M6: 0.5777 | N6: 0.7309 | O6: 0.2686 | P6: 41108.83 | Q6: -0.0458 | R6: -0.0297 | S6: -0.106 | T6: -0.4977 | U6: 0.0921 | V6: 0.9893 | W6: 0.2969 | X6: 0.1788 | Y6: -0.465 | Z6: 22691.1 | AA6: 78228.02 | AB6: 100919.12 | AC6: 47800 | AD6: 0 | AE6: -57782.51 | AF6: -158701.63 | AG6: -0.5726 | AH6: 834842.73 | AI6: 221000 | AJ6: 28343.6 | AK6: Gross revenue = revenue + inventory & livestock value changes + gains (FFSC accrual). YTD ratios not annualized except WC/GR.

Sheet Budget_vs_Actual
A1: business_id | B1: year | C1: period | D1: enterprise_id | E1: planned_revenue | F1: actual_revenue | G1: revenue_variance | H1: planned_expenses | I1: actual_expenses | J1: expense_variance | K1: planned_gross_margin | L1: actual_gross_margin | M1: planned_gross_margin_pct | N1: actual_gross_margin_pct | O1: planned_net_income | P1: actual_net_income | Q1: net_income_variance | R1: basis
A2: BIZ-SAM | B2: 2023 | C2: Full year | D2: ENT-SAM-CORN | E2: 104022.8 | F2: 75862.9 | G2: -28159.9 | H2: 119307.47 | I2: 122675.87 | J2: 3368.4 | K2: 3262.32 | L2: -28265.98 | M2: 0.0314 | N2: -0.3726 | O2: -15284.67 | P2: -46812.97 | Q2: -31528.3 | R2: Operating basis (excludes inventory & livestock value changes); enterprise rows include internal transfers
A3: BIZ-SAM | B3: 2023 | C3: Full year | D3: ENT-SAM-COT | E3: 41289.6 | F3: 23992.12 | G3: -17297.48 | H3: 39354.2 | I3: 37228.76 | J3: -2125.44 | K3: 2366.4 | L3: -12805.64 | M3: 0.0573 | N3: -0.5337 | O3: 1935.4 | P3: -13236.64 | Q3: -15172.04 | R3: Operating basis (excludes inventory & livestock value changes); enterprise rows include internal transfers
A4: BIZ-SAM | B4: 2023 | C4: Full year | D4: ENT-SAM-CUS | E4: 220678.64 | F4: 196886.41 | G4: -23792.23 | H4: 109871.29 | I4: 104960.95 | J4: -4910.34 | K4: 149220.61 | L4: 130338.72 | M4: 0.6762 | N4: 0.662 | O4: 110807.35 | P4: 91925.46 | Q4: -18881.89 | R4: Operating basis (excludes inventory & livestock value changes); enterprise rows include internal transfers
A5: BIZ-SAM | B5: 2023 | C5: Full year | D5: ENT-SAM-OVH | E5: 0 | F5: 0 | G5: 0 | H5: 74797.81 | I5: 77965.15 | J5: 3167.34 | K5: -12050.4 | L5: -12366.52 | O5: -74797.81 | P5: -77965.15 | Q5: -3167.34 | R5: Operating basis (excludes inventory & livestock value changes); enterprise rows include internal transfers
A6: BIZ-SAM | B6: 2023 | C6: Full year | D6: ENT-SAM-SOY | E6: 54644 | F6: 54644 | G6: 0 | H6: 11623.04 | I6: 11623.04 | J6: 0 | K6: 54644 | L6: 54644 | M6: 1 | N6: 1 | O6: 43020.96 | P6: 43020.96 | Q6: 0 | R6: Operating basis (excludes inventory & livestock value changes); enterprise rows include internal transfers
A7: BIZ-SAM | B7: 2023 | C7: Full year | D7: ENT-SAM-WHT | E7: 28913.76 | F7: 23283.12 | G7: -5630.64 | H7: 20293.76 | I7: 20293.76 | J7: 0 | K7: 15539.72 | L7: 9909.08 | M7: 0.5375 | N7: 0.4256 | O7: 8620 | P7: 2989.36 | Q7: -5630.64 | R7: Operating basis (excludes inventory & livestock value changes); enterprise rows include internal transfers
A8: BIZ-SAM | B8: 2023 | C8: Full year | D8: TOTAL | E8: 449548.8 | F8: 374668.55 | G8: -74880.25 | H8: 375247.57 | I8: 374747.53 | J8: -500.04 | K8: 212982.65 | L8: 141453.66 | M8: 0.4738 | N8: 0.3775 | O8: 74301.23 | P8: -78.98 | Q8: -74380.21 | R8: Operating basis (excludes inventory & livestock value changes); enterprise rows include internal transfers
A9: BIZ-SAM | B9: 2024 | C9: Full year | D9: ENT-SAM-CORN | E9: 92106 | F9: 74384.21 | G9: -17721.79 | H9: 19769.47 | I9: 19769.47 | J9: 0 | K9: 91280.4 | L9: 73558.61 | M9: 0.991 | N9: 0.9889 | O9: 72336.53 | P9: 54614.74 | Q9: -17721.79 | R9: Operating basis (excludes inventory & livestock value changes); enterprise rows include internal transfers
A10: BIZ-SAM | B10: 2024 | C10: Full year | D10: ENT-SAM-COT | E10: 38493.73 | F10: 40196.43 | G10: 1702.7 | H10: 44514.89 | I10: 44885.83 | J10: 370.94 | K10: -5577.23 | L10: -4245.47 | M10: -0.1449 | N10: -0.1056 | O10: -6021.16 | P10: -4689.4 | Q10: 1331.76 | R10: Operating basis (excludes inventory & livestock value changes); enterprise rows include internal transfers
A11: BIZ-SAM | B11: 2024 | C11: Full year | D11: ENT-SAM-CUS | E11: 234502.72 | F11: 235377.78 | G11: 875.06 | H11: 115254.1 | I11: 116274.59 | J11: 1020.49 | K11: 160007.45 | L11: 159862.02 | M11: 0.6823 | N11: 0.6792 | O11: 119248.62 | P11: 119103.19 | Q11: -145.43 | R11: Operating basis (excludes inventory & livestock value changes); enterprise rows include internal transfers
A12: BIZ-SAM | B12: 2024 | C12: Full year | D12: ENT-SAM-OVH | E12: 0 | F12: 0 | G12: 0 | H12: 70584.6 | I12: 80729.66 | J12: 10145.06 | K12: -12532 | L12: -13424.82 | O12: -70584.6 | P12: -80729.66 | Q12: -10145.06 | R12: Operating basis (excludes inventory & livestock value changes); enterprise rows include internal transfers
A13: BIZ-SAM | B13: 2024 | C13: Full year | D13: ENT-SAM-SOY | E13: 76466.07 | F13: 66902.4 | G13: -9563.67 | H13: 60668.58 | I13: 59258.58 | J13: -1410 | K13: 27552.82 | L13: 19399.15 | M13: 0.3603 | N13: 0.29 | O13: 15797.49 | P13: 7643.82 | Q13: -8153.67 | R13: Operating basis (excludes inventory & livestock value changes); enterprise rows include internal transfers
A14: BIZ-SAM | B14: 2024 | C14: Full year | D14: ENT-SAM-WHT | E14: 13278.91 | F14: 12210.24 | G14: -1068.67 | H14: 19638.34 | I14: 19638.34 | J14: 0 | K14: 692.55 | L14: -376.12 | M14: 0.0522 | N14: -0.0308 | O14: -6359.43 | P14: -7428.1 | Q14: -1068.67 | R14: Operating basis (excludes inventory & livestock value changes); enterprise rows include internal transfers
A15: BIZ-SAM | B15: 2024 | C15: Full year | D15: TOTAL | E15: 454847.43 | F15: 429071.06 | G15: -25776.37 | H15: 330429.98 | I15: 340556.47 | J15: 10126.49 | K15: 261423.99 | L15: 234773.37 | M15: 0.5748 | N15: 0.5472 | O15: 124417.45 | P15: 88514.59 | Q15: -35902.86 | R15: Operating basis (excludes inventory & livestock value changes); enterprise rows include internal transfers
A16: BIZ-SAM | B16: 2025 | C16: Full year | D16: ENT-SAM-CORN | E16: 38320.04 | F16: 39211.28 | G16: 891.24 | H16: 91761.97 | I16: 93162.37 | J16: 1400.4 | K16: -33261.84 | L16: -33771 | M16: -0.868 | N16: -0.8613 | O16: -53441.93 | P16: -53951.09 | Q16: -509.16 | R16: Operating basis (excludes inventory & livestock value changes); enterprise rows include internal transfers
A17: BIZ-SAM | B17: 2025 | C17: Full year | D17: ENT-SAM-COT | E17: 37120.38 | F17: 49296.28 | G17: 12175.9 | H17: 45763.01 | I17: 46867.2 | J17: 1104.19 | K17: -8185.38 | L17: 2886.33 | M17: -0.2205 | N17: 0.0586 | O17: -8642.63 | P17: 2429.08 | Q17: 11071.71 | R17: Operating basis (excludes inventory & livestock value changes); enterprise rows include internal transfers
A18: BIZ-SAM | B18: 2025 | C18: Full year | D18: ENT-SAM-CUS | E18: 251815.75 | F18: 265687.6 | G18: 13871.85 | H18: 127932.66 | I18: 138718.88 | J18: 10786.22 | K18: 173752.83 | L18: 176838.46 | M18: 0.69 | N18: 0.6656 | O18: 123883.09 | P18: 126968.72 | Q18: 3085.63 | R18: Operating basis (excludes inventory & livestock value changes); enterprise rows include internal transfers
A19: BIZ-SAM | B19: 2025 | C19: Full year | D19: ENT-SAM-OVH | E19: 0 | F19: 6215 | G19: 6215 | H19: 72743.27 | I19: 83438.43 | J19: 10695.16 | K19: -13013.6 | L19: -7038.06 | N19: -1.1324 | O19: -72743.27 | P19: -77223.43 | Q19: -4480.16 | R19: Operating basis (excludes inventory & livestock value changes); enterprise rows include internal transfers
A20: BIZ-SAM | B20: 2025 | C20: Full year | D20: ENT-SAM-SOY | E20: 59949.94 | F20: 62677.6 | G20: 2727.66 | H20: 25065.08 | I20: 25065.08 | J20: 0 | K20: 47669.14 | L20: 50396.8 | M20: 0.7951 | N20: 0.8041 | O20: 34884.86 | P20: 37612.52 | Q20: 2727.66 | R20: Operating basis (excludes inventory & livestock value changes); enterprise rows include internal transfers
A21: BIZ-SAM | B21: 2025 | C21: Full year | D21: ENT-SAM-WHT | E21: 18946.85 | F21: 20357.44 | G21: 1410.59 | H21: 19994.15 | I21: 21474.15 | J21: 1480 | K21: 6307.97 | L21: 6238.56 | M21: 0.3329 | N21: 0.3065 | O21: -1047.3 | P21: -1116.71 | Q21: -69.41 | R21: Operating basis (excludes inventory & livestock value changes); enterprise rows include internal transfers
A22: BIZ-SAM | B22: 2025 | C22: Full year | D22: TOTAL | E22: 406152.96 | F22: 443445.2 | G22: 37292.24 | H22: 383260.14 | I22: 408726.11 | J22: 25465.97 | K22: 173269.12 | L22: 195551.09 | M22: 0.4266 | N22: 0.441 | O22: 22892.82 | P22: 34719.09 | Q22: 11826.27 | R22: Operating basis (excludes inventory & livestock value changes); enterprise rows include internal transfers
A23: BIZ-SAM | B23: 2026 | C23: YTD Jan-Sep | D23: ENT-SAM-CORN | E23: 109054.51 | F23: 117118.74 | G23: 8064.23 | H23: 40592.36 | I23: 40592.36 | J23: 0 | K23: 83699.31 | L23: 91763.54 | M23: 0.7675 | N23: 0.7835 | O23: 68462.15 | P23: 76526.38 | Q23: 8064.23 | R23: Operating basis (excludes inventory & livestock value changes); enterprise rows include internal transfers
A24: BIZ-SAM | B24: 2026 | C24: YTD Jan-Sep | D24: ENT-SAM-COT | E24: 0 | F24: 11265.6 | G24: 11265.6 | H24: 30800.4 | I24: 30800.4 | J24: 0 | K24: -30800.4 | L24: -19534.8 | N24: -1.734 | O24: -30800.4 | P24: -19534.8 | Q24: 11265.6 | R24: Operating basis (excludes inventory & livestock value changes); enterprise rows include internal transfers
A25: BIZ-SAM | B25: 2026 | C25: YTD Jan-Sep | D25: ENT-SAM-CUS | E25: 92173.75 | F25: 60106.99 | G25: -32066.76 | H25: 98235.38 | I25: 92586.2 | J25: -5649.18 | K25: 34160.2 | L25: 7742.62 | M25: 0.3706 | N25: 0.1288 | O25: -6061.63 | P25: -32479.21 | Q25: -26417.58 | R25: Operating basis (excludes inventory & livestock value changes); enterprise rows include internal transfers
A26: BIZ-SAM | B26: 2026 | C26: YTD Jan-Sep | D26: ENT-SAM-OVH | E26: 0 | F26: 0 | G26: 0 | H26: 55193.91 | I26: 61089.01 | J26: 5895.1 | K26: -8595.6 | L26: -8675.31 | O26: -55193.91 | P26: -61089.01 | Q26: -5895.1 | R26: Operating basis (excludes inventory & livestock value changes); enterprise rows include internal transfers
A27: BIZ-SAM | B27: 2026 | C27: YTD Jan-Sep | D27: ENT-SAM-SOY | E27: 15659.04 | F27: 19841.6 | G27: 4182.56 | H27: 44625.01 | I27: 45565.01 | J27: 940 | K27: -19251.21 | L27: -16008.65 | M27: -1.2294 | N27: -0.8068 | O27: -28965.97 | P27: -25723.41 | Q27: 3242.56 | R27: Operating basis (excludes inventory & livestock value changes); enterprise rows include internal transfers
A28: BIZ-SAM | B28: 2026 | C28: YTD Jan-Sep | D28: ENT-SAM-WHT | E28: 23128.06 | F28: 25787.28 | G28: 2659.22 | H28: 14176.72 | I28: 14176.72 | J28: 0 | K28: 14485.5 | L28: 17144.72 | M28: 0.6263 | N28: 0.6649 | O28: 8951.34 | P28: 11610.56 | Q28: 2659.22 | R28: Operating basis (excludes inventory & livestock value changes); enterprise rows include internal transfers
A29: BIZ-SAM | B29: 2026 | C29: YTD Jan-Sep | D29: TOTAL | E29: 240015.36 | F29: 234120.21 | G29: -5895.15 | H29: 283623.78 | I29: 284809.7 | J29: 1185.92 | K29: 73697.8 | L29: 72432.12 | M29: 0.3071 | N29: 0.3094 | O29: -43608.42 | P29: -50689.49 | Q29: -7081.07 | R29: Operating basis (excludes inventory & livestock value changes); enterprise rows include internal transfers
A30: BIZ-SAM | B30: 2026 | C30: Full-year budget (reference) | D30: ENT-SAM-CORN | E30: 109054.51 | H30: 46049.42 | K30: 83321.31 | M30: 0.764 | O30: 63005.09 | R30: Operating basis (excludes inventory & livestock value changes); enterprise rows include internal transfers
A31: BIZ-SAM | B31: 2026 | C31: Full-year budget (reference) | D31: ENT-SAM-COT | E31: 34776.19 | H31: 47709.45 | K31: -12462.29 | M31: -0.3584 | O31: -12933.26 | R31: Operating basis (excludes inventory & livestock value changes); enterprise rows include internal transfers
A32: BIZ-SAM | B32: 2026 | C32: Full-year budget (reference) | D32: ENT-SAM-CUS | E32: 256327.13 | H32: 130572.61 | K32: 173421.85 | M32: 0.6766 | O32: 125754.52 | R32: Operating basis (excludes inventory & livestock value changes); enterprise rows include internal transfers
A33: BIZ-SAM | B33: 2026 | C33: Full-year budget (reference) | D33: ENT-SAM-OVH | E33: 14470 | H33: 87127.07 | K33: 974.8 | M33: 0.0674 | O33: -72657.07 | R33: Operating basis (excludes inventory & livestock value changes); enterprise rows include internal transfers
A34: BIZ-SAM | B34: 2026 | C34: Full-year budget (reference) | D34: ENT-SAM-SOY | E34: 50507.65 | H34: 51413.01 | K34: 12047.65 | M34: 0.2385 | O34: -905.36 | R34: Operating basis (excludes inventory & livestock value changes); enterprise rows include internal transfers
A35: BIZ-SAM | B35: 2026 | C35: Full-year budget (reference) | D35: ENT-SAM-WHT | E35: 28983.68 | H35: 21155.84 | K35: 15206.72 | M35: 0.5247 | O35: 7827.84 | R35: Operating basis (excludes inventory & livestock value changes); enterprise rows include internal transfers
A36: BIZ-SAM | B36: 2026 | C36: Full-year budget (reference) | D36: TOTAL | E36: 494119.16 | H36: 384027.4 | K36: 272510.04 | M36: 0.5515 | O36: 110091.76 | R36: Operating basis (excludes inventory & livestock value changes); enterprise rows include internal transfers

Sheet Budget_Monthly
A1: business_id | B1: month_end | C1: revenue | D1: cost_of_production | E1: overhead | F1: depreciation | G1: interest | H1: net_income_operating_basis
A2: BIZ-SAM | B2: 44957 | C2: 54644 | D2: 1344 | E2: 13315 | F2: 5603.83 | G2: 13566.98 | H2: 20814.19
A3: BIZ-SAM | B3: 44985 | C3: 0 | D3: 0 | E3: 4295 | F3: 5603.81 | G3: 501.3 | H3: -10400.11
A4: BIZ-SAM | B4: 45016 | C4: 0 | D4: 23232.5 | E4: 735 | F4: 5603.84 | G4: 612.53 | H4: -30183.87
A5: BIZ-SAM | B5: 45046 | C5: 0 | D5: 62992.87 | E5: 1215 | F5: 5603.81 | G5: 707.77 | H5: -70519.45
A6: BIZ-SAM | B6: 45077 | C6: 0 | D6: 17729.82 | E6: 735 | F6: 5603.82 | G6: 970.82 | H6: -25039.46
A7: BIZ-SAM | B7: 45107 | C7: 89002.28 | D7: 20059.02 | E7: 735 | F7: 5603.8 | G7: 1215.74 | H7: 61388.72
A8: BIZ-SAM | B8: 45138 | C8: 6230.78 | D8: 25448.31 | E8: 735 | F8: 5603.83 | G8: 1503.85 | H8: -27060.21
A9: BIZ-SAM | B9: 45169 | C9: 0 | D9: 12435.32 | E9: 735 | F9: 5603.83 | G9: 1012.87 | H9: -19787.02
A10: BIZ-SAM | B10: 45199 | C10: 45628.8 | D10: 23752.78 | E10: 735 | F10: 5603.81 | G10: 1111.15 | H10: 14426.06
A11: BIZ-SAM | B11: 45230 | C11: 182335.53 | D11: 23817.66 | E11: 735 | F11: 5603.83 | G11: 989.48 | H11: 151189.56
A12: BIZ-SAM | B12: 45260 | C12: 30417.81 | D12: 20051.47 | E12: 735 | F12: 5603.81 | G12: 606.49 | H12: 3421.04
A13: BIZ-SAM | B13: 45291 | C13: 41289.6 | D13: 5702.4 | E13: 8106 | F13: 5603.83 | G13: 15825.59 | H13: 6051.78
... A49: BIZ-SAM | B49: 46387 | C49: 40631.81 | D49: 6124.8 | E49: 8883.07 | F49: 6414.24 | G49: 13807.66 | H49: 5402.04

Sheet Forecast_12M
A1: Monthly forecast Oct-2026 to Sep-2027 by scenario (IS + cash flow). Negative ending cash = projected shortfall with the line maxed.
A2: business_id | B2: scenario | C2: month_end | D2: revenue | E2: cost_of_production | F2: gross_profit | G2: overhead | H2: ebitda | I2: depreciation | J2: interest | K2: net_income_before_inventory | L2: inventory_change | M2: livestock_value_change | N2: net_farm_income | O2: beginning_cash | P2: cf_Collections - invoices outstanding at 9/30 | Q2: cf_Expected commodity sales | R2: cf_Expected livestock sales | S2: cf_Expected customer receipts | T2: cf_Government & insurance receipts | U2: cf_Other receipts (leases, misc.) | V2: cf_Asset sales | W2: cf_Payment of AP/accruals outstanding at 9/30 | X2: cf_Payroll | Y2: cf_Planned input purchases | Z2: cf_Contractor payments | AA2: cf_Veterinary & genetics | AB2: cf_Processing | AC2: cf_Fuel, repairs & equipment expenses | AD2: cf_Insurance | AE2: cf_Property & payroll taxes | AF2: cf_Other operating payments | AG2: cf_Scheduled debt payments | AH2: cf_Operating line interest | AI2: cf_Equipment & capital purchases | AJ2: cf_Owner distributions | AK2: cf_Owner estimated income taxes | AL2: cf_Operating line draws | AM2: cf_Operating line repayments | AN2: cf_Term loan proceeds | AO2: cf_Owner contributions | AP2: ending_cash | AQ2: operating_line_balance
A3: BIZ-SAM | B3: Base | C3: 46326 | D3: 207072.57 | E3: 29807.86 | F3: 177264.71 | G3: 694.51 | H3: 176570.2 | I3: 6414.25 | J3: 1687.77 | K3: 168468.18 | L3: 15753.57 | M3: 0 | N3: 184221.75 | O3: 28343.6 | P3: 4613.98 | Q3: 36449.6 | R3: 0 | S3: 0 | T3: 14470 | U3: 0 | V3: 0 | W3: -21393.12 | X3: -7152.45 | Y3: 0 | Z3: 0 | AA3: 0 | AB3: 0 | AC3: 0 | AD3: 0 | AE3: 0 | AF3: -289.1 | AG3: -1732.49 | AH3: -1463.63 | AI3: 0 | AJ3: -4200 | AK3: 0 | AL3: 17000 | AM3: -36000 | AN3: 0 | AO3: 0 | AP3: 28646.39 | AQ3: 202000
A4: BIZ-SAM | B4: Base | C4: 46356 | D4: 17904.97 | E4: 19857.55 | F4: -1952.58 | G4: 746.1 | H4: -2698.68 | I4: 6414.23 | J4: 1460.23 | K4: -10573.14 | L4: -33454.57 | M4: 0 | N4: -44027.71 | O4: 28646.39 | P4: 0 | Q4: 0 | R4: 0 | S4: 61802.46 | T4: 0 | U4: 0 | V4: 0 | W4: 0 | X4: -2011.71 | Y4: -6531.52 | Z4: -941.76 | AA4: 0 | AB4: 0 | AC4: -14552.71 | AD4: 0 | AE4: 0 | AF4: -632.04 | AG4: -1732.49 | AH4: -1245.21 | AI4: 0 | AJ4: -4200 | AK4: 0 | AL4: 0 | AM4: -30000 | AN4: 0 | AO4: 0 | AP4: 28601.41 | AQ4: 172000
A5: BIZ-SAM | B5: Base | C5: 46387 | D5: 47754.38 | E5: 6333.6 | F5: 41420.78 | G5: 8869.44 | H5: 32551.34 | I5: 6414.24 | J5: 15027.38 | K5: 11109.72 | L5: -4709.93 | M5: 0 | N5: 6399.79 | O5: 28601.41 | P5: 12843.25 | Q5: 4803.84 | R5: 0 | S5: 58168.06 | T5: 0 | U5: 0 | V5: 0 | W5: 0 | X5: -121.64 | Y5: -32450 | Z5: 0 | AA5: 0 | AB5: 0 | AC5: -10865.62 | AD5: 0 | AE5: -3758.55 | AF5: -954.04 | AG5: -33602.17 | AH5: -1273.97 | AI5: 0 | AJ5: -4200 | AK5: 0 | AL5: 28000 | AM5: -17000 | AN5: 0 | AO5: 0 | AP5: 28190.57 | AQ5: 183000
A6: BIZ-SAM | B6: Base | C6: 46418 | D6: 43855.98 | E6: 1505.28 | F6: 42350.7 | G6: 21261.67 | H6: 21089.03 | I6: 6414.22 | J6: 7393.69 | K6: 7281.12 | L6: -42265.42 | M6: 0 | N6: -34984.3 | O6: 28190.57 | P6: 0 | Q6: 63555.66 | R6: 0 | S6: 41634.89 | T6: 0 | U6: 0 | V6: 0 | W6: 0 | X6: 0 | Y6: 0 | Z6: -7488 | AA6: 0 | AB6: 0 | AC6: 0 | AD6: -19300 | AE6: -470.97 | AF6: -2000.98 | AG6: -46847.33 | AH6: -1165.68 | AI6: 0 | AJ6: -4200 | AK6: -2500 | AL6: 0 | AM6: -21000 | AN6: 0 | AO6: 0 | AP6: 28408.16 | AQ6: 162000
A7: BIZ-SAM | B7: Base | C7: 46446 | D7: 0 | E7: 0 | F7: 0 | G7: 4818.1 | H7: -4818.1 | I7: 6414.24 | J7: 1119.4 | K7: -12351.74 | L7: 0.03 | M7: 0 | N7: -12351.71 | O7: 28408.16 | P7: 0 | Q7: 7132.94 | R7: 0 | S7: 12452.53 | T7: 0 | U7: 0 | V7: 0 | W7: 0 | X7: 0 | Y7: 0 | Z7: -7838.88 | AA7: 0 | AB7: 0 | AC7: 0 | AD7: 0 | AE7: 0 | AF7: -4761.49 | AG7: -1732.49 | AH7: -932.05 | AI7: 0 | AJ7: -4200 | AK7: 0 | AL7: 0 | AM7: 0 | AN7: 0 | AO7: 0 | AP7: 28528.72 | AQ7: 162000
A8: BIZ-SAM | B8: Base | C8: 46477 | D8: 0 | E8: 21624.03 | F8: -21624.03 | G8: 639.78 | H8: -22263.81 | I8: 6414.23 | J8: 12021.22 | K8: -40699.26 | L8: 9092.46 | M8: 0 | N8: -31606.8 | O8: 28528.72 | P8: 0 | Q8: 0 | R8: 0 | S8: 0 | T8: 0 | U8: 0 | V8: 0 | W8: 0 | X8: 0 | Y8: 0 | Z8: 0 | AA8: 0 | AB8: 0 | AC8: 0 | AD8: -5900 | AE8: 0 | AF8: -712.72 | AG8: -36874.14 | AH8: -1191.16 | AI8: 0 | AJ8: -4200 | AK8: 0 | AL8: 31000 | AM8: 0 | AN8: 0 | AO8: 0 | AP8: 10650.7 | AQ8: 193000
A9: BIZ-SAM | B9: Base | C9: 46507 | D9: 0 | E9: 46444.19 | F9: -46444.19 | G9: 1191.35 | H9: -47635.54 | I9: 6414.25 | J9: 1469.31 | K9: -55519.1 | L9: 56071.21 | M9: 0 | N9: 552.11 | O9: 10650.7 | P9: 0 | Q9: 5372.64 | R9: 0 | S9: 0 | T9: 0 | U9: 0 | V9: 0 | W9: 0 | X9: 0 | Y9: -12290.75 | Z9: -2580.48 | AA9: 0 | AB9: 0 | AC9: -852.8 | AD9: 0 | AE9: 0 | AF9: -638.37 | AG9: -1732.49 | AH9: -1300.68 | AI9: 0 | AJ9: -4200 | AK9: -2500 | AL9: 18000 | AM9: 0 | AN9: 0 | AO9: 0 | AP9: 7927.77 | AQ9: 211000
A10: BIZ-SAM | B10: Base | C10: 46538 | D10: 0 | E10: 37581.43 | F10: -37581.43 | G10: 740.43 | H10: -38321.86 | I10: 6414.24 | J10: 1638.22 | K10: -46374.32 | L10: 25722.65 | M10: 0 | N10: -20651.67 | O10: 7927.77 | P10: 0 | Q10: 0 | R10: 0 | S10: 0 | T10: 0 | U10: 0 | V10: 0 | W10: 0 | X10: -2774.6 | Y10: -10769.29 | Z10: -967.68 | AA10: 0 | AB10: 0 | AC10: -2257.22 | AD10: 0 | AE10: -3758.55 | AF10: -1206.81 | AG10: -1732.49 | AH10: -1479.04 | AI10: 0 | AJ10: -4200 | AK10: 0 | AL10: 30000 | AM10: 0 | AN10: 0 | AO10: 0 | AP10: 8782.09 | AQ10: 241000
A11: BIZ-SAM | B11: Base | C11: 46568 | D11: 65077.55 | E11: 24700.57 | F11: 40376.98 | G11: 723.76 | H11: 39653.22 | I11: 6414.22 | J11: 1690.77 | K11: 31548.23 | L11: 2393.21 | M11: 0 | N11: 33941.44 | O11: 8782.09 | P11: 0 | Q11: 0 | R11: 0 | S11: 0 | T11: 0 | U11: 0 | V11: 0 | W11: 0 | X11: -4770.6 | Y11: -21622.75 | Z11: -2580.48 | AA11: 0 | AB11: 0 | AC11: -10359.44 | AD11: 0 | AE11: 0 | AF11: -745.49 | AG11: -1732.49 | AH11: -1541.1 | AI11: 0 | AJ11: -4200 | AK11: -2500 | AL11: 9000 | AM11: 0 | AN11: 0 | AO11: 0 | AP11: -32270.26 | AQ11: 250000
A12: BIZ-SAM | B12: Base | C12: 46599 | D12: 43035.85 | E12: 27430.12 | F12: 15605.73 | G12: 750 | H12: 14855.73 | I12: 6414.25 | J12: 1732.58 | K12: 6708.9 | L12: 12623.76 | M12: 0 | N12: 19332.66 | O12: -32270.26 | P12: 0 | Q12: 19978.56 | R12: 0 | S12: 0 | T12: 0 | U12: 0 | V12: 0 | W12: 0 | X12: -4216.96 | Y12: -3287.28 | Z12: -967.68 | AA12: 0 | AB12: 0 | AC12: -9545.84 | AD12: 0 | AE12: 0 | AF12: -6675.11 | AG12: -1732.49 | AH12: -1592.47 | AI12: 0 | AJ12: -4200 | AK12: 0 | AL12: 0 | AM12: 0 | AN12: 0 | AO12: 0 | AP12: -44509.53 | AQ12: 250000
A13: BIZ-SAM | B13: Base | C13: 46630 | D13: 0 | E13: 8903.41 | F13: -8903.41 | G13: 771.19 | H13: -9674.6 | I13: 6414.24 | J13: 1722.96 | K13: -17811.8 | L13: 5755.89 | M13: 0 | N13: -12055.91 | O13: -44509.53 | P13: 0 | Q13: 0 | R13: 0 | S13: 78992.43 | T13: 0 | U13: 0 | V13: 0 | W13: 0 | X13: -3198.52 | Y13: -5355.28 | Z13: -967.68 | AA13: 0 | AB13: 0 | AC13: -10607.49 | AD13: -1559.04 | AE13: 0 | AF13: -7141.11 | AG13: -1732.49 | AH13: -1592.47 | AI13: 0 | AJ13: -4200 | AK13: 0 | AL13: 0 | AM13: 0 | AN13: 0 | AO13: 0 | AP13: -1871.18 | AQ13: 250000
A14: BIZ-SAM | B14: Base | C14: 46660 | D14: 14847.52 | E14: 22660.51 | F14: -7812.99 | G14: 751.51 | H14: -8564.5 | I14: 6414.24 | J14: 1661.91 | K14: -16640.65 | L14: 134.4 | M14: 0 | N14: -16506.25 | O14: -1871.18 | P14: 0 | Q14: 0 | R14: 0 | S14: 14515.05 | T14: 0 | U14: 0 | V14: 0 | W14: 0 | X14: -4047.39 | Y14: 0 | Z14: -134.4 | AA14: 0 | AB14: 0 | AC14: 0 | AD14: 0 | AE14: 0 | AF14: -4983.89 | AG14: -1732.49 | AH14: -1541.1 | AI14: 0 | AJ14: -4200 | AK14: -2500 | AL14: 0 | AM14: 0 | AN14: 0 | AO14: 0 | AP14: -6495.4 | AQ14: 250000
... A38: BIZ-SAM | B38: Downside | C38: 46660 | D38: 14847.52 | E38: 22660.51 | F38: -7812.99 | G38: 751.51 | H38: -8564.5 | I38: 6414.24 | J38: 1816.02 | K38: -16794.76 | L38: 134.4 | M38: 0 | N38: -16660.36 | O38: -35103.82 | P38: 0 | Q38: 0 | R38: 0 | S38: 14515.05 | T38: 0 | U38: 0 | V38: 0 | W38: 0 | X38: -4047.39 | Y38: 0 | Z38: -134.4 | AA38: 0 | AB38: 0 | AC38: 0 | AD38: 0 | AE38: 0 | AF38: -4983.89 | AG38: -1732.49 | AH38: -1695.21 | AI38: 0 | AJ38: -4200 | AK38: -2500 | AL38: 0 | AM38: 0 | AN38: 0 | AO38: 0 | AP38: -39882.15 | AQ38: 250000

Sheet Forecast_Assumptions
A1: business_id | B1: scenario | C1: driver | D1: assumption | E1: source_or_note
A2: BIZ-SAM | B2: Base | C2: Cotton pool price 2026 crop | D2: $0.82/lb lint | E2: Dec-26 futures ~88.8c (Aug 2026) less pool basis/costs
A3: BIZ-SAM | B3: Optimistic | C3: Cotton pool price 2026 crop | D3: $0.88/lb
A4: BIZ-SAM | B4: Downside | C4: Cotton pool price 2026 crop | D4: $0.70/lb (-15%)
A5: BIZ-SAM | B5: Base | C5: Cotton yield 2026 | D5: 455 lb lint/ac | E5: APH 440
A6: BIZ-SAM | B6: Optimistic | C6: Cotton yield 2026 | D6: 525 lb/ac
A7: BIZ-SAM | B7: Downside | C7: Cotton yield 2026 | D7: 300 lb/ac | E7: Late-season drought / hail
A8: BIZ-SAM | B8: Base | C8: Corn / soybean / wheat cash prices | D8: Corn $4.20-4.30, soy $10.25-10.40, wheat $5.55-5.70 | E8: Central KS cash
A9: BIZ-SAM | B9: Optimistic | C9: Grain prices | D9: Corn $4.45-4.60, soy $10.80-11.10, wheat $6.00-6.20
A10: BIZ-SAM | B10: Downside | C10: Grain prices | D10: Corn $3.55-3.80, soy $9.10-9.40, wheat $4.75-4.95
A11: BIZ-SAM | B11: All | C11: Known contract | D11: Forward contract #FC-2611: 4,000 bu soybeans @ $10.45, Nov-2026 delivery | E11: Hedges ~50% of 2026 irrigated soy
A12: BIZ-SAM | B12: Base/Opt/Down | C12: Yield factor 2027 crops | D12: 100% / 105-108% / 72-85% of APH | E12: Downside wheat 72% (repeat of 2026 freeze)
A13: BIZ-SAM | B13: All | C13: Custom harvest acres 2027 | D13: Wheat 1,900; soybeans 1,450; corn 1,300 | E13: Client commitments; rates +$1/ac
A14: BIZ-SAM | B14: Base/Opt/Down | C14: Prime rate | D14: 6.50% / 6.25% / 7.25% | E14: Line = prime + 1.00%
A15: BIZ-SAM | B15: All | C15: ARC/PLC 2025 crop (Oct 2026) | D15: Base $14,470 / Opt $10,700 / Down $18,700 | E15: OBBBA reference prices

Sheet Cash_13_Week
A1: Rolling 13-week cash forecast from 10/1/2026 (base case).
A2: business_id | B2: week | C2: week_start | D2: week_end | E2: starting_cash | F2: Collections - invoices outstanding at 9/30 | G2: Expected commodity sales | H2: Expected livestock sales | I2: Expected customer receipts | J2: Government & insurance receipts | K2: Other receipts (leases, misc.) | L2: Asset sales | M2: Total receipts | N2: Payment of AP/accruals outstanding at 9/30 | O2: Payroll | P2: Planned input purchases | Q2: Contractor payments | R2: Veterinary & genetics | S2: Processing | T2: Fuel, repairs & equipment expenses | U2: Insurance | V2: Property & payroll taxes | W2: Other operating payments | X2: Scheduled debt payments | Y2: Operating line interest | Z2: Equipment & capital purchases | AA2: Owner distributions | AB2: Owner estimated income taxes | AC2: Total disbursements | AD2: Net cash before financing | AE2: Operating line draws | AF2: Operating line repayments | AG2: Term loan proceeds | AH2: Owner contributions | AI2: Ending projected cash | AJ2: Operating line balance | AK2: Line availability
A3: BIZ-SAM | B3: 1 | C3: 46296 | D3: 46302 | E3: 28343.6 | F3: 0 | G3: 0 | H3: 0 | I3: 0 | J3: 0 | K3: 0 | L3: 0 | M3: 0 | N3: -6646.08 | O3: -2357.4 | P3: 0 | Q3: 0 | R3: 0 | S3: 0 | T3: 0 | U3: 0 | V3: 0 | W3: 0 | X3: 0 | Y3: 0 | Z3: 0 | AA3: -4200 | AB3: 0 | AC3: -13203.48 | AD3: -13203.48 | AE3: 0 | AF3: 0 | AG3: 0 | AH3: 0 | AI3: 15140.12 | AJ3: 221000 | AK3: 29000
A4: BIZ-SAM | B4: 2 | C4: 46303 | D4: 46309 | E4: 15140.12 | F4: 0 | G4: 0 | H4: 0 | I4: 0 | J4: 0 | K4: 0 | L4: 0 | M4: 0 | N4: 0 | O4: 0 | P4: 0 | Q4: 0 | R4: 0 | S4: 0 | T4: 0 | U4: 0 | V4: 0 | W4: -289.1 | X4: 0 | Y4: 0 | Z4: 0 | AA4: 0 | AB4: 0 | AC4: -289.1 | AD4: -289.1 | AE4: 0 | AF4: 0 | AG4: 0 | AH4: 0 | AI4: 14851.02 | AJ4: 221000 | AK4: 29000
A5: BIZ-SAM | B5: 3 | C5: 46310 | D5: 46316 | E5: 14851.02 | F5: 0 | G5: 36449.6 | H5: 0 | I5: 0 | J5: 14470 | K5: 0 | L5: 0 | M5: 50919.6 | N5: -6590.84 | O5: -2549.87 | P5: 0 | Q5: 0 | R5: 0 | S5: 0 | T5: 0 | U5: 0 | V5: 0 | W5: 0 | X5: -1732.49 | Y5: 0 | Z5: 0 | AA5: 0 | AB5: 0 | AC5: -10873.2 | AD5: 40046.4 | AE5: 17000 | AF5: 0 | AG5: 0 | AH5: 0 | AI5: 71897.42 | AJ5: 238000 | AK5: 12000
A6: BIZ-SAM | B6: 4 | C6: 46317 | D6: 46323 | E6: 71897.42 | F6: 4613.98 | G6: 0 | H6: 0 | I6: 0 | J6: 0 | K6: 0 | L6: 0 | M6: 4613.98 | N6: -8156.2 | O6: 0 | P6: 0 | Q6: 0 | R6: 0 | S6: 0 | T6: 0 | U6: 0 | V6: 0 | W6: 0 | X6: 0 | Y6: 0 | Z6: 0 | AA6: 0 | AB6: 0 | AC6: -8156.2 | AD6: -3542.22 | AE6: 0 | AF6: 0 | AG6: 0 | AH6: 0 | AI6: 68355.2 | AJ6: 238000 | AK6: 12000
A7: BIZ-SAM | B7: 5 | C7: 46324 | D7: 46330 | E7: 68355.2 | F7: 0 | G7: 0 | H7: 0 | I7: 0 | J7: 0 | K7: 0 | L7: 0 | M7: 0 | N7: 0 | O7: -2245.18 | P7: 0 | Q7: 0 | R7: 0 | S7: 0 | T7: 0 | U7: 0 | V7: 0 | W7: 0 | X7: 0 | Y7: -1463.63 | Z7: 0 | AA7: -4200 | AB7: 0 | AC7: -7908.81 | AD7: -7908.81 | AE7: 0 | AF7: -36000 | AG7: 0 | AH7: 0 | AI7: 24446.39 | AJ7: 202000 | AK7: 48000
A8: BIZ-SAM | B8: 6 | C8: 46331 | D8: 46337 | E8: 24446.39 | F8: 0 | G8: 0 | H8: 0 | I8: 0 | J8: 0 | K8: 0 | L8: 0 | M8: 0 | N8: 0 | O8: 0 | P8: 0 | Q8: 0 | R8: 0 | S8: 0 | T8: -5827.76 | U8: 0 | V8: 0 | W8: 0 | X8: 0 | Y8: 0 | Z8: 0 | AA8: 0 | AB8: 0 | AC8: -5827.76 | AD8: -5827.76 | AE8: 0 | AF8: 0 | AG8: 0 | AH8: 0 | AI8: 18618.63 | AJ8: 202000 | AK8: 48000
A9: BIZ-SAM | B9: 7 | C9: 46338 | D9: 46344 | E9: 18618.63 | F9: 0 | G9: 0 | H9: 0 | I9: 18601.93 | J9: 0 | K9: 0 | L9: 0 | M9: 18601.93 | N9: 0 | O9: -2011.71 | P9: -4648 | Q9: 0 | R9: 0 | S9: 0 | T9: -486.4 | U9: 0 | V9: 0 | W9: -226.63 | X9: -1732.49 | Y9: 0 | Z9: 0 | AA9: 0 | AB9: 0 | AC9: -9105.23 | AD9: 9496.7 | AE9: 0 | AF9: 0 | AG9: 0 | AH9: 0 | AI9: 28115.33 | AJ9: 202000 | AK9: 48000
A10: BIZ-SAM | B10: 8 | C10: 46345 | D10: 46351 | E10: 28115.33 | F10: 0 | G10: 0 | H10: 0 | I10: 19884.06 | J10: 0 | K10: 0 | L10: 0 | M10: 19884.06 | N10: 0 | O10: 0 | P10: -1883.52 | Q10: -941.76 | R10: 0 | S10: 0 | T10: -8238.55 | U10: 0 | V10: 0 | W10: -405.41 | X10: 0 | Y10: 0 | Z10: 0 | AA10: 0 | AB10: 0 | AC10: -11469.24 | AD10: 8414.82 | AE10: 0 | AF10: 0 | AG10: 0 | AH10: 0 | AI10: 36530.15 | AJ10: 202000 | AK10: 48000
A11: BIZ-SAM | B11: 9 | C11: 46352 | D11: 46358 | E11: 36530.15 | F11: 0 | G11: 0 | H11: 0 | I11: 23316.47 | J11: 0 | K11: 0 | L11: 0 | M11: 23316.47 | N11: 0 | O11: 0 | P11: 0 | Q11: 0 | R11: 0 | S11: 0 | T11: 0 | U11: 0 | V11: 0 | W11: 0 | X11: -31869.68 | Y11: -1245.21 | Z11: 0 | AA11: -4200 | AB11: 0 | AC11: -37314.89 | AD11: -13998.42 | AE11: 28000 | AF11: -30000 | AG11: 0 | AH11: 0 | AI11: 20531.73 | AJ11: 200000 | AK11: 50000
A12: BIZ-SAM | B12: 10 | C12: 46359 | D12: 46365 | E12: 20531.73 | F12: 0 | G12: 0 | H12: 0 | I12: 15833.32 | J12: 0 | K12: 0 | L12: 0 | M12: 15833.32 | N12: 0 | O12: 0 | P12: 0 | Q12: 0 | R12: 0 | S12: 0 | T12: -9538.47 | U12: 0 | V12: 0 | W12: 0 | X12: 0 | Y12: 0 | Z12: 0 | AA12: 0 | AB12: 0 | AC12: -9538.47 | AD12: 6294.85 | AE12: 0 | AF12: 0 | AG12: 0 | AH12: 0 | AI12: 26826.58 | AJ12: 200000 | AK12: 50000
A13: BIZ-SAM | B13: 11 | C13: 46366 | D13: 46372 | E13: 26826.58 | F13: 12843.25 | G13: 0 | H13: 0 | I13: 5636.95 | J13: 0 | K13: 0 | L13: 0 | M13: 18480.2 | N13: 0 | O13: -121.64 | P13: 0 | Q13: 0 | R13: 0 | S13: 0 | T13: -1327.15 | U13: 0 | V13: 0 | W13: -434.57 | X13: -1732.49 | Y13: 0 | Z13: 0 | AA13: 0 | AB13: 0 | AC13: -3615.85 | AD13: 14864.35 | AE13: 0 | AF13: 0 | AG13: 0 | AH13: 0 | AI13: 41690.93 | AJ13: 200000 | AK13: 50000
A14: BIZ-SAM | B14: 12 | C14: 46373 | D14: 46379 | E14: 41690.93 | F14: 0 | G14: 4803.84 | H14: 0 | I14: 27671.32 | J14: 0 | K14: 0 | L14: 0 | M14: 32475.16 | N14: 0 | O14: 0 | P14: -32450 | Q14: 0 | R14: 0 | S14: 0 | T14: 0 | U14: 0 | V14: -3758.55 | W14: -519.47 | X14: 0 | Y14: 0 | Z14: 0 | AA14: 0 | AB14: 0 | AC14: -36728.02 | AD14: -4252.86 | AE14: 0 | AF14: 0 | AG14: 0 | AH14: 0 | AI14: 37438.07 | AJ14: 200000 | AK14: 50000
A15: BIZ-SAM | B15: 13 | C15: 46380 | D15: 46386 | E15: 37438.07 | F15: 0 | G15: 0 | H15: 0 | I15: 9026.47 | J15: 0 | K15: 0 | L15: 0 | M15: 9026.47 | N15: 0 | O15: 0 | P15: 0 | Q15: 0 | R15: 0 | S15: 0 | T15: 0 | U15: 0 | V15: 0 | W15: 0 | X15: 0 | Y15: 0 | Z15: 0 | AA15: 0 | AB15: 0 | AC15: 0 | AD15: 9026.47 | AE15: 0 | AF15: 0 | AG15: 0 | AH15: 0 | AI15: 46464.54 | AJ15: 200000 | AK15: 50000

Sheet Cash_13_Week_Items
A1: business_id | B1: week | C1: week_start | D1: expected_date | E1: group | F1: account_code | G1: enterprise_id | H1: counterparty_id | I1: description | J1: amount | K1: source
A2: BIZ-SAM | B2: 1 | C2: 46296 | D2: 46297 | E2: Payment of AP/accruals outstanding at 9/30 | F2: 5150 | G2: ENT-SAM-CUS | H2: VEN-SAM-013 | I2: Pre-season combine service, sieves, belts, knife sections (corn) | J2: -6646.08 | K2: Open invoice/bill at 9/30
A3: BIZ-SAM | B3: 1 | C3: 46296 | D3: 46297 | E3: Payroll | F3: 5130 | G3: ENT-SAM-CUS | H3: VEN-SAM-017 | I3: Seasonal hand/truck driver (107 h) - custom 60% | J3: -1414.44 | K3: Operating plan (base case)
A4: BIZ-SAM | B4: 1 | C4: 46296 | D4: 46297 | E4: Payroll | F4: 5130 | G4: ENT-SAM-OVH | H4: VEN-SAM-017 | I4: Seasonal hand - own farm 40% | J4: -942.96 | K4: Operating plan (base case)
A5: BIZ-SAM | B5: 1 | C5: 46296 | D5: 46296 | E5: Owner distributions | F5: 8041 | G5: ENT-SAM-OVH | I5: Owner distribution - family living | J5: -4200 | K5: Operating plan (base case)
A6: BIZ-SAM | B6: 2 | C6: 46303 | D6: 46307 | E6: Other operating payments | F6: 6030 | G6: ENT-SAM-OVH | H6: VEN-SAM-016 | I6: Shop/bins electricity | J6: -289.1 | K6: Operating plan (base case)
A7: BIZ-SAM | B7: 3 | C7: 46310 | D7: 46314 | E7: Expected commodity sales | F7: 4010 | G7: ENT-SAM-SOY | H7: CUS-SAM-001 | I7: Soybeans - forward contract #FC-2611 3,488 bu @ $10.45 | J7: 36449.6 | K7: Operating plan (base case)
A8: BIZ-SAM | B8: 3 | C8: 46310 | D8: 46314 | E8: Government & insurance receipts | F8: 4210 | G8: ENT-SAM-OVH | H8: CUS-SAM-005 | I8: ARC/PLC - 2025 crop (wheat, corn, seed cotton PLC; new OBBBA reference prices) | J8: 14470 | K8: Operating plan (base case)
A9: BIZ-SAM | B9: 3 | C9: 46310 | D9: 46311 | E9: Payment of AP/accruals outstanding at 9/30 | F9: 5150 | G9: ENT-SAM-CUS | H9: VEN-SAM-013 | I9: Pre-season combine service, sieves, belts, knife sections (soybeans) | J9: -6246.24 | K9: Open invoice/bill at 9/30
A10: BIZ-SAM | B10: 3 | C10: 46310 | D10: 46310 | E10: Payment of AP/accruals outstanding at 9/30 | F10: 5131 | G10: ENT-SAM-CUS | H10: VEN-SAM-017 | I10: Employer payroll taxes | J10: -125.22 | K10: Open invoice/bill at 9/30
A11: BIZ-SAM | B11: 3 | C11: 46310 | D11: 46310 | E11: Payment of AP/accruals outstanding at 9/30 | F11: 5131 | G11: ENT-SAM-CUS | H11: VEN-SAM-017 | I11: Employer payroll taxes | J11: -219.38 | K11: Open invoice/bill at 9/30
A12: BIZ-SAM | B12: 3 | C12: 46310 | D12: 46311 | E12: Payroll | F12: 5130 | G12: ENT-SAM-CUS | H12: VEN-SAM-017 | I12: Seasonal hand/truck driver (116 h) - custom 60% | J12: -1529.92 | K12: Operating plan (base case)
A13: BIZ-SAM | B13: 3 | C13: 46310 | D13: 46311 | E13: Payroll | F13: 5130 | G13: ENT-SAM-OVH | H13: VEN-SAM-017 | I13: Seasonal hand - own farm 40% | J13: -1019.95 | K13: Operating plan (base case)
A14: BIZ-SAM | B14: 3 | C14: 46310 | D14: 46311 | E14: Scheduled debt payments | F14: 7020 | G14: ENT-SAM-CUS | H14: VEN-SAM-009 | I14: Interest - LN-SAM-004 payment 26/48 | J14: -224.14 | K14: Loan schedule
A15: BIZ-SAM | B15: 3 | C15: 46310 | D15: 46311 | E15: Scheduled debt payments | F15: 8011 | G15: ENT-SAM-CUS | H15: VEN-SAM-009 | I15: Principal - LN-SAM-004 payment 26/48 | J15: -1508.35 | K15: Loan schedule
A16: BIZ-SAM | B16: 3 | C16: 46310 | D16: 46311 | E16: Operating line draws | F16: 8020 | G16: ENT-SAM-OVH | H16: VEN-SAM-009 | I16: Draw on operating line (First Plains Bank) | J16: 17000 | K16: Operating plan (base case)
A17: BIZ-SAM | B17: 4 | C17: 46317 | D17: 46317 | E17: Payment of AP/accruals outstanding at 9/30 | F17: 5140 | G17: ENT-SAM-CORN | H17: VEN-SAM-001 | I17: Diesel - harvest & hauling Corn | J17: -936.32 | K17: Open invoice/bill at 9/30
... A19: BIZ-SAM | B19: 4 | C19: 46317 | D19: 46321 | E19: Collections - invoices outstanding at 9/30 | F19: 4020 | G19: ENT-SAM-COT | H19: CUS-SAM-002 | I19: 2025 cotton - pool progress/final (50,016 lb @ $0.615 est. pool price) | J19: 4613.98 | K19: Open invoice/bill at 9/30
A20: BIZ-SAM | B20: 4 | C20: 46317 | D20: 46317 | E20: Payment of AP/accruals outstanding at 9/30 | F20: 5180 | G20: ENT-SAM-CUS | I20: Header trailer/lowboy moves & permits (soybeans run) | J20: -2300 | K20: Open invoice/bill at 9/30
A21: BIZ-SAM | B21: 4 | C21: 46317 | D21: 46317 | E21: Payment of AP/accruals outstanding at 9/30 | F21: 5180 | G21: ENT-SAM-CUS | I21: Header trailer/lowboy moves & permits (corn run) | J21: -2300 | K21: Open invoice/bill at 9/30
A22: BIZ-SAM | B22: 4 | C22: 46317 | D22: 46317 | E22: Payment of AP/accruals outstanding at 9/30 | F22: 6100 | G22: ENT-SAM-OVH | I22: Phone, internet, farm software (Climate/FarmLogs) | J22: -165 | K22: Open invoice/bill at 9/30
A23: BIZ-SAM | B23: 4 | C23: 46317 | D23: 46317 | E23: Payment of AP/accruals outstanding at 9/30 | F23: 6050 | G23: ENT-SAM-OVH | I23: Pickup fuel & upkeep | J23: -362.08 | K23: Open invoice/bill at 9/30
A24: BIZ-SAM | B24: 5 | C24: 46324 | D24: 46325 | E24: Payroll | F24: 5130 | G24: ENT-SAM-CUS | H24: VEN-SAM-017 | I24: Seasonal hand/truck driver (102 h) - custom 60% | J24: -1347.11 | K24: Operating plan (base case)
A25: BIZ-SAM | B25: 5 | C25: 46324 | D25: 46325 | E25: Payroll | F25: 5130 | G25: ENT-SAM-OVH | H25: VEN-SAM-017 | I25: Seasonal hand - own farm 40% | J25: -898.07 | K25: Operating plan (base case)
A26: BIZ-SAM | B26: 5 | C26: 46324 | D26: 46327 | E26: Owner distributions | F26: 8041 | G26: ENT-SAM-OVH | I26: Owner distribution - family living | J26: -4200 | K26: Operating plan (base case)
A27: BIZ-SAM | B27: 5 | C27: 46324 | D27: 46326 | E27: Operating line interest | F27: 7021 | G27: ENT-SAM-OVH | H27: VEN-SAM-009 | I27: Operating line interest (7.50%) | J27: -1463.63 | K27: Operating plan (base case)
A28: BIZ-SAM | B28: 5 | C28: 46324 | D28: 46326 | E28: Operating line repayments | F28: 8021 | G28: ENT-SAM-OVH | H28: VEN-SAM-009 | I28: Repayment on operating line (First Plains Bank) | J28: -36000 | K28: Operating plan (base case)
A29: BIZ-SAM | B29: 6 | C29: 46331 | D29: 46337 | E29: Fuel, repairs & equipment expenses | F29: 5150 | G29: ENT-SAM-CORN | H29: VEN-SAM-001 | I29: Drying propane & electricity (7,840 bu) | J29: -352.8 | K29: Operating plan (base case)
A30: BIZ-SAM | B30: 6 | C30: 46331 | D30: 46332 | E30: Fuel, repairs & equipment expenses | F30: 5140 | G30: ENT-SAM-SOY | H30: VEN-SAM-001 | I30: Diesel - harvest & hauling Soybeans | J30: -1097.25 | K30: Operating plan (base case)
A31: BIZ-SAM | B31: 6 | C31: 46331 | D31: 46337 | E31: Fuel, repairs & equipment expenses | F31: 5150 | G31: ENT-SAM-SOY | H31: VEN-SAM-013 | I31: Machinery repairs/parts allocated - Soybeans | J31: -2452.5 | K31: Operating plan (base case)
A32: BIZ-SAM | B32: 6 | C32: 46331 | D32: 46331 | E32: Fuel, repairs & equipment expenses | F32: 5150 | G32: ENT-SAM-CUS | H32: VEN-SAM-013 | I32: Semi service, tires, DOT inspection | J32: -1925.21 | K32: Operating plan (base case)
A33: BIZ-SAM | B33: 7 | C33: 46338 | D33: 46339 | E33: Planned input purchases | F33: 5010 | G33: ENT-SAM-WHT | H33: VEN-SAM-001 | I33: Wheat seed (certified HRW) 80 ac | J33: -2464 | K33: Operating plan (base case)
A34: BIZ-SAM | B34: 7 | C34: 46338 | D34: 46339 | E34: Planned input purchases | F34: 5020 | G34: ENT-SAM-WHT | H34: VEN-SAM-001 | I34: Starter P (11-52-0) with drill | J34: -2184 | K34: Operating plan (base case)
A35: BIZ-SAM | B35: 7 | C35: 46338 | D35: 46339 | E35: Fuel, repairs & equipment expenses | F35: 5140 | G35: ENT-SAM-WHT | H35: VEN-SAM-001 | I35: Diesel - drilling wheat | J35: -486.4 | K35: Operating plan (base case)
A36: BIZ-SAM | B36: 7 | C36: 46338 | D36: 46342 | E36: Expected customer receipts | F36: 4090 | G36: ENT-SAM-CUS | H36: CUS-SAM-101 | I36: Custom combining soybeans 363 ac @ $44/ac - Heartland Land & Cattle | J36: 15972 | K36: Operating plan (base case)
A37: BIZ-SAM | B37: 7 | C37: 46338 | D37: 46342 | E37: Expected customer receipts | F37: 4091 | G37: ENT-SAM-CUS | H37: CUS-SAM-101 | I37: Custom hauling 12,524 bu @ $0.21/bu - Heartland Land & Cattle | J37: 2629.93 | K37: Operating plan (base case)
A38: BIZ-SAM | B38: 7 | C38: 46338 | D38: 46341 | E38: Payroll | F38: 5131 | G38: ENT-SAM-CUS | H38: VEN-SAM-017 | I38: Employer payroll taxes | J38: -207.45 | K38: Operating plan (base case)
... A53: BIZ-SAM | B53: 8 | C53: 46345 | D53: 46346 | E53: Expected customer receipts | F53: 4091 | G53: ENT-SAM-CUS | H53: CUS-SAM-105 | I53: Custom hauling 17,572 bu @ $0.21/bu - Lindquist Family Farms | J53: 3690.22 | K53: Operating plan (base case)
A54: BIZ-SAM | B54: 8 | C54: 46345 | D54: 46348 | E54: Other operating payments | F54: 6100 | G54: ENT-SAM-OVH | I54: Phone, internet, farm software (Climate/FarmLogs) | J54: -165 | K54: Operating plan (base case)
A55: BIZ-SAM | B55: 8 | C55: 46345 | D55: 46348 | E55: Other operating payments | F55: 6050 | G55: ENT-SAM-OVH | I55: Pickup fuel & upkeep | J55: -240.41 | K55: Operating plan (base case)
A56: BIZ-SAM | B56: 9 | C56: 46352 | D56: 46356 | E56: Expected customer receipts | F56: 4090 | G56: ENT-SAM-CUS | H56: CUS-SAM-103 | I56: Custom combining soybeans 196 ac @ $44/ac - Rudd Brothers Partnership | J56: 8624 | K56: Operating plan (base case)
A57: BIZ-SAM | B57: 9 | C57: 46352 | D57: 46356 | E57: Expected customer receipts | F57: 4091 | G57: ENT-SAM-CUS | H57: CUS-SAM-103 | I57: Custom hauling 6,762 bu @ $0.21/bu - Rudd Brothers Partnership | J57: 1420.02 | K57: Operating plan (base case)
A58: BIZ-SAM | B58: 9 | C58: 46352 | D58: 46356 | E58: Expected customer receipts | F58: 4090 | G58: ENT-SAM-CUS | H58: CUS-SAM-104 | I58: Custom combining soybeans 131 ac @ $44/ac - Gail Schrag | J58: 5764 | K58: Operating plan (base case)
A59: BIZ-SAM | B59: 9 | C59: 46352 | D59: 46356 | E59: Expected customer receipts | F59: 4091 | G59: ENT-SAM-CUS | H59: CUS-SAM-104 | I59: Custom hauling 4,520 bu @ $0.21/bu - Gail Schrag | J59: 949.09 | K59: Operating plan (base case)
A60: BIZ-SAM | B60: 9 | C60: 46352 | D60: 46353 | E60: Expected customer receipts | F60: 4090 | G60: ENT-SAM-CUS | H60: CUS-SAM-107 | I60: Custom combining soybeans 128 ac @ $44/ac - Dale & Jo Unruh | J60: 5632 | K60: Operating plan (base case)
A61: BIZ-SAM | B61: 9 | C61: 46352 | D61: 46353 | E61: Expected customer receipts | F61: 4091 | G61: ENT-SAM-CUS | H61: CUS-SAM-107 | I61: Custom hauling 4,416 bu @ $0.21/bu - Dale & Jo Unruh | J61: 927.36 | K61: Operating plan (base case)
A62: BIZ-SAM | B62: 9 | C62: 46352 | D62: 46357 | E62: Owner distributions | F62: 8041 | G62: ENT-SAM-OVH | I62: Owner distribution - family living | J62: -4200 | K62: Operating plan (base case)
A63: BIZ-SAM | B63: 9 | C63: 46352 | D63: 46357 | E63: Scheduled debt payments | F63: 7020 | G63: ENT-SAM-OVH | H63: VEN-SAM-007 | I63: Interest - LN-SAM-001 payment 8/20 | J63: -13547.55 | K63: Loan schedule
A64: BIZ-SAM | B64: 9 | C64: 46352 | D64: 46357 | E64: Scheduled debt payments | F64: 8011 | G64: ENT-SAM-OVH | H64: VEN-SAM-007 | I64: Principal - LN-SAM-001 payment 8/20 | J64: -18322.13 | K64: Loan schedule
A65: BIZ-SAM | B65: 9 | C65: 46352 | D65: 46356 | E65: Operating line interest | F65: 7021 | G65: ENT-SAM-OVH | H65: VEN-SAM-009 | I65: Operating line interest (7.50%) | J65: -1245.21 | K65: Operating plan (base case)
A66: BIZ-SAM | B66: 9 | C66: 46352 | D66: 46356 | E66: Operating line repayments | F66: 8021 | G66: ENT-SAM-OVH | H66: VEN-SAM-009 | I66: Repayment on operating line (First Plains Bank) | J66: -30000 | K66: Operating plan (base case)
A67: BIZ-SAM | B67: 9 | C67: 46352 | D67: 46357 | E67: Operating line draws | F67: 8020 | G67: ENT-SAM-OVH | H67: VEN-SAM-009 | I67: Draw on operating line (First Plains Bank) | J67: 28000 | K67: Operating plan (base case)
A68: BIZ-SAM | B68: 10 | C68: 46359 | D68: 46365 | E68: Expected customer receipts | F68: 4090 | G68: ENT-SAM-CUS | H68: CUS-SAM-104 | I68: Custom combining corn 120 ac @ $48/ac - Gail Schrag | J68: 5760 | K68: Operating plan (base case)
A69: BIZ-SAM | B69: 10 | C69: 46359 | D69: 46365 | E69: Expected customer receipts | F69: 4091 | G69: ENT-SAM-CUS | H69: CUS-SAM-104 | I69: Custom hauling 14,850 bu @ $0.21/bu - Gail Schrag | J69: 3118.5 | K69: Operating plan (base case)
A70: BIZ-SAM | B70: 10 | C70: 46359 | D70: 46363 | E70: Expected customer receipts | F70: 4090 | G70: ENT-SAM-CUS | H70: CUS-SAM-108 | I70: Custom combining corn 94 ac @ $48/ac - Smoky Hill Farms LLC | J70: 4512 | K70: Operating plan (base case)
A71: BIZ-SAM | B71: 10 | C71: 46359 | D71: 46363 | E71: Expected customer receipts | F71: 4091 | G71: ENT-SAM-CUS | H71: CUS-SAM-108 | I71: Custom hauling 11,632 bu @ $0.21/bu - Smoky Hill Farms LLC | J71: 2442.82 | K71: Operating plan (base case)
A72: BIZ-SAM | B72: 10 | C72: 46359 | D72: 46365 | E72: Fuel, repairs & equipment expenses | F72: 5140 | G72: ENT-SAM-CUS | H72: VEN-SAM-001 | I72: Diesel - custom combining corn (1,290 ac) | J72: -6617.7 | K72: Operating plan (base case)
A73: BIZ-SAM | B73: 10 | C73: 46359 | D73: 46365 | E73: Fuel, repairs & equipment expenses | F73: 5140 | G73: ENT-SAM-CUS | H73: VEN-SAM-001 | I73: Truck diesel - custom hauling (corn) | J73: -2920.77 | K73: Operating plan (base case)
A74: BIZ-SAM | B74: 11 | C74: 46366 | D74: 46371 | E74: Collections - invoices outstanding at 9/30 | F74: 4090 | G74: ENT-SAM-CUS | H74: CUS-SAM-103 | I74: Custom combining corn 179 ac @ $47/ac - Rudd Brothers Partnership | J74: 8413 | K74: Open invoice/bill at 9/30
... A87: BIZ-SAM | B87: 12 | C87: 46373 | D87: 46377 | E87: Expected customer receipts | F87: 4091 | G87: ENT-SAM-CUS | H87: CUS-SAM-101 | I87: Custom hauling 46,282 bu @ $0.21/bu - Heartland Land & Cattle | J87: 9719.32 | K87: Operating plan (base case)
A88: BIZ-SAM | B88: 12 | C88: 46373 | D88: 46378 | E88: Other operating payments | F88: 6100 | G88: ENT-SAM-OVH | I88: Phone, internet, farm software (Climate/FarmLogs) | J88: -165 | K88: Operating plan (base case)
A89: BIZ-SAM | B89: 12 | C89: 46373 | D89: 46378 | E89: Other operating payments | F89: 6050 | G89: ENT-SAM-OVH | I89: Pickup fuel & upkeep | J89: -354.47 | K89: Operating plan (base case)
A90: BIZ-SAM | B90: 12 | C90: 46373 | D90: 46376 | E90: Property & payroll taxes | F90: 6020 | G90: ENT-SAM-OVH | H90: VEN-SAM-014 | I90: 2026 KS property tax - 1st half | J90: -3758.55 | K90: Operating plan (base case)
A91: BIZ-SAM | B91: 13 | C91: 46380 | D91: 46380 | E91: Expected customer receipts | F91: 4090 | G91: ENT-SAM-CUS | H91: CUS-SAM-107 | I91: Custom combining corn 122 ac @ $48/ac - Dale & Jo Unruh | J91: 5856 | K91: Operating plan (base case)
A92: BIZ-SAM | B92: 13 | C92: 46380 | D92: 46380 | E92: Expected customer receipts | F92: 4091 | G92: ENT-SAM-CUS | H92: CUS-SAM-107 | I92: Custom hauling 15,098 bu @ $0.21/bu - Dale & Jo Unruh | J92: 3170.47 | K92: Operating plan (base case)

Sheet Scenario_Levers
A1: lever_id | B1: business_id | C1: decision_question | D1: driver | E1: base_value | F1: scenario_change | G1: estimated_annual_impact | H1: impact_unit | I1: calculation_basis
A2: LEV-SAM-01 | B2: BIZ-SAM | C2: What happens if cotton prices decline 15%? | D2: Cotton pool price (2026 crop) | E2: 0.82 | F2: -15% to $0.70 | G2: -5372.64 | H2: $ / yr | I2: 43,680 lb lint x $0.82 x 15%; downside forecast scenario also cuts yield to 300 lb/ac. Base vs downside 12-mo NFI: $72,263 vs $34,121
A3: LEV-SAM-02 | B3: BIZ-SAM | C3: Should Sam replace his combine? | D3: Combine annual cost (2025 repairs + note) | E3: 83610 | F3: Trade for ~1,200-hr S780 at $520k ($210k trade, $310k financed 7 yr @ 7.5%) | G3: 19081.94 | H3: $ / yr | I3: 2025 repairs $38,495 + current note $45,115 vs new payment $58,528 + ~$6,000 warranty-era repairs. Positive = replacing saves cash; also adds ~$30k/yr depreciation.
A4: LEV-SAM-03 | B4: BIZ-SAM | C4: Is custom harvesting more profitable than time on his own farm? | D4: Custom net income per separator hour (2025) | E4: 441 | F4: per hour | G4: 288.17 | H4: $ / separator hour | I4: Custom 2025 net $126,969 / 441 hrs; own KS crops earned $-9,233 operating income on 285 ac (~29 combine hrs).
A5: LEV-SAM-04 | B5: BIZ-SAM | C5: What happens if fertilizer prices rise 20%? | D5: Fertilizer spend (2025) | E5: 28491 | F5: +20% | G5: -5698.24 | H5: $ / yr | I5: 2025 fertilizer & lime (5020) x 20%
A6: LEV-SAM-05 | B6: BIZ-SAM | C6: How bad is a downside year (low prices + weak yields)? | D6: 12-month NFI (Oct-26 to Sep-27) | E6: 72263.4 | F6: Downside scenario | G6: -38142.14 | H6: $ / yr | I6: forecast_12_month Base vs Downside

Sheet Unit_Econ_Crops
A1: business_id | B1: crop_season_id | C1: enterprise_id | D1: crop | E1: crop_year | F1: acres | G1: yield_per_acre | H1: yield_unit | I1: avg_price | J1: revenue_total | K1: revenue_per_acre | L1: of_which_unsold_inventory_value | M1: insurance_govt_per_acre | N1: seed_per_acre | O1: fertilizer_per_acre | P1: chemical_per_acre | Q1: fuel_per_acre | R1: contractor_per_acre | S1: irrigation_per_acre | T1: repairs_per_acre | U1: crop_insurance_per_acre | V1: other_direct_per_acre | W1: direct_cost_per_acre | X1: allocated_depreciation_per_acre | Y1: allocated_shared_cost_per_acre | Z1: total_cost_per_acre | AA1: profit_per_acre | AB1: break_even_yield | AC1: break_even_price | AD1: data_type
A2: BIZ-SAM | B2: CS-SAM-W23-D1 | C2: ENT-SAM-WHT | D2: Wheat | E2: 2023 | F2: 80 | G2: 31 | H2: bu/ac | I2: 7.42 | J2: 18411.52 | K2: 230.14 | L2: 0 | M2: 0 | N2: 0 | O2: 51.2 | P2: 14 | Q2: 8.26 | R2: 0 | S2: 0 | T2: 16 | U2: 18 | V2: 0 | W2: 107.46 | X2: 86.5 | Y2: 0 | Z2: 193.95 | AA2: 36.19 | AB2: 26.14 | AC2: 6.2565 | AD2: Actual
A3: BIZ-SAM | B3: CS-SAM-C23-D2 | C3: ENT-SAM-CORN | D3: Corn | E3: 2023 | F3: 80 | G3: 74 | H3: bu/ac | I3: 4.72 | J3: 27942.4 | K3: 349.28 | L3: 0 | M3: 0 | N3: 78 | O3: 101.2 | P3: 50 | Q3: 22.12 | R3: 0 | S3: 0 | T3: 27.33 | U3: 22 | V3: 0 | W3: 300.65 | X3: 90.47 | Y3: 0 | Z3: 391.12 | AA3: -41.84 | AB3: 82.87 | AC3: 5.2854 | AD3: Actual
A4: BIZ-SAM | B4: CS-SAM-C23-P1 | C4: ENT-SAM-CORN | D4: Corn | E4: 2023 | F4: 125 | G4: 207 | H4: bu/ac | I4: 4.41 | J4: 113992.31 | K4: 911.94 | L4: 0 | M4: 0 | N4: 116 | O4: 210.1 | P4: 86 | Q4: 22.12 | R4: 0 | S4: 141 | T4: 33.32 | U4: 28 | V4: 0 | W4: 636.54 | X4: 90.47 | Y4: 0 | Z4: 727.01 | AA4: 184.93 | AB4: 164.85 | AC4: 3.5121 | AD4: Actual
A5: BIZ-SAM | B5: CS-SAM-W24-D2 | C5: ENT-SAM-WHT | D5: Wheat | E5: 2024 | F5: 80 | G5: 46 | H5: bu/ac | I5: 5.41 | J5: 19894.08 | K5: 248.68 | L5: 0 | M5: 0 | N5: 28.7 | O5: 64.7 | P5: 14.35 | Q5: 13.74 | R5: 0 | S5: 0 | T5: 16.48 | U5: 18 | V5: 0 | W5: 155.97 | X5: 88.15 | Y5: 0 | Z5: 244.12 | AA5: 4.56 | AB5: 45.12 | AC5: 5.3069 | AD5: Actual
A6: BIZ-SAM | B6: CS-SAM-S24-P1 | C6: ENT-SAM-SOY | D6: Soybeans | E6: 2024 | F6: 125 | G6: 64 | H6: bu/ac | I6: 9.83 | J6: 78640 | K6: 629.12 | L6: 0 | M6: 0 | N6: 71.75 | O6: 28.5 | P6: 71.75 | Q6: 14.91 | R6: 0 | S6: 63.92 | T6: 18.54 | U6: 14 | V6: 0 | W6: 283.37 | X6: 57.34 | Y6: 0 | Z6: 340.71 | AA6: 288.41 | AB6: 34.66 | AC6: 5.3236 | AD6: Actual
A7: BIZ-SAM | B7: CS-SAM-S24-D1 | C7: ENT-SAM-SOY | D7: Soybeans | E7: 2024 | F7: 80 | G7: 36 | H7: bu/ac | I7: 9.73 | J7: 28022.4 | K7: 350.28 | L7: 0 | M7: 0 | N7: 59.45 | O7: 0 | P7: 46.12 | Q7: 14.91 | R7: 0 | S7: 0 | T7: 18.54 | U7: 12 | V7: 0 | W7: 151.03 | X7: 57.34 | Y7: 0 | Z7: 208.37 | AA7: 141.91 | AB7: 21.42 | AC7: 5.788 | AD7: Actual
A8: BIZ-SAM | B8: CS-SAM-W25-D1 | C8: ENT-SAM-WHT | D8: Wheat | E8: 2025 | F8: 80 | G8: 53 | H8: bu/ac | I8: 5.03 | J8: 21306 | K8: 266.32 | L8: 0 | M8: 0 | N8: 29.4 | O8: 63.6 | P8: 33.2 | Q8: 12.79 | R8: 0 | S8: 0 | T8: 16.96 | U8: 18 | V8: 0 | W8: 173.95 | X8: 91.94 | Y8: 0 | Z8: 265.89 | AA8: 0.44 | AB8: 52.86 | AC8: 5.0167 | AD8: Actual
A9: BIZ-SAM | B9: CS-SAM-C25-P1 | C9: ENT-SAM-CORN | D9: Corn | E9: 2025 | F9: 125 | G9: 231 | H9: bu/ac | I9: 4.12 | J9: 119037.14 | K9: 952.3 | L9: 4.12 | M9: 0 | N9: 121.8 | O9: 158.4 | P9: 90.3 | Q9: 19.04 | R9: 0 | S9: 112.8 | T9: 35.84 | U9: 28 | V9: 0 | W9: 566.18 | X9: 161.44 | Y9: 0 | Z9: 727.62 | AA9: 224.68 | AB9: 176.61 | AC9: 3.1499 | AD9: Actual
A10: BIZ-SAM | B10: CS-SAM-S25-D2 | C10: ENT-SAM-SOY | D10: Soybeans | E10: 2025 | F10: 80 | G10: 42 | H10: bu/ac | I10: 10.18 | J10: 34188 | K10: 427.35 | L10: 0 | M10: 0 | N10: 60.9 | O10: 0 | P10: 47.25 | Q10: 14.28 | R10: 0 | S10: 0 | T10: 19.08 | U10: 12 | V10: 0 | W10: 153.51 | X10: 159.8 | Y10: 0 | Z10: 313.31 | AA10: 114.04 | AB10: 30.78 | AC10: 7.4598 | AD10: Actual
A11: BIZ-SAM | B11: CS-SAM-W26-D2 | C11: ENT-SAM-WHT | D11: Wheat | E11: 2026 | F11: 80 | G11: 36 | H11: bu/ac | I11: 5.68 | J11: 16355.52 | K11: 204.44 | L11: 0 | M11: 0 | N11: 30.1 | O11: 77.68 | P11: 15.05 | Q11: 13.38 | R11: 0 | S11: 0 | T11: 17.44 | U11: 18 | V11: 0 | W11: 171.65 | X11: 92.24 | Y11: 0 | Z11: 263.89 | AA11: -59.44 | AB11: 46.46 | AC11: 7.3302 | AD11: Actual harvest; stored grain unsold
A12: BIZ-SAM | B12: CS-SAM-C26-D1 | C12: ENT-SAM-CORN | D12: Corn | E12: 2026 | F12: 80 | G12: 98 | H12: bu/ac | I12: 4.05 | J12: 31752 | K12: 396.9 | L12: 0 | M12: 0 | N12: 83.85 | O12: 98.44 | P12: 53.75 | Q12: 21.28 | R12: 0 | S12: 0 | T12: 30.57 | U12: 22 | V12: 0 | W12: 309.89 | X12: 253.95 | Y12: 0 | Z12: 563.84 | AA12: -166.94 | AB12: 139.22 | AC12: 5.7535 | AD12: Actual
A13: BIZ-SAM | B13: CS-SAM-S26-P1 | C13: ENT-SAM-SOY | D13: Soybeans | E13: 2026 | F13: 125 | G13: 62 | H13: bu/ac | I13: 10.36 | J13: 80305.58 | K13: 642.44 | L13: 0 | M13: 0 | N13: 75.25 | O13: 32.4 | P13: 75.25 | Q13: 15.96 | R13: 0 | S13: 82.72 | T13: 19.62 | U13: 14 | V13: 0 | W13: 315.2 | X13: 103.62 | Y13: 0 | Z13: 418.82 | AA13: 223.62 | AB13: 40.43 | AC13: 6.7552 | AD13: Forecast
... A18: BIZ-SAM | B18: CS-SAM-COT26 | C18: ENT-SAM-COT | D18: Cotton (dryland) | E18: 2026 | F18: 96 | G18: 455 | H18: lb lint/ac | I18: 0.82 | J18: 42950.54 | K18: 447.4 | L18: 0 | M18: 0 | N18: 89.38 | O18: 43.16 | P18: 93.74 | Q18: 0 | R18: 252.16 | S18: 0 | T18: 0 | U18: 15.8 | V18: 0 | W18: 494.24 | X18: 0 | Y18: 0 | Z18: 494.24 | AA18: -46.84 | AB18: 602.73 | AC18: 1.0862 | AD18: Forecast

Sheet Transactions
A1: txn_id | B1: business_id | C1: txn_date | D1: cash_date | E1: expected_cash_date | F1: period | G1: enterprise_id | H1: account_code | I1: account_name | J1: section | K1: statement_line | L1: description | M1: counterparty_id | N1: quantity | O1: unit | P1: unit_price | Q1: amount | R1: cash_effect | S1: payment_method | T1: invoice_id | U1: bill_id | V1: due_date | W1: asset_id | X1: loan_id | Y1: crop_season_id | Z1: animal_id | AA1: txn_year (formula)
A2: TXN-SAM-000001 | B2: BIZ-SAM | C2: 44914 | D2: 44939 | F2: Prior period (opening balance item) | G2: ENT-SAM-COT | H2: 4020 | I2: Cotton lint sales | J2: REV | K2: Crop sales | L2: 2022 cotton - pool payment (37,920 lb lint @ $0.790) | M2: CUS-SAM-002 | Q2: 16476.24 | R2: 16476.24 | S2: ACH | T2: POOL-SAM-2022 | V2: 44939 | AA2: =YEAR(C2) -> 2022
A3: TXN-SAM-000002 | B3: BIZ-SAM | C3: 44914 | D3: 45030 | F3: Prior period (opening balance item) | G3: ENT-SAM-COT | H3: 4020 | I3: Cotton lint sales | J3: REV | K3: Crop sales | L3: 2022 cotton - pool payment (37,920 lb lint @ $0.790) | M3: CUS-SAM-002 | Q3: 4493.52 | R3: 4493.52 | S3: ACH | T3: POOL-SAM-2022 | V3: 45030 | AA3: =YEAR(C3) -> 2022
A4: TXN-SAM-000003 | B4: BIZ-SAM | C4: 44914 | D4: 45121 | F4: Prior period (opening balance item) | G4: ENT-SAM-COT | H4: 4020 | I4: Cotton lint sales | J4: REV | K4: Crop sales | L4: 2022 cotton - pool payment (37,920 lb lint @ $0.790) | M4: CUS-SAM-002 | Q4: 4493.52 | R4: 4493.52 | S4: ACH | T4: POOL-SAM-2022 | V4: 45121 | AA4: =YEAR(C4) -> 2022
A5: TXN-SAM-000004 | B5: BIZ-SAM | C5: 44914 | D5: 45226 | F5: Prior period (opening balance item) | G5: ENT-SAM-COT | H5: 4020 | I5: Cotton lint sales | J5: REV | K5: Crop sales | L5: 2022 cotton - pool payment (37,920 lb lint @ $0.790) | M5: CUS-SAM-002 | Q5: 4493.52 | R5: 4493.52 | S5: ACH | T5: POOL-SAM-2022 | V5: 45226 | AA5: =YEAR(C5) -> 2022
A6: TXN-SAM-000005 | B6: BIZ-SAM | C6: 44915 | D6: 44945 | F6: Prior period (opening balance item) | G6: ENT-SAM-OVH | H6: 5140 | I6: Fuel & oil | J6: COP | K6: Fuel | L6: Bulk diesel delivery Dec 2022 | M6: VEN-SAM-001 | Q6: 3184.55 | R6: -3184.55 | S6: Vendor account | U6: BILL-SAM-00001 | V6: 44945 | AA6: =YEAR(C6) -> 2022
A7: TXN-SAM-000006 | B7: BIZ-SAM | C7: 44926 | D7: 44953 | F7: Prior period (opening balance item) | G7: ENT-SAM-COT | H7: 6020 | I7: Property taxes | J7: OVH | K7: Property taxes | L7: 2022 Carson Co. TX property tax | M7: VEN-SAM-015 | Q7: 431.2 | R7: -431.2 | S7: Check | AA7: =YEAR(C7) -> 2022
A8: TXN-SAM-000007 | B8: BIZ-SAM | C8: 44926 | D8: 45056 | F8: Prior period (opening balance item) | G8: ENT-SAM-OVH | H8: 6020 | I8: Property taxes | J8: OVH | K8: Property taxes | L8: 2022 KS property tax - 2nd half (due May 10) | M8: VEN-SAM-014 | Q8: 3390.12 | R8: -3390.12 | S8: Check | AA8: =YEAR(C8) -> 2022
A9: TXN-SAM-000008 | B9: BIZ-SAM | C9: 44927 | D9: 44927 | F9: Current | G9: ENT-SAM-OVH | H9: 8041 | I9: Owner distributions / family living | J9: CASHBS | K9: Owner | L9: Owner distribution - family living | Q9: 4000 | R9: -4000 | S9: Transfer | AA9: =YEAR(C9) -> 2023
A10: TXN-SAM-000009 | B10: BIZ-SAM | C10: 44934 | D10: 44979 | F10: Current | G10: ENT-SAM-OVH | H10: 6100 | I10: Office, phone & software | J10: OVH | K10: Professional & admin | L10: Phone, internet, farm software (Climate/FarmLogs) | Q10: 165 | R10: -165 | S10: Credit card | AA10: =YEAR(C10) -> 2023
A11: TXN-SAM-000010 | B11: BIZ-SAM | C11: 44936 | D11: 44936 | F11: Current | G11: ENT-SAM-OVH | H11: 7020 | I11: Interest - term debt | J11: INT | K11: Interest | L11: Interest - LN-SAM-005 payment 19/60 | M11: VEN-SAM-010 | Q11: 107.66 | R11: -107.66 | S11: ACH | X11: LN-SAM-005 | AA11: =YEAR(C11) -> 2023
A12: TXN-SAM-000011 | B12: BIZ-SAM | C12: 44936 | D12: 44936 | F12: Current | G12: ENT-SAM-OVH | H12: 8011 | I12: Term loan principal payments | J12: CASHBS | K12: Financing | L12: Principal - LN-SAM-005 payment 19/60 | M12: VEN-SAM-010 | Q12: 737.43 | R12: -737.43 | S12: ACH | X12: LN-SAM-005 | AA12: =YEAR(C12) -> 2023
A13: TXN-SAM-000012 | B13: BIZ-SAM | C13: 44938 | D13: 44938 | F13: Current | G13: ENT-SAM-OVH | H13: 6030 | I13: Utilities | J13: OVH | K13: Utilities | L13: Shop/bins electricity | M13: VEN-SAM-016 | Q13: 395.26 | R13: -395.26 | S13: Auto-draft | AA13: =YEAR(C13) -> 2023
A14: TXN-SAM-000013 | B14: BIZ-SAM | C14: 44940 | D14: 44940 | F14: Current | G14: ENT-SAM-CUS | H14: 7020 | I14: Interest - term debt | J14: INT | K14: Interest | L14: Interest - LN-SAM-002 payment 1/7 | M14: VEN-SAM-008 | Q14: 12838 | R14: -12838 | S14: ACH | X14: LN-SAM-002 | AA14: =YEAR(C14) -> 2023
A15: TXN-SAM-000014 | B15: BIZ-SAM | C15: 44940 | D15: 44940 | F15: Current | G15: ENT-SAM-CUS | H15: 8011 | I15: Term loan principal payments | J15: CASHBS | K15: Financing | L15: Principal - LN-SAM-002 payment 1/7 | M15: VEN-SAM-008 | Q15: 32276.84 | R15: -32276.84 | S15: ACH | X15: LN-SAM-002 | AA15: =YEAR(C15) -> 2023
A16: TXN-SAM-000015 | B16: BIZ-SAM | C16: 44940 | D16: 44940 | F16: Current | G16: ENT-SAM-OVH | H16: 8020 | I16: Operating line draws | J16: CASHBS | K16: Financing | L16: Draw on operating line (First Plains Bank) | M16: VEN-SAM-009 | Q16: 16000 | R16: 16000 | S16: Line transfer | X16: LOC-SAM-001 | AA16: =YEAR(C16) -> 2023
A17: TXN-SAM-000016 | B17: BIZ-SAM | C17: 44941 | D17: 44941 | F17: Current | G17: ENT-SAM-OVH | H17: 8042 | I17: Owner estimated income-tax payments | J17: CASHBS | K17: Owner | L17: Owner estimated income-tax payment | Q17: 3000 | R17: -3000 | S17: EFTPS | AA17: =YEAR(C17) -> 2023
A18: TXN-SAM-000017 | B18: BIZ-SAM | C18: 44944 | D18: 44944 | F18: Current | G18: ENT-SAM-CUS | H18: 6010 | I18: Insurance - property & liability | J18: OVH | K18: Insurance | L18: Commercial auto (trucks) + custom-harvest liability | M18: VEN-SAM-012 | Q18: 3900 | R18: -3900 | S18: Check | AA18: =YEAR(C18) -> 2023
A19: TXN-SAM-000018 | B19: BIZ-SAM | C19: 44944 | D19: 44944 | F19: Current | G19: ENT-SAM-OVH | H19: 6010 | I19: Insurance - property & liability | J19: OVH | K19: Insurance | L19: Farm package: inland marine (machinery), buildings, liability | M19: VEN-SAM-012 | Q19: 7880 | R19: -7880 | S19: Check | AA19: =YEAR(C19) -> 2023
A20: TXN-SAM-000019 | B20: BIZ-SAM | C20: 44944 | D20: 44944 | F20: Current | G20: ENT-SAM-OVH | H20: 8020 | I20: Operating line draws | J20: CASHBS | K20: Financing | L20: Draw on operating line (First Plains Bank) | M20: VEN-SAM-009 | Q20: 15000 | R20: 15000 | S20: Line transfer | X20: LOC-SAM-001 | AA20: =YEAR(C20) -> 2023
A21: TXN-SAM-000020 | B21: BIZ-SAM | C21: 44944 | D21: 44949 | F21: Current | G21: ENT-SAM-SOY | H21: 4010 | I21: Grain sales | J21: REV | K21: Crop sales | L21: 2022 soybeans from bin - 3,800 bu @ $14.38 | M21: CUS-SAM-001 | N21: 3800 | O21: bu | P21: 14.38 | Q21: 54644 | R21: 54644 | S21: Check | AA21: =YEAR(C21) -> 2023
A22: TXN-SAM-000021 | B22: BIZ-SAM | C22: 44946 | D22: 44980 | F22: Current | G22: ENT-SAM-COT | H22: 5050 | I22: Custom hire - field operations | J22: COP | K22: Contractors & custom hire | L22: Shred stalks (96 ac) | M22: VEN-SAM-003 | N22: 96 | O22: ac | P22: 14 | Q22: 1344 | R22: -1344 | S22: Vendor account | U22: BILL-SAM-00117 | V22: 44976 | Y22: CS-SAM-COT23 | AA22: =YEAR(C22) -> 2023
A23: TXN-SAM-000022 | B23: BIZ-SAM | C23: 44952 | D23: 44952 | F23: Current | G23: ENT-SAM-CUS | H23: 6090 | I23: Dues, licenses & subscriptions | J23: OVH | K23: Professional & admin | L23: Truck registration, IFTA, DOT | M23: VEN-SAM-021 | Q23: 640 | R23: -640 | S23: Check | AA23: =YEAR(C23) -> 2023
A24: TXN-SAM-000023 | B24: BIZ-SAM | C24: 44952 | D24: 44979 | F24: Current | G24: ENT-SAM-OVH | H24: 6050 | I24: Vehicle expense | J24: OVH | K24: Vehicles | L24: Pickup fuel & upkeep | Q24: 284.74 | R24: -284.74 | S24: Credit card | AA24: =YEAR(C24) -> 2023
A25: TXN-SAM-000024 | B25: BIZ-SAM | C25: 44957 | D25: 44957 | F25: Current | G25: ENT-SAM-OVH | H25: 7021 | I25: Interest - operating line | J25: INT | K25: Interest | L25: Operating line interest (8.50%) | M25: VEN-SAM-009 | Q25: 621.32 | R25: -621.32 | S25: Auto-draft | X25: LOC-SAM-001 | AA25: =YEAR(C25) -> 2023
A26: TXN-SAM-000025 | B26: BIZ-SAM | C26: 44957 | D26: 44957 | F26: Current | G26: ENT-SAM-OVH | H26: 8021 | I26: Operating line repayments | J26: CASHBS | K26: Financing | L26: Repayment on operating line (First Plains Bank) | M26: VEN-SAM-009 | Q26: 42000 | R26: -42000 | S26: Line transfer | X26: LOC-SAM-001 | AA26: =YEAR(C26) -> 2023
A27: TXN-SAM-000026 | B27: BIZ-SAM | C27: 44958 | D27: 44958 | F27: Current | G27: ENT-SAM-OVH | H27: 8041 | I27: Owner distributions / family living | J27: CASHBS | K27: Owner | L27: Owner distribution - family living | Q27: 4000 | R27: -4000 | S27: Transfer | AA27: =YEAR(C27) -> 2023
A28: TXN-SAM-000027 | B28: BIZ-SAM | C28: 44965 | D28: 45007 | F28: Current | G28: ENT-SAM-OVH | H28: 6100 | I28: Office, phone & software | J28: OVH | K28: Professional & admin | L28: Phone, internet, farm software (Climate/FarmLogs) | Q28: 165 | R28: -165 | S28: Credit card | AA28: =YEAR(C28) -> 2023
A29: TXN-SAM-000028 | B29: BIZ-SAM | C29: 44967 | D29: 44967 | F29: Current | G29: ENT-SAM-OVH | H29: 7020 | I29: Interest - term debt | J29: INT | K29: Interest | L29: Interest - LN-SAM-005 payment 20/60 | M29: VEN-SAM-010 | Q29: 105.27 | R29: -105.27 | S29: ACH | X29: LN-SAM-005 | AA29: =YEAR(C29) -> 2023
A30: TXN-SAM-000029 | B30: BIZ-SAM | C30: 44967 | D30: 44967 | F30: Current | G30: ENT-SAM-OVH | H30: 8011 | I30: Term loan principal payments | J30: CASHBS | K30: Financing | L30: Principal - LN-SAM-005 payment 20/60 | M30: VEN-SAM-010 | Q30: 739.82 | R30: -739.82 | S30: ACH | X30: LN-SAM-005 | AA30: =YEAR(C30) -> 2023
A31: TXN-SAM-000030 | B31: BIZ-SAM | C31: 44969 | D31: 44969 | F31: Current | G31: ENT-SAM-OVH | H31: 6030 | I31: Utilities | J31: OVH | K31: Utilities | L31: Shop/bins electricity | M31: VEN-SAM-016 | Q31: 433 | R31: -433 | S31: Auto-draft | AA31: =YEAR(C31) -> 2023
A32: TXN-SAM-000031 | B32: BIZ-SAM | C32: 44983 | D32: 45007 | F32: Current | G32: ENT-SAM-OVH | H32: 6050 | I32: Vehicle expense | J32: OVH | K32: Vehicles | L32: Pickup fuel & upkeep | Q32: 389.28 | R32: -389.28 | S32: Credit card | AA32: =YEAR(C32) -> 2023
A33: TXN-SAM-000032 | B33: BIZ-SAM | C33: 44984 | D33: 44984 | F33: Current | G33: ENT-SAM-OVH | H33: 6080 | I33: Professional fees | J33: OVH | K33: Professional & admin | L33: Accounting, tax return & payroll filings | M33: VEN-SAM-019 | Q33: 3400 | R33: -3400 | S33: Check | AA33: =YEAR(C33) -> 2023
A34: TXN-SAM-000033 | B34: BIZ-SAM | C34: 44985 | D34: 44985 | F34: Current | G34: ENT-SAM-OVH | H34: 7021 | I34: Interest - operating line | J34: INT | K34: Interest | L34: Operating line interest (8.75%) | M34: VEN-SAM-009 | Q34: 396.03 | R34: -396.03 | S34: Auto-draft | X34: LOC-SAM-001 | AA34: =YEAR(C34) -> 2023
A35: TXN-SAM-000034 | B35: BIZ-SAM | C35: 44986 | D35: 44986 | F35: Current | G35: ENT-SAM-OVH | H35: 8041 | I35: Owner distributions / family living | J35: CASHBS | K35: Owner | L35: Owner distribution - family living | Q35: 4000 | R35: -4000 | S35: Transfer | AA35: =YEAR(C35) -> 2023
A36: TXN-SAM-000035 | B36: BIZ-SAM | C36: 44987 | D36: 45019 | F36: Current | G36: ENT-SAM-WHT | H36: 5020 | I36: Fertilizer & lime | J36: COP | K36: Fertilizer | L36: Topdress N (UAN 80 lb) - custom applied | M36: VEN-SAM-001 | Q36: 4096 | R36: -4096 | S36: Vendor account | U36: BILL-SAM-00002 | V36: 45017 | Y36: CS-SAM-W23-D1 | AA36: =YEAR(C36) -> 2023
A37: TXN-SAM-000036 | B37: BIZ-SAM | C37: 44991 | D37: 45026 | F37: Current | G37: ENT-SAM-COT | H37: 5050 | I37: Custom hire - field operations | J37: COP | K37: Contractors & custom hire | L37: Disk & list beds (96 ac) | M37: VEN-SAM-003 | N37: 96 | O37: ac | P37: 24 | Q37: 2304 | R37: -2304 | S37: Vendor account | U37: BILL-SAM-00118 | V37: 45021 | Y37: CS-SAM-COT23 | AA37: =YEAR(C37) -> 2023
A38: TXN-SAM-000037 | B38: BIZ-SAM | C38: 44993 | D38: 45038 | F38: Current | G38: ENT-SAM-OVH | H38: 6100 | I38: Office, phone & software | J38: OVH | K38: Professional & admin | L38: Phone, internet, farm software (Climate/FarmLogs) | Q38: 165 | R38: -165 | S38: Credit card | AA38: =YEAR(C38) -> 2023
A39: TXN-SAM-000038 | B39: BIZ-SAM | C39: 44995 | D39: 44995 | F39: Current | G39: ENT-SAM-OVH | H39: 7020 | I39: Interest - term debt | J39: INT | K39: Interest | L39: Interest - LN-SAM-005 payment 21/60 | M39: VEN-SAM-010 | Q39: 102.86 | R39: -102.86 | S39: ACH | X39: LN-SAM-005 | AA39: =YEAR(C39) -> 2023
A40: TXN-SAM-000039 | B40: BIZ-SAM | C40: 44995 | D40: 44995 | F40: Current | G40: ENT-SAM-OVH | H40: 8011 | I40: Term loan principal payments | J40: CASHBS | K40: Financing | L40: Principal - LN-SAM-005 payment 21/60 | M40: VEN-SAM-010 | Q40: 742.23 | R40: -742.23 | S40: ACH | X40: LN-SAM-005 | AA40: =YEAR(C40) -> 2023
A41: TXN-SAM-000040 | B41: BIZ-SAM | C41: 44997 | D41: 44997 | F41: Current | G41: ENT-SAM-OVH | H41: 6030 | I41: Utilities | J41: OVH | K41: Utilities | L41: Shop/bins electricity | M41: VEN-SAM-016 | Q41: 271.38 | R41: -271.38 | S41: Auto-draft | AA41: =YEAR(C41) -> 2023
A42: TXN-SAM-000041 | B42: BIZ-SAM | C42: 44999 | D42: 45029 | F42: Current | G42: ENT-SAM-OVH | H42: 5150 | I42: Repairs - machinery & equipment | J42: COP | K42: Repairs & maintenance | L42: Shop supplies, filters, tires | M42: VEN-SAM-013 | Q42: 1290.98 | R42: -1290.98 | S42: Vendor account | U42: BILL-SAM-00244 | V42: 45029 | AA42: =YEAR(C42) -> 2023
A43: TXN-SAM-000042 | B43: BIZ-SAM | C43: 45000 | D43: 45000 | F43: Current | G43: ENT-SAM-WHT | H43: 5040 | I43: Crop insurance premiums | J43: COP | K43: Crop insurance | L43: Crop insurance premium - wheat RP 75% | M43: VEN-SAM-011 | Q43: 1440 | R43: -1440 | S43: Check | Y43: CS-SAM-W23-D1 | AA43: =YEAR(C43) -> 2023
A44: TXN-SAM-000043 | B44: BIZ-SAM | C44: 45000 | D44: 45000 | F44: Current | G44: ENT-SAM-CORN | H44: 5040 | I44: Crop insurance premiums | J44: COP | K44: Crop insurance | L44: Crop insurance - Corn RP 75% | M44: VEN-SAM-011 | Q44: 1760 | R44: -1760 | S44: Check | Y44: CS-SAM-C23-D2 | AA44: =YEAR(C44) -> 2023
A45: TXN-SAM-000044 | B45: BIZ-SAM | C45: 45000 | D45: 45000 | F45: Current | G45: ENT-SAM-CORN | H45: 5040 | I45: Crop insurance premiums | J45: COP | K45: Crop insurance | L45: Crop insurance - Corn RP 75% | M45: VEN-SAM-011 | Q45: 3500 | R45: -3500 | S45: Check | Y45: CS-SAM-C23-P1 | AA45: =YEAR(C45) -> 2023
A46: TXN-SAM-000045 | B46: BIZ-SAM | C46: 45000 | D46: 45000 | F46: Current | G46: ENT-SAM-OVH | H46: 8020 | I46: Operating line draws | J46: CASHBS | K46: Financing | L46: Draw on operating line (First Plains Bank) | M46: VEN-SAM-009 | Q46: 14000 | R46: 14000 | S46: Line transfer | X46: LOC-SAM-001 | AA46: =YEAR(C46) -> 2023
A47: TXN-SAM-000046 | B47: BIZ-SAM | C47: 45011 | D47: 45038 | F47: Current | G47: ENT-SAM-OVH | H47: 6050 | I47: Vehicle expense | J47: OVH | K47: Vehicles | L47: Pickup fuel & upkeep | Q47: 355.59 | R47: -355.59 | S47: Credit card | AA47: =YEAR(C47) -> 2023
A48: TXN-SAM-000047 | B48: BIZ-SAM | C48: 45013 | D48: 45043 | F48: Current | G48: ENT-SAM-WHT | H48: 5030 | I48: Chemicals | J48: COP | K48: Chemicals | L48: Wheat herbicide (spring) | M48: VEN-SAM-001 | Q48: 1120 | R48: -1120 | S48: Vendor account | U48: BILL-SAM-00003 | V48: 45043 | Y48: CS-SAM-W23-D1 | AA48: =YEAR(C48) -> 2023
A49: TXN-SAM-000048 | B49: BIZ-SAM | C49: 45015 | D49: 45047 | F49: Current | G49: ENT-SAM-CORN | H49: 5020 | I49: Fertilizer & lime | J49: COP | K49: Fertilizer | L49: P&K blend (custom spread) | M49: VEN-SAM-001 | Q49: 7562.5 | R49: -7562.5 | S49: Vendor account | U49: BILL-SAM-00015 | V49: 45045 | Y49: CS-SAM-C23-P1 | AA49: =YEAR(C49) -> 2023
A50: TXN-SAM-000049 | B50: BIZ-SAM | C50: 45016 | D50: 45016 | F50: Current | G50: ENT-SAM-OVH | H50: 7021 | I50: Interest - operating line | J50: INT | K50: Interest | L50: Operating line interest (9.00%) | M50: VEN-SAM-009 | Q50: 509.67 | R50: -509.67 | S50: Auto-draft | X50: LOC-SAM-001 | AA50: =YEAR(C50) -> 2023
A51: TXN-SAM-000050 | B51: BIZ-SAM | C51: 45017 | D51: 45017 | F51: Current | G51: ENT-SAM-OVH | H51: 8041 | I51: Owner distributions / family living | J51: CASHBS | K51: Owner | L51: Owner distribution - family living | Q51: 4000 | R51: -4000 | S51: Transfer | AA51: =YEAR(C51) -> 2023
A52: TXN-SAM-000051 | B52: BIZ-SAM | C52: 45019 | D52: 44917 | F52: Current | G52: ENT-SAM-CORN | H52: 5020 | I52: Fertilizer & lime | J52: COP | K52: Fertilizer | L52: Anhydrous (220 lb N) - pivot corn, prepaid Dec-2022 | M52: VEN-SAM-001 | Q52: 18700 | R52: -18700 | S52: Check | Y52: CS-SAM-C23-P1 | AA52: =YEAR(C52) -> 2023
A53: TXN-SAM-000052 | B53: BIZ-SAM | C53: 45020 | D53: 45050 | F53: Current | G53: ENT-SAM-CORN | H53: 5020 | I53: Fertilizer & lime | J53: COP | K53: Fertilizer | L53: P&K blend (custom spread) | M53: VEN-SAM-001 | Q53: 2464 | R53: -2464 | S53: Vendor account | U53: BILL-SAM-00008 | V53: 45050 | Y53: CS-SAM-C23-D2 | AA53: =YEAR(C53) -> 2023
A54: TXN-SAM-000053 | B54: BIZ-SAM | C54: 45024 | D54: 45068 | F54: Current | G54: ENT-SAM-OVH | H54: 6100 | I54: Office, phone & software | J54: OVH | K54: Professional & admin | L54: Phone, internet, farm software (Climate/FarmLogs) | Q54: 165 | R54: -165 | S54: Credit card | AA54: =YEAR(C54) -> 2023
A55: TXN-SAM-000054 | B55: BIZ-SAM | C55: 45026 | D55: 44917 | F55: Current | G55: ENT-SAM-CORN | H55: 5010 | I55: Seed & plants | J55: COP | K55: Seed & plants | L55: Seed corn - pivot, prepaid Dec-2022 (early-pay discount) | M55: VEN-SAM-002 | Q55: 14500 | R55: -14500 | S55: Check | Y55: CS-SAM-C23-P1 | AA55: =YEAR(C55) -> 2023
A56: TXN-SAM-000055 | B56: BIZ-SAM | C56: 45026 | D56: 45026 | F56: Current | G56: ENT-SAM-OVH | H56: 7020 | I56: Interest - term debt | J56: INT | K56: Interest | L56: Interest - LN-SAM-005 payment 22/60 | M56: VEN-SAM-010 | Q56: 100.45 | R56: -100.45 | S56: ACH | X56: LN-SAM-005 | AA56: =YEAR(C56) -> 2023
A57: TXN-SAM-000056 | B57: BIZ-SAM | C57: 45026 | D57: 45026 | F57: Current | G57: ENT-SAM-OVH | H57: 8011 | I57: Term loan principal payments | J57: CASHBS | K57: Financing | L57: Principal - LN-SAM-005 payment 22/60 | M57: VEN-SAM-010 | Q57: 744.64 | R57: -744.64 | S57: ACH | X57: LN-SAM-005 | AA57: =YEAR(C57) -> 2023
A58: TXN-SAM-000057 | B58: BIZ-SAM | C58: 45026 | D58: 45026 | F58: Current | G58: ENT-SAM-OVH | H58: 8020 | I58: Operating line draws | J58: CASHBS | K58: Financing | L58: Draw on operating line (First Plains Bank) | M58: VEN-SAM-009 | Q58: 13000 | R58: 13000 | S58: Line transfer | X58: LOC-SAM-001 | AA58: =YEAR(C58) -> 2023
A59: TXN-SAM-000058 | B59: BIZ-SAM | C59: 45026 | D59: 45056 | F59: Current | G59: ENT-SAM-CORN | H59: 5020 | I59: Fertilizer & lime | J59: COP | K59: Fertilizer | L59: N fertilizer 110 lb/ac | M59: VEN-SAM-001 | N59: 80 | O59: ac | Q59: 5632 | R59: -5632 | S59: Vendor account | U59: BILL-SAM-00007 | V59: 45056 | Y59: CS-SAM-C23-D2 | AA59: =YEAR(C59) -> 2023
A60: TXN-SAM-000059 | B60: BIZ-SAM | C60: 45028 | D60: 45028 | F60: Current | G60: ENT-SAM-OVH | H60: 6030 | I60: Utilities | J60: OVH | K60: Utilities | L60: Shop/bins electricity | M60: VEN-SAM-016 | Q60: 237.29 | R60: -237.29 | S60: Auto-draft | AA60: =YEAR(C60) -> 2023
A61: TXN-SAM-000060 | B61: BIZ-SAM | C61: 45028 | D61: 45062 | F61: Current | G61: ENT-SAM-COT | H61: 5030 | I61: Chemicals | J61: COP | K61: Chemicals | L61: Preplant herbicide (product) (96 ac) | M61: VEN-SAM-006 | N61: 96 | O61: ac | P61: 22 | Q61: 2112 | R61: -2112 | S61: Vendor account | U61: BILL-SAM-00120 | V61: 45058 | Y61: CS-SAM-COT23 | AA61: =YEAR(C61) -> 2023
A62: TXN-SAM-000061 | B62: BIZ-SAM | C62: 45028 | D62: 45062 | F62: Current | G62: ENT-SAM-COT | H62: 5050 | I62: Custom hire - field operations | J62: COP | K62: Contractors & custom hire | L62: Preplant herbicide application (96 ac) | M62: VEN-SAM-003 | N62: 96 | O62: ac | P62: 9 | Q62: 864 | R62: -864 | S62: Vendor account | U62: BILL-SAM-00119 | V62: 45058 | Y62: CS-SAM-COT23 | AA62: =YEAR(C62) -> 2023
A63: TXN-SAM-000062 | B63: BIZ-SAM | C63: 45030 | D63: 45075 | F63: Current | G63: ENT-SAM-CORN | H63: 5010 | I63: Seed & plants | J63: COP | K63: Seed & plants | L63: Corn seed 80 ac | M63: VEN-SAM-002 | N63: 80 | O63: ac | Q63: 6240 | R63: -6240 | S63: Vendor account | U63: BILL-SAM-00006 | V63: 45075 | Y63: CS-SAM-C23-D2 | AA63: =YEAR(C63) -> 2023
A64: TXN-SAM-000063 | B64: BIZ-SAM | C64: 45031 | D64: 45031 | F64: Current | G64: ENT-SAM-OVH | H64: 8042 | I64: Owner estimated income-tax payments | J64: CASHBS | K64: Owner | L64: Owner estimated income-tax payment | Q64: 3000 | R64: -3000 | S64: EFTPS | AA64: =YEAR(C64) -> 2023
A65: TXN-SAM-000064 | B65: BIZ-SAM | C65: 45035 | D65: 45065 | F65: Current | G65: ENT-SAM-CORN | H65: 5140 | I65: Fuel & oil | J65: COP | K65: Fuel | L65: Diesel - tillage/planting/spraying Corn | M65: VEN-SAM-001 | Q65: 1244.25 | R65: -1244.25 | S65: Vendor account | U65: BILL-SAM-00019 | V65: 45065 | Y65: CS-SAM-C23-P1 | AA65: =YEAR(C65) -> 2023
A66: TXN-SAM-000065 | B66: BIZ-SAM | C66: 45037 | D66: 45068 | F66: Current | G66: ENT-SAM-CORN | H66: 5030 | I66: Chemicals | J66: COP | K66: Chemicals | L66: Pre-emerge herbicide | M66: VEN-SAM-001 | Q66: 3987.5 | R66: -3987.5 | S66: Vendor account | U66: BILL-SAM-00016 | V66: 45067 | Y66: CS-SAM-C23-P1 | AA66: =YEAR(C66) -> 2023
A67: TXN-SAM-000066 | B67: BIZ-SAM | C67: 45038 | D67: 45068 | F67: Current | G67: ENT-SAM-OVH | H67: 6090 | I67: Dues, licenses & subscriptions | J67: OVH | K67: Professional & admin | L67: KS Farm Bureau, Kansas Wheat, Corn Growers dues | Q67: 480 | R67: -480 | S67: Credit card | AA67: =YEAR(C67) -> 2023
A68: TXN-SAM-000067 | B68: BIZ-SAM | C68: 45040 | D68: 45070 | F68: Current | G68: ENT-SAM-CORN | H68: 5140 | I68: Fuel & oil | J68: COP | K68: Fuel | L68: Diesel - tillage/planting/spraying Corn | M68: VEN-SAM-001 | Q68: 796.32 | R68: -796.32 | S68: Vendor account | U68: BILL-SAM-00011 | V68: 45070 | Y68: CS-SAM-C23-D2 | AA68: =YEAR(C68) -> 2023
A69: TXN-SAM-000068 | B69: BIZ-SAM | C69: 45041 | D69: 45075 | F69: Current | G69: ENT-SAM-COT | H69: 5020 | I69: Fertilizer & lime | J69: COP | K69: Fertilizer | L69: Fertilizer 40-20-0 + custom app (96 ac) | M69: VEN-SAM-006 | N69: 96 | O69: ac | P69: 44.3 | Q69: 4252.8 | R69: -4252.8 | S69: Vendor account | U69: BILL-SAM-00121 | V69: 45071 | Y69: CS-SAM-COT23 | AA69: =YEAR(C69) -> 2023
A70: TXN-SAM-000069 | B70: BIZ-SAM | C70: 45042 | D70: 45068 | F70: Current | G70: ENT-SAM-OVH | H70: 6050 | I70: Vehicle expense | J70: OVH | K70: Vehicles | L70: Pickup fuel & upkeep | Q70: 290.65 | R70: -290.65 | S70: Credit card | AA70: =YEAR(C70) -> 2023
A71: TXN-SAM-000070 | B71: BIZ-SAM | C71: 45042 | D71: 45072 | F71: Current | G71: ENT-SAM-CORN | H71: 5030 | I71: Chemicals | J71: COP | K71: Chemicals | L71: Pre-emerge herbicide | M71: VEN-SAM-001 | Q71: 2200 | R71: -2200 | S71: Vendor account | U71: BILL-SAM-00009 | V71: 45072 | Y71: CS-SAM-C23-D2 | AA71: =YEAR(C71) -> 2023
A72: TXN-SAM-000071 | B72: BIZ-SAM | C72: 45046 | D72: 45046 | F72: Current | G72: ENT-SAM-OVH | H72: 7021 | I72: Interest - operating line | J72: INT | K72: Interest | L72: Operating line interest (9.00%) | M72: VEN-SAM-009 | Q72: 607.32 | R72: -607.32 | S72: Auto-draft | X72: LOC-SAM-001 | AA72: =YEAR(C72) -> 2023
A73: TXN-SAM-000072 | B73: BIZ-SAM | C73: 45047 | D73: 45047 | F73: Current | G73: ENT-SAM-OVH | H73: 8020 | I73: Operating line draws | J73: CASHBS | K73: Financing | L73: Draw on operating line (First Plains Bank) | M73: VEN-SAM-009 | Q73: 14000 | R73: 14000 | S73: Line transfer | X73: LOC-SAM-001 | AA73: =YEAR(C73) -> 2023
A74: TXN-SAM-000073 | B74: BIZ-SAM | C74: 45047 | D74: 45047 | F74: Current | G74: ENT-SAM-OVH | H74: 8041 | I74: Owner distributions / family living | J74: CASHBS | K74: Owner | L74: Owner distribution - family living | Q74: 4000 | R74: -4000 | S74: Transfer | AA74: =YEAR(C74) -> 2023
A75: TXN-SAM-000074 | B75: BIZ-SAM | C75: 45054 | D75: 45099 | F75: Current | G75: ENT-SAM-OVH | H75: 6100 | I75: Office, phone & software | J75: OVH | K75: Professional & admin | L75: Phone, internet, farm software (Climate/FarmLogs) | Q75: 165 | R75: -165 | S75: Credit card | AA75: =YEAR(C75) -> 2023
A76: TXN-SAM-000075 | B76: BIZ-SAM | C76: 45056 | D76: 45056 | F76: Current | G76: ENT-SAM-OVH | H76: 7020 | I76: Interest - term debt | J76: INT | K76: Interest | L76: Interest - LN-SAM-005 payment 23/60 | M76: VEN-SAM-010 | Q76: 98.03 | R76: -98.03 | S76: ACH | X76: LN-SAM-005 | AA76: =YEAR(C76) -> 2023
A77: TXN-SAM-000076 | B77: BIZ-SAM | C77: 45056 | D77: 45056 | F77: Current | G77: ENT-SAM-OVH | H77: 8011 | I77: Term loan principal payments | J77: CASHBS | K77: Financing | L77: Principal - LN-SAM-005 payment 23/60 | M77: VEN-SAM-010 | Q77: 747.06 | R77: -747.06 | S77: ACH | X77: LN-SAM-005 | AA77: =YEAR(C77) -> 2023
A78: TXN-SAM-000077 | B78: BIZ-SAM | C78: 45058 | D78: 45058 | F78: Current | G78: ENT-SAM-CUS | H78: 5130 | I78: Hired labor - wages | J78: COP | K78: Direct labor | L78: Seasonal hand/truck driver (57 h) - custom 60% | M78: VEN-SAM-017 | Q78: 644.47 | R78: -644.47 | S78: ACH | AA78: =YEAR(C78) -> 2023
A79: TXN-SAM-000078 | B79: BIZ-SAM | C79: 45058 | D79: 45058 | F79: Current | G79: ENT-SAM-OVH | H79: 5130 | I79: Hired labor - wages | J79: COP | K79: Direct labor | L79: Seasonal hand - own farm 40% | M79: VEN-SAM-017 | Q79: 429.65 | R79: -429.65 | S79: ACH | AA79: =YEAR(C79) -> 2023
A80: TXN-SAM-000079 | B80: BIZ-SAM | C80: 45058 | D80: 45058 | F80: Current | G80: ENT-SAM-OVH | H80: 6030 | I80: Utilities | J80: OVH | K80: Utilities | L80: Shop/bins electricity | M80: VEN-SAM-016 | Q80: 247.2 | R80: -247.2 | S80: Auto-draft | AA80: =YEAR(C80) -> 2023
A81: TXN-SAM-000080 | B81: BIZ-SAM | C81: 45058 | D81: 45058 | F81: Current | G81: ENT-SAM-OVH | H81: 8020 | I81: Operating line draws | J81: CASHBS | K81: Financing | L81: Draw on operating line (First Plains Bank) | M81: VEN-SAM-009 | Q81: 13000 | R81: 13000 | S81: Line transfer | X81: LOC-SAM-001 | AA81: =YEAR(C81) -> 2023
A82: TXN-SAM-000081 | B82: BIZ-SAM | C82: 45058 | D82: 45092 | F82: Current | G82: ENT-SAM-CUS | H82: 5131 | I82: Payroll taxes & benefits | J82: COP | K82: Direct labor | L82: Employer payroll taxes | M82: VEN-SAM-017 | Q82: 94.52 | R82: -94.52 | S82: EFTPS | AA82: =YEAR(C82) -> 2023
A83: TXN-SAM-000082 | B83: BIZ-SAM | C83: 45064 | D83: 45098 | F83: Current | G83: ENT-SAM-COT | H83: 5010 | I83: Seed & plants | J83: COP | K83: Seed & plants | L83: Cottonseed (B3XF) + tech fee (96 ac) | M83: VEN-SAM-006 | N83: 96 | O83: ac | P83: 82 | Q83: 7872 | R83: -7872 | S83: Vendor account | U83: BILL-SAM-00123 | V83: 45094 | Y83: CS-SAM-COT23 | AA83: =YEAR(C83) -> 2023
A84: TXN-SAM-000083 | B84: BIZ-SAM | C84: 45064 | D84: 45098 | F84: Current | G84: ENT-SAM-COT | H84: 5050 | I84: Custom hire - field operations | J84: COP | K84: Contractors & custom hire | L84: Custom planting (96 ac) | M84: VEN-SAM-003 | N84: 96 | O84: ac | P84: 24 | Q84: 2304 | R84: -2304 | S84: Vendor account | U84: BILL-SAM-00122 | V84: 45094 | Y84: CS-SAM-COT23 | AA84: =YEAR(C84) -> 2023
A85: TXN-SAM-000084 | B85: BIZ-SAM | C85: 45066 | D85: 45100 | F85: Current | G85: ENT-SAM-COT | H85: 5030 | I85: Chemicals | J85: COP | K85: Chemicals | L85: Pre-emerge herbicide (96 ac) | M85: VEN-SAM-006 | N85: 96 | O85: ac | P85: 18 | Q85: 1728 | R85: -1728 | S85: Vendor account | U85: BILL-SAM-00124 | V85: 45096 | Y85: CS-SAM-COT23 | AA85: =YEAR(C85) -> 2023
A86: TXN-SAM-000085 | B86: BIZ-SAM | C86: 45072 | D86: 45072 | F86: Current | G86: ENT-SAM-CUS | H86: 5130 | I86: Hired labor - wages | J86: COP | K86: Direct labor | L86: Seasonal hand/truck driver (59 h) - custom 60% | M86: VEN-SAM-017 | Q86: 674.29 | R86: -674.29 | S86: ACH | AA86: =YEAR(C86) -> 2023
A87: TXN-SAM-000086 | B87: BIZ-SAM | C87: 45072 | D87: 45072 | F87: Current | G87: ENT-SAM-OVH | H87: 5130 | I87: Hired labor - wages | J87: COP | K87: Direct labor | L87: Seasonal hand - own farm 40% | M87: VEN-SAM-017 | Q87: 449.52 | R87: -449.52 | S87: ACH | AA87: =YEAR(C87) -> 2023
A88: TXN-SAM-000087 | B88: BIZ-SAM | C88: 45072 | D88: 45072 | F88: Current | G88: ENT-SAM-OVH | H88: 8020 | I88: Operating line draws | J88: CASHBS | K88: Financing | L88: Draw on operating line (First Plains Bank) | M88: VEN-SAM-009 | Q88: 13000 | R88: 13000 | S88: Line transfer | X88: LOC-SAM-001 | AA88: =YEAR(C88) -> 2023
A89: TXN-SAM-000088 | B89: BIZ-SAM | C89: 45072 | D89: 45092 | F89: Current | G89: ENT-SAM-CUS | H89: 5131 | I89: Payroll taxes & benefits | J89: COP | K89: Direct labor | L89: Employer payroll taxes | M89: VEN-SAM-017 | Q89: 98.9 | R89: -98.9 | S89: EFTPS | AA89: =YEAR(C89) -> 2023
A90: TXN-SAM-000089 | B90: BIZ-SAM | C90: 45072 | D90: 45099 | F90: Current | G90: ENT-SAM-OVH | H90: 6050 | I90: Vehicle expense | J90: OVH | K90: Vehicles | L90: Pickup fuel & upkeep | Q90: 287.8 | R90: -287.8 | S90: Credit card | AA90: =YEAR(C90) -> 2023
A91: TXN-SAM-000090 | B91: BIZ-SAM | C91: 45075 | D91: 45105 | F91: Current | G91: ENT-SAM-CORN | H91: 5030 | I91: Chemicals | J91: COP | K91: Chemicals | L91: Post-emerge herbicide | M91: VEN-SAM-001 | Q91: 3262.5 | R91: -3262.5 | S91: Vendor account | U91: BILL-SAM-00017 | V91: 45105 | Y91: CS-SAM-C23-P1 | AA91: =YEAR(C91) -> 2023
A92: TXN-SAM-000091 | B92: BIZ-SAM | C92: 45077 | D92: 45077 | F92: Current | G92: ENT-SAM-OVH | H92: 7021 | I92: Interest - operating line | J92: INT | K92: Interest | L92: Operating line interest (9.25%) | M92: VEN-SAM-009 | Q92: 871.27 | R92: -871.27 | S92: Auto-draft | X92: LOC-SAM-001 | AA92: =YEAR(C92) -> 2023
A93: TXN-SAM-000092 | B93: BIZ-SAM | C93: 45078 | D93: 45078 | F93: Current | G93: ENT-SAM-OVH | H93: 8020 | I93: Operating line draws | J93: CASHBS | K93: Financing | L93: Draw on operating line (First Plains Bank) | M93: VEN-SAM-009 | Q93: 16000 | R93: 16000 | S93: Line transfer | X93: LOC-SAM-001 | AA93: =YEAR(C93) -> 2023
A94: TXN-SAM-000093 | B94: BIZ-SAM | C94: 45078 | D94: 45078 | F94: Current | G94: ENT-SAM-OVH | H94: 8041 | I94: Owner distributions / family living | J94: CASHBS | K94: Owner | L94: Owner distribution - family living | Q94: 4000 | R94: -4000 | S94: Transfer | AA94: =YEAR(C94) -> 2023
A95: TXN-SAM-000094 | B95: BIZ-SAM | C95: 45080 | D95: 45110 | F95: Current | G95: ENT-SAM-CORN | H95: 5030 | I95: Chemicals | J95: COP | K95: Chemicals | L95: Post-emerge herbicide | M95: VEN-SAM-001 | Q95: 1800 | R95: -1800 | S95: Vendor account | U95: BILL-SAM-00010 | V95: 45110 | Y95: CS-SAM-C23-D2 | AA95: =YEAR(C95) -> 2023
A96: TXN-SAM-000095 | B96: BIZ-SAM | C96: 45083 | D96: 45113 | F96: Current | G96: ENT-SAM-CUS | H96: 5150 | I96: Repairs - machinery & equipment | J96: COP | K96: Repairs & maintenance | L96: Pre-season combine service, sieves, belts, knife sections (wheat) | M96: VEN-SAM-013 | Q96: 5576 | R96: -5576 | S96: Vendor account | U96: BILL-SAM-00191 | V96: 45113 | W96: AST-SAM-004 | AA96: =YEAR(C96) -> 2023
A97: TXN-SAM-000096 | B97: BIZ-SAM | C97: 45085 | D97: 45129 | F97: Current | G97: ENT-SAM-OVH | H97: 6100 | I97: Office, phone & software | J97: OVH | K97: Professional & admin | L97: Phone, internet, farm software (Climate/FarmLogs) | Q97: 165 | R97: -165 | S97: Credit card | AA97: =YEAR(C97) -> 2023
A98: TXN-SAM-000097 | B98: BIZ-SAM | C98: 45086 | D98: 45086 | F98: Current | G98: ENT-SAM-CUS | H98: 5130 | I98: Hired labor - wages | J98: COP | K98: Direct labor | L98: Seasonal hand/truck driver (62 h) - custom 60% | M98: VEN-SAM-017 | Q98: 711.65 | R98: -711.65 | S98: ACH | AA98: =YEAR(C98) -> 2023
A99: TXN-SAM-000098 | B99: BIZ-SAM | C99: 45086 | D99: 45086 | F99: Current | G99: ENT-SAM-OVH | H99: 5130 | I99: Hired labor - wages | J99: COP | K99: Direct labor | L99: Seasonal hand - own farm 40% | M99: VEN-SAM-017 | Q99: 474.43 | R99: -474.43 | S99: ACH | AA99: =YEAR(C99) -> 2023
A100: TXN-SAM-000099 | B100: BIZ-SAM | C100: 45086 | D100: 45122 | F100: Current | G100: ENT-SAM-CUS | H100: 5131 | I100: Payroll taxes & benefits | J100: COP | K100: Direct labor | L100: Employer payroll taxes | M100: VEN-SAM-017 | Q100: 104.38 | R100: -104.38 | S100: EFTPS | AA100: =YEAR(C100) -> 2023
...

Sheet AR_Invoices
A1: amount | B1: business_id | C1: invoice_id | D1: customer_id | E1: enterprise_id | F1: invoice_date | G1: due_date | H1: description | I1: amount_paid | J1: balance_due | K1: status | L1: paid_date | M1: expected_payment_date | N1: days_outstanding | O1: days_past_due
A2: 29956.8 | B2: BIZ-SAM | C2: POOL-SAM-2022 | D2: CUS-SAM-002 | E2: ENT-SAM-COT | F2: 44914 | G2: 45226 | H2: 2022 cotton - pool payment (37,920 lb lint @ $0.790) | I2: 29956.8 | J2: 0 | K2: Paid | L2: 45226 | N2: 312 | O2: 0
A3: 6271.78 | B3: BIZ-SAM | C3: INV-SAM-00035 | D3: CUS-SAM-107 | E3: ENT-SAM-CUS | F3: 45101 | G3: 45131 | H3: Custom hauling 2,693 bu @ $0.17/bu - Dale & Jo Unruh | I3: 6271.78 | J3: 0 | K3: Paid | L3: 45145 | N3: 44 | O3: 14
A4: 6230.78 | B4: BIZ-SAM | C4: INV-SAM-00032 | D4: CUS-SAM-104 | E4: ENT-SAM-CUS | F4: 45102 | G4: 45132 | H4: Custom hauling 2,675 bu @ $0.17/bu - Gail Schrag | I4: 6230.78 | J4: 0 | K4: Paid | L4: 45145 | N4: 43 | O4: 13
A5: 8239.39 | B5: BIZ-SAM | C5: INV-SAM-00033 | D5: CUS-SAM-105 | E5: ENT-SAM-CUS | F5: 45103 | G5: 45133 | H5: Custom hauling 3,538 bu @ $0.17/bu - Lindquist Family Farms | I5: 8239.39 | J5: 0 | K5: Paid | L5: 45146 | N5: 43 | O5: 13
A6: 8157.41 | B6: BIZ-SAM | C6: INV-SAM-00031 | D6: CUS-SAM-103 | E6: ENT-SAM-CUS | F6: 45104 | G6: 45134 | H6: Custom hauling 3,502 bu @ $0.17/bu - Rudd Brothers Partnership | I6: 8157.41 | J6: 0 | K6: Paid | L6: 45177 | N6: 73 | O6: 43
A7: 11814.72 | B7: BIZ-SAM | C7: INV-SAM-00001 | D7: CUS-SAM-004 | E7: ENT-SAM-WHT | F7: 45105 | G7: 45105 | H7: Wheat (2023 crop) 1,488 bu @ $7.94 at harvest | I7: 11814.72 | J7: 0 | K7: Paid | L7: 45114 | N7: 9 | O7: 9
A8: 17134.66 | B8: BIZ-SAM | C8: INV-SAM-00029 | D8: CUS-SAM-101 | E8: ENT-SAM-CUS | F8: 45105 | G8: 45135 | H8: Custom hauling 7,357 bu @ $0.17/bu - Heartland Land & Cattle | I8: 17134.66 | J8: 0 | K8: Paid | L8: 45160 | N8: 55 | O8: 25
A9: 4427.14 | B9: BIZ-SAM | C9: INV-SAM-00036 | D9: CUS-SAM-108 | E9: ENT-SAM-CUS | F9: 45105 | G9: 45135 | H9: Custom hauling 1,901 bu @ $0.17/bu - Smoky Hill Farms LLC | I9: 4427.14 | J9: 0 | K9: Paid | L9: 45149 | N9: 44 | O9: 14
A10: 10043.04 | B10: BIZ-SAM | C10: INV-SAM-00030 | D10: CUS-SAM-102 | E10: ENT-SAM-CUS | F10: 45108 | G10: 45138 | H10: Custom hauling 4,312 bu @ $0.17/bu - Ostrander Farms | I10: 10043.04 | J10: 0 | K10: Paid | L10: 45223 | N10: 115 | O10: 85
A11: 5984.83 | B11: BIZ-SAM | C11: INV-SAM-00034 | D11: CUS-SAM-106 | E11: ENT-SAM-CUS | F11: 45109 | G11: 45139 | H11: Custom hauling 2,570 bu @ $0.17/bu - Prairie Rose Dairy | I11: 5984.83 | J11: 0 | K11: Paid | L11: 45169 | N11: 60 | O11: 30
A12: 27942.4 | B12: BIZ-SAM | C12: INV-SAM-00003 | D12: CUS-SAM-001 | E12: ENT-SAM-CORN | F12: 45187 | G12: 45187 | H12: Corn (2023 crop) 5,920 bu @ $4.72 at harvest | I12: 27942.4 | J12: 0 | K12: Paid | L12: 45191 | N12: 4 | O12: 4
A13: 11334.64 | B13: BIZ-SAM | C13: INV-SAM-00046 | D13: CUS-SAM-102 | E13: ENT-SAM-CUS | F13: 45205 | G13: 45235 | H13: Custom hauling 21,904 bu @ $0.17/bu - Ostrander Farms | I13: 11334.64 | J13: 0 | K13: Paid | L13: 45327 | N13: 122 | O13: 92
... A80: 9830.3 | B80: BIZ-SAM | C80: INV-SAM-00087 | D80: CUS-SAM-103 | E80: ENT-SAM-CUS | F80: 45940 | G80: 45970 | H80: Custom hauling 6,796 bu @ $0.2/bu - Rudd Brothers Partnership | I80: 9830.3 | J80: 0 | K80: Paid | L80: 45999 | N80: 59 | O80: 29
A81: 12843.25 | B81: BIZ-SAM | C81: INV-SAM-00095 | D81: CUS-SAM-103 | E81: ENT-SAM-CUS | F81: 45941 | G81: 45971 | H81: Custom hauling 22,151 bu @ $0.2/bu - Rudd Brothers Partnership | I81: 0 | J81: 12843.25 | K81: Unpaid | M81: 46371 | N81: 354 | O81: 324
A82: 7820.75 | B82: BIZ-SAM | C82: INV-SAM-00099 | D82: CUS-SAM-107 | E82: ENT-SAM-CUS | F82: 45941 | G82: 45971 | H82: Custom hauling 13,489 bu @ $0.2/bu - Dale & Jo Unruh | I82: 7820.75 | J82: 0 | K82: Paid | L82: 45971 | N82: 30 | O82: 0
A83: 18962 | B83: BIZ-SAM | C83: INV-SAM-00085 | D83: CUS-SAM-101 | E83: ENT-SAM-CUS | F83: 45943 | G83: 45973 | H83: Custom hauling 13,110 bu @ $0.2/bu - Heartland Land & Cattle | I83: 18962 | J83: 0 | K83: Paid | L83: 45999 | N83: 56 | O83: 26
A84: 6137.7 | B84: BIZ-SAM | C84: INV-SAM-00091 | D84: CUS-SAM-107 | E84: ENT-SAM-CUS | F84: 45943 | G84: 45973 | H84: Custom hauling 4,244 bu @ $0.2/bu - Dale & Jo Unruh | I84: 6137.7 | J84: 0 | K84: Paid | L84: 45992 | N84: 49 | O84: 19
A85: 6672.75 | B85: BIZ-SAM | C85: INV-SAM-00098 | D85: CUS-SAM-106 | E85: ENT-SAM-CUS | F85: 45943 | G85: 45973 | H85: Custom hauling 11,509 bu @ $0.2/bu - Prairie Rose Dairy | I85: 6672.75 | J85: 0 | K85: Paid | L85: 46013 | N85: 70 | O85: 40
A86: 25543 | B86: BIZ-SAM | C86: INV-SAM-00093 | D86: CUS-SAM-101 | E86: ENT-SAM-CUS | F86: 45944 | G86: 45974 | H86: Custom hauling 44,055 bu @ $0.2/bu - Heartland Land & Cattle | I86: 25543 | J86: 0 | K86: Paid | L86: 46000 | N86: 56 | O86: 26
A87: 16816.8 | B87: BIZ-SAM | C87: INV-SAM-00017 | D87: CUS-SAM-001 | E87: ENT-SAM-SOY | F87: 45946 | G87: 45946 | H87: Soybeans (2025 crop) 1,680 bu @ $10.01 at harvest | I87: 16816.8 | J87: 0 | K87: Paid | L87: 45950 | N87: 4 | O87: 4
A88: 5888.2 | B88: BIZ-SAM | C88: INV-SAM-00088 | D88: CUS-SAM-104 | E88: ENT-SAM-CUS | F88: 45946 | G88: 45976 | H88: Custom hauling 4,071 bu @ $0.2/bu - Gail Schrag | I88: 5888.2 | J88: 0 | K88: Paid | L88: 45992 | N88: 46 | O88: 16
A89: 11077.8 | B89: BIZ-SAM | C89: INV-SAM-00086 | D89: CUS-SAM-102 | E89: ENT-SAM-CUS | F89: 45948 | G89: 45978 | H89: Custom hauling 7,659 bu @ $0.2/bu - Ostrander Farms | I89: 11077.8 | J89: 0 | K89: Paid | L89: 46027 | N89: 79 | O89: 49
A90: 5389.2 | B90: BIZ-SAM | C90: INV-SAM-00092 | D90: CUS-SAM-108 | E90: ENT-SAM-CUS | F90: 45949 | G90: 45979 | H90: Custom hauling 3,726 bu @ $0.2/bu - Smoky Hill Farms LLC | I90: 5389.2 | J90: 0 | K90: Paid | L90: 46007 | N90: 58 | O90: 28
A91: 7103.25 | B91: BIZ-SAM | C91: INV-SAM-00100 | D91: CUS-SAM-108 | E91: ENT-SAM-CUS | F91: 45959 | G91: 45989 | H91: Custom hauling 12,251 bu @ $0.2/bu - Smoky Hill Farms LLC | I91: 7103.25 | J91: 0 | K91: Paid | L91: 46013 | N91: 54 | O91: 24
A92: 16215.5 | B92: BIZ-SAM | C92: INV-SAM-00094 | D92: CUS-SAM-102 | E92: ENT-SAM-CUS | F92: 45960 | G92: 45990 | H92: Custom hauling 27,968 bu @ $0.2/bu - Ostrander Farms | I92: 16215.5 | J92: 0 | K92: Paid | L92: 46048 | N92: 88 | O92: 58
A93: 7457.39 | B93: BIZ-SAM | C93: INV-SAM-00027 | D93: CUS-SAM-003 | E93: ENT-SAM-COT | F93: 46009 | G93: 46039 | H93: Cottonseed 35.5 tons @ $210 | I93: 7457.39 | J93: 0 | K93: Paid | L93: 46059 | N93: 50 | O93: 20
A94: 30759.85 | B94: BIZ-SAM | C94: POOL-SAM-2025 | D94: CUS-SAM-002 | E94: ENT-SAM-COT | F94: 46010 | G94: 46321 | H94: 2025 cotton - pool progress/final (50,016 lb @ $0.615 est. pool price) | I94: 26145.87 | J94: 4613.98 | K94: Partially paid | M94: 46321 | N94: 285 | O94: 0
A95: 17371.2 | B95: BIZ-SAM | C95: INV-SAM-00018 | D95: CUS-SAM-001 | E95: ENT-SAM-SOY | F95: 46042 | G95: 46042 | H95: Soybeans (2025 crop) 1,680 bu @ $10.34 from bin | I95: 17371.2 | J95: 0 | K95: Paid | L95: 46048 | N95: 6 | O95: 6
A96: 42748.38 | B96: BIZ-SAM | C96: INV-SAM-00015 | D96: CUS-SAM-001 | E96: ENT-SAM-CORN | F96: 46070 | G96: 46070 | H96: Corn (2025 crop) 10,106 bu @ $4.23 from bin | I96: 42748.38 | J96: 0 | K96: Paid | L96: 46076 | N96: 6 | O96: 6
A97: 11087.6 | B97: BIZ-SAM | C97: INV-SAM-00013 | D97: CUS-SAM-004 | E97: ENT-SAM-WHT | F97: 46092 | G97: 46092 | H97: Wheat (2025 crop) 2,120 bu @ $5.23 from bin | I97: 11087.6 | J97: 0 | K97: Paid | L97: 46101 | N97: 9 | O97: 9
A98: 37073.36 | B98: BIZ-SAM | C98: INV-SAM-00016 | D98: CUS-SAM-001 | E98: ENT-SAM-CORN | F98: 46134 | G98: 46134 | H98: Corn (2025 crop) 8,662 bu @ $4.28 from bin | I98: 37073.36 | J98: 0 | K98: Paid | L98: 46139 | N98: 5 | O98: 5
A99: 11551.68 | B99: BIZ-SAM | C99: INV-SAM-00019 | D99: CUS-SAM-004 | E99: ENT-SAM-WHT | F99: 46198 | G99: 46198 | H99: Wheat (2026 crop) 2,016 bu @ $5.73 at harvest | I99: 11551.68 | J99: 0 | K99: Paid | L99: 46209 | N99: 11 | O99: 11
A100: 4414.64 | B100: BIZ-SAM | C100: INV-SAM-00108 | D100: CUS-SAM-108 | E100: ENT-SAM-CUS | F100: 46198 | G100: 46228 | H100: Custom hauling 2,389 bu @ $0.21/bu - Smoky Hill Farms LLC | I100: 4414.64 | J100: 0 | K100: Paid | L100: 46248 | N100: 50 | O100: 20
A101: 7664.98 | B101: BIZ-SAM | C101: INV-SAM-00105 | D101: CUS-SAM-105 | E101: ENT-SAM-CUS | F101: 46201 | G101: 46231 | H101: Custom hauling 4,148 bu @ $0.21/bu - Lindquist Family Farms | I101: 7664.98 | J101: 0 | K101: Paid | L101: 46237 | N101: 36 | O101: 6
A102: 14408.21 | B102: BIZ-SAM | C102: INV-SAM-00101 | D102: CUS-SAM-101 | E102: ENT-SAM-CUS | F102: 46202 | G102: 46232 | H102: Custom hauling 7,796 bu @ $0.21/bu - Heartland Land & Cattle | I102: 14408.21 | J102: 0 | K102: Paid | L102: 46252 | N102: 50 | O102: 20
A103: 5336.38 | B103: BIZ-SAM | C103: INV-SAM-00106 | D103: CUS-SAM-106 | E103: ENT-SAM-CUS | F103: 46204 | G103: 46234 | H103: Custom hauling 2,888 bu @ $0.21/bu - Prairie Rose Dairy | I103: 5336.38 | J103: 0 | K103: Paid | L103: 46252 | N103: 48 | O103: 18
A104: 10381.67 | B104: BIZ-SAM | C104: INV-SAM-00102 | D104: CUS-SAM-102 | E104: ENT-SAM-CUS | F104: 46205 | G104: 46235 | H104: Custom hauling 5,618 bu @ $0.21/bu - Ostrander Farms | I104: 10381.67 | J104: 0 | K104: Paid | L104: 46286 | N104: 81 | O104: 51
A105: 7519.44 | B105: BIZ-SAM | C105: INV-SAM-00103 | D105: CUS-SAM-103 | E105: ENT-SAM-CUS | F105: 46209 | G105: 46239 | H105: Custom hauling 4,069 bu @ $0.21/bu - Rudd Brothers Partnership | I105: 7519.44 | J105: 0 | K105: Paid | L105: 46269 | N105: 60 | O105: 30
A106: 5530.42 | B106: BIZ-SAM | C106: INV-SAM-00104 | D106: CUS-SAM-104 | E106: ENT-SAM-CUS | F106: 46210 | G106: 46240 | H106: Custom hauling 2,992 bu @ $0.21/bu - Gail Schrag | I106: 5530.42 | J106: 0 | K106: Paid | L106: 46244 | N106: 34 | O106: 4
... A108: 31752 | B108: BIZ-SAM | C108: INV-SAM-00021 | D108: CUS-SAM-001 | E108: ENT-SAM-CORN | F108: 46289 | G108: 46289 | H108: Corn (2026 crop) 7,840 bu @ $4.05 at harvest | I108: 31752 | J108: 0 | K108: Paid | L108: 46293 | N108: 4 | O108: 4

Sheet AP_Bills
A1: amount | B1: business_id | C1: bill_id | D1: vendor_id | E1: enterprise_id | F1: bill_date | G1: due_date | H1: expense_category | I1: account_code | J1: description | K1: amount_paid | L1: balance_due | M1: status | N1: paid_date | O1: expected_payment_date | P1: days_outstanding | Q1: days_past_due
A2: 3184.55 | B2: BIZ-SAM | C2: BILL-SAM-00001 | D2: VEN-SAM-001 | E2: ENT-SAM-OVH | F2: 44915 | G2: 44945 | H2: Fuel | I2: 5140 | J2: Bulk diesel delivery Dec 2022 | K2: 3184.55 | L2: 0 | M2: Paid | N2: 44945 | P2: 30 | Q2: 0
A3: 1344 | B3: BIZ-SAM | C3: BILL-SAM-00117 | D3: VEN-SAM-003 | E3: ENT-SAM-COT | F3: 44946 | G3: 44976 | H3: Contractors & custom hire | I3: 5050 | J3: Shred stalks (96 ac) | K3: 1344 | L3: 0 | M3: Paid | N3: 44980 | P3: 34 | Q3: 4
A4: 4096 | B4: BIZ-SAM | C4: BILL-SAM-00002 | D4: VEN-SAM-001 | E4: ENT-SAM-WHT | F4: 44987 | G4: 45017 | H4: Fertilizer | I4: 5020 | J4: Topdress N (UAN 80 lb) - custom applied | K4: 4096 | L4: 0 | M4: Paid | N4: 45019 | P4: 32 | Q4: 2
A5: 2304 | B5: BIZ-SAM | C5: BILL-SAM-00118 | D5: VEN-SAM-003 | E5: ENT-SAM-COT | F5: 44991 | G5: 45021 | H5: Contractors & custom hire | I5: 5050 | J5: Disk & list beds (96 ac) | K5: 2304 | L5: 0 | M5: Paid | N5: 45026 | P5: 35 | Q5: 5
A6: 1290.98 | B6: BIZ-SAM | C6: BILL-SAM-00244 | D6: VEN-SAM-013 | E6: ENT-SAM-OVH | F6: 44999 | G6: 45029 | H6: Repairs & maintenance | I6: 5150 | J6: Shop supplies, filters, tires | K6: 1290.98 | L6: 0 | M6: Paid | N6: 45029 | P6: 30 | Q6: 0
A7: 1120 | B7: BIZ-SAM | C7: BILL-SAM-00003 | D7: VEN-SAM-001 | E7: ENT-SAM-WHT | F7: 45013 | G7: 45043 | H7: Chemicals | I7: 5030 | J7: Wheat herbicide (spring) | K7: 1120 | L7: 0 | M7: Paid | N7: 45043 | P7: 30 | Q7: 0
A8: 7562.5 | B8: BIZ-SAM | C8: BILL-SAM-00015 | D8: VEN-SAM-001 | E8: ENT-SAM-CORN | F8: 45015 | G8: 45045 | H8: Fertilizer | I8: 5020 | J8: P&K blend (custom spread) | K8: 7562.5 | L8: 0 | M8: Paid | N8: 45047 | P8: 32 | Q8: 2
A9: 2464 | B9: BIZ-SAM | C9: BILL-SAM-00008 | D9: VEN-SAM-001 | E9: ENT-SAM-CORN | F9: 45020 | G9: 45050 | H9: Fertilizer | I9: 5020 | J9: P&K blend (custom spread) | K9: 2464 | L9: 0 | M9: Paid | N9: 45050 | P9: 30 | Q9: 0
A10: 5632 | B10: BIZ-SAM | C10: BILL-SAM-00007 | D10: VEN-SAM-001 | E10: ENT-SAM-CORN | F10: 45026 | G10: 45056 | H10: Fertilizer | I10: 5020 | J10: N fertilizer 110 lb/ac | K10: 5632 | L10: 0 | M10: Paid | N10: 45056 | P10: 30 | Q10: 0
A11: 864 | B11: BIZ-SAM | C11: BILL-SAM-00119 | D11: VEN-SAM-003 | E11: ENT-SAM-COT | F11: 45028 | G11: 45058 | H11: Contractors & custom hire | I11: 5050 | J11: Preplant herbicide application (96 ac) | K11: 864 | L11: 0 | M11: Paid | N11: 45062 | P11: 34 | Q11: 4
A12: 2112 | B12: BIZ-SAM | C12: BILL-SAM-00120 | D12: VEN-SAM-006 | E12: ENT-SAM-COT | F12: 45028 | G12: 45058 | H12: Chemicals | I12: 5030 | J12: Preplant herbicide (product) (96 ac) | K12: 2112 | L12: 0 | M12: Paid | N12: 45062 | P12: 34 | Q12: 4
A13: 6240 | B13: BIZ-SAM | C13: BILL-SAM-00006 | D13: VEN-SAM-002 | E13: ENT-SAM-CORN | F13: 45030 | G13: 45075 | H13: Seed & plants | I13: 5010 | J13: Corn seed 80 ac | K13: 6240 | L13: 0 | M13: Paid | N13: 45075 | P13: 45 | Q13: 0
... A198: 5170 | B198: BIZ-SAM | C198: BILL-SAM-00095 | D198: VEN-SAM-016 | E198: ENT-SAM-SOY | F198: 46252 | G198: 46267 | H198: Irrigation | I198: 5160 | J198: Irrigation pumping power (4.4 in) | K198: 5170 | L198: 0 | M198: Paid | N198: 46267 | P198: 15 | Q198: 0
A199: 6646.08 | B199: BIZ-SAM | C199: BILL-SAM-00224 | D199: VEN-SAM-013 | E199: ENT-SAM-CUS | F199: 46267 | G199: 46297 | H199: Repairs & maintenance | I199: 5150 | J199: Pre-season combine service, sieves, belts, knife sections (corn) | K199: 0 | L199: 6646.08 | M199: Unpaid | O199: 46297 | P199: 28 | Q199: 0
A200: 6246.24 | B200: BIZ-SAM | C200: BILL-SAM-00221 | D200: VEN-SAM-013 | E200: ENT-SAM-CUS | F200: 46281 | G200: 46311 | H200: Repairs & maintenance | I200: 5150 | J200: Pre-season combine service, sieves, belts, knife sections (soybeans) | K200: 0 | L200: 6246.24 | M200: Unpaid | O200: 46311 | P200: 14 | Q200: 0
A201: 936.32 | B201: BIZ-SAM | C201: BILL-SAM-00086 | D201: VEN-SAM-001 | E201: ENT-SAM-CORN | F201: 46287 | G201: 46317 | H201: Fuel | I201: 5140 | J201: Diesel - harvest & hauling Corn | K201: 0 | L201: 936.32 | M201: Unpaid | O201: 46317 | P201: 8 | Q201: 0
A202: 2092.8 | B202: BIZ-SAM | C202: BILL-SAM-00087 | D202: VEN-SAM-013 | E202: ENT-SAM-CORN | F202: 46292 | G202: 46322 | H202: Repairs & maintenance | I202: 5150 | J202: Machinery repairs/parts allocated - Corn | K202: 0 | L202: 2092.8 | M202: Unpaid | O202: 46322 | P202: 3 | Q202: 0

Sheet Crop_Seasons
A1: business_id | B1: crop_season_id | C1: enterprise_id | D1: crop | E1: field_id | F1: crop_year | G1: acres | H1: irrigated | I1: plant_date | J1: harvest_start | K1: harvest_end | L1: expected_yield | M1: actual_yield | N1: yield_unit | O1: total_production | P1: expected_price | Q1: actual_avg_price | R1: qty_sold | S1: qty_stored_end | T1: revenue | U1: data_type
A2: BIZ-SAM | B2: CS-SAM-W23-D1 | C2: ENT-SAM-WHT | D2: Wheat | E2: KS-D1 | F2: 2023 | G2: 80 | H2: =FALSE() -> FALSE | I2: 44840 | J2: 45103 | K2: 45106 | L2: 46 | M2: 31 | N2: bu/ac | O2: 2480 | P2: 8.1 | Q2: 7.42 | R2: 2480 | S2: 0 | T2: 18411.52 | U2: Actual
A3: BIZ-SAM | B3: CS-SAM-C23-D2 | C3: ENT-SAM-CORN | D3: Corn | E3: KS-D2 | F3: 2023 | G3: 80 | H3: =FALSE() -> FALSE | I3: 45040 | J3: 45183 | K3: 45186 | L3: 105 | M3: 74 | N3: bu/ac | O3: 5920 | P3: 5.6 | Q3: 4.72 | R3: 5920 | S3: 0 | T3: 27942.4 | U3: Actual
A4: BIZ-SAM | B4: CS-SAM-C23-P1 | C4: ENT-SAM-CORN | D4: Corn | E4: KS-P1 | F4: 2023 | G4: 125 | H4: =TRUE() -> TRUE | I4: 45035 | J4: 45208 | K4: 45214 | L4: 215 | M4: 207 | N4: bu/ac | O4: 25875 | P4: 5.6 | Q4: 4.41 | R4: 25875 | S4: 0 | T4: 113992.31 | U4: Actual
A5: BIZ-SAM | B5: CS-SAM-W24-D2 | C5: ENT-SAM-WHT | D5: Wheat | E5: KS-D2 | F5: 2024 | G5: 80 | H5: =FALSE() -> FALSE | I5: 45201 | J5: 45467 | K5: 45470 | L5: 46 | M5: 46 | N5: bu/ac | O5: 3680 | P5: 6.2 | Q5: 5.41 | R5: 3680 | S5: 0 | T5: 19894.08 | U5: Actual
A6: BIZ-SAM | B6: CS-SAM-S24-P1 | C6: ENT-SAM-SOY | D6: Soybeans | E6: KS-P1 | F6: 2024 | G6: 125 | H6: =TRUE() -> TRUE | I6: 45426 | J6: 45568 | K6: 45574 | L6: 62 | M6: 64 | N6: bu/ac | O6: 8000 | P6: 11.4 | Q6: 9.83 | R6: 8000 | S6: 0 | T6: 78640 | U6: Actual
A7: BIZ-SAM | B7: CS-SAM-S24-D1 | C7: ENT-SAM-SOY | D7: Soybeans | E7: KS-D1 | F7: 2024 | G7: 80 | H7: =FALSE() -> FALSE | I7: 45432 | J7: 45575 | K7: 45578 | L7: 38 | M7: 36 | N7: bu/ac | O7: 2880 | P7: 11.4 | Q7: 9.73 | R7: 2880 | S7: 0 | T7: 28022.4 | U7: Actual
A8: BIZ-SAM | B8: CS-SAM-W25-D1 | C8: ENT-SAM-WHT | D8: Wheat | E8: KS-D1 | F8: 2025 | G8: 80 | H8: =FALSE() -> FALSE | I8: 45583 | J8: 45831 | K8: 45834 | L8: 46 | M8: 53 | N8: bu/ac | O8: 4240 | P8: 5.4 | Q8: 5.03 | R8: 4240 | S8: 0 | T8: 21306 | U8: Actual
A9: BIZ-SAM | B9: CS-SAM-C25-P1 | C9: ENT-SAM-CORN | D9: Corn | E9: KS-P1 | F9: 2025 | G9: 125 | H9: =TRUE() -> TRUE | I9: 45768 | J9: 45936 | K9: 45942 | L9: 215 | M9: 231 | N9: bu/ac | O9: 28875 | P9: 4.2 | Q9: 4.12 | R9: 28874 | S9: 1 | T9: 119033.02 | U9: Actual
A10: BIZ-SAM | B10: CS-SAM-S25-D2 | C10: ENT-SAM-SOY | D10: Soybeans | E10: KS-D2 | F10: 2025 | G10: 80 | H10: =FALSE() -> FALSE | I10: 45796 | J10: 45943 | K10: 45946 | L10: 38 | M10: 42 | N10: bu/ac | O10: 3360 | P10: 10.1 | Q10: 10.18 | R10: 3360 | S10: 0 | T10: 34188 | U10: Actual
A11: BIZ-SAM | B11: CS-SAM-W26-D2 | C11: ENT-SAM-WHT | D11: Wheat | E11: KS-D2 | F11: 2026 | G11: 80 | H11: =FALSE() -> FALSE | I11: 45950 | J11: 46195 | K11: 46198 | L11: 46 | M11: 36 | N11: bu/ac | O11: 2880 | P11: 5.2 | Q11: 5.68 | R11: 2880 | S11: 0 | T11: 16355.52 | U11: Actual harvest; stored grain unsold
A12: BIZ-SAM | B12: CS-SAM-C26-D1 | C12: ENT-SAM-CORN | D12: Corn | E12: KS-D1 | F12: 2026 | G12: 80 | H12: =FALSE() -> FALSE | I12: 46139 | J12: 46287 | K12: 46290 | L12: 105 | M12: 98 | N12: bu/ac | O12: 7840 | P12: 4.2 | Q12: 4.05 | R12: 7840 | S12: 0 | T12: 31752 | U12: Actual
A13: BIZ-SAM | B13: CS-SAM-S26-P1 | C13: ENT-SAM-SOY | D13: Soybeans | E13: KS-P1 | F13: 2026 | G13: 125 | H13: =TRUE() -> TRUE | I13: 46154 | J13: 46302 | K13: 46308 | L13: 62 | M13: 62 | N13: bu/ac | O13: 7750 | P13: 10.3 | Q13: 10.36 | R13: 7750 | S13: 0 | T13: 80305.58 | U13: Forecast
A14: BIZ-SAM | B14: CS-SAM-W27-D1 | C14: ENT-SAM-WHT | D14: Wheat | E14: KS-D1 | F14: 2027 | G14: 80 | H14: =FALSE() -> FALSE | I14: 46309 | J14: 46561 | K14: 46564 | L14: 46 | M14: 46 | N14: bu/ac | O14: 3680 | P14: 5.6 | Q14: 5.67 | R14: 2576 | S14: 1104 | T14: 14605.92 | U14: Forecast
A15: BIZ-SAM | B15: CS-SAM-COT23 | C15: ENT-SAM-COT | D15: Cotton (dryland) | E15: TX-C1 | F15: 2023 | G15: 96 | H15: =FALSE() -> FALSE | I15: 45064 | J15: 45244 | K15: 45246 | L15: 440 | M15: 276 | N15: lb lint/ac | O15: 26496 | P15: 0.8 | Q15: 0.728 | R15: 26496 | S15: 0 | T15: 23992.13 | U15: Actual
A16: BIZ-SAM | B16: CS-SAM-COT24 | C16: ENT-SAM-COT | D16: Cotton (dryland) | E16: TX-C1 | F16: 2024 | G16: 96 | H16: =FALSE() -> FALSE | I16: 45430 | J16: 45610 | K16: 45612 | L16: 440 | M16: 468 | N16: lb lint/ac | O16: 44928 | P16: 0.74 | Q16: 0.645 | R16: 44928 | S16: 0 | T16: 35198.84 | U16: Actual
A17: BIZ-SAM | B17: CS-SAM-COT25 | C17: ENT-SAM-COT | D17: Cotton (dryland) | E17: TX-C1 | F17: 2025 | G17: 96 | H17: =FALSE() -> FALSE | I17: 45795 | J17: 45975 | K17: 45977 | L17: 440 | M17: 521 | N17: lb lint/ac | O17: 50016 | P17: 0.66 | Q17: 0.615 | R17: 50016 | S17: 0 | T17: 38217.23 | U17: Actual
A18: BIZ-SAM | B18: CS-SAM-COT26 | C18: ENT-SAM-COT | D18: Cotton (dryland) | E18: TX-C1 | F18: 2026 | G18: 96 | H18: =FALSE() -> FALSE | I18: 46160 | J18: 46340 | K18: 46342 | L18: 440 | M18: 455 | N18: lb lint/ac | O18: 43680 | P18: 0.66 | Q18: 0.82 | R18: 43680 | S18: 0 | T18: 42950.54 | U18: Forecast

Sheet Production_Log
A1: business_id | B1: enterprise_id | C1: date | D1: record_type | E1: item | F1: quantity | G1: unit | H1: data_type | I1: record_id
A2: BIZ-SAM | B2: ENT-SAM-CUS | C2: 45101 | D2: Combine separator hours | E2: AST-SAM-004 | F2: 13 | G2: hrs | H2: Actual | I2: PRD-SAM-00001
A3: BIZ-SAM | B3: ENT-SAM-CUS | C3: 45102 | D3: Combine separator hours | E3: AST-SAM-004 | F3: 12.9 | G3: hrs | H3: Actual | I3: PRD-SAM-00002
A4: BIZ-SAM | B4: ENT-SAM-WHT | C4: 45103 | D4: Combine separator hours | E4: AST-SAM-004 | F4: 8 | G4: hrs | H4: Actual | I4: PRD-SAM-00003
A5: BIZ-SAM | B5: ENT-SAM-CUS | C5: 45103 | D5: Combine separator hours | E5: AST-SAM-004 | F5: 17.1 | G5: hrs | H5: Actual | I5: PRD-SAM-00004
A6: BIZ-SAM | B6: ENT-SAM-CUS | C6: 45104 | D6: Combine separator hours | E6: AST-SAM-004 | F6: 16.9 | G6: hrs | H6: Actual | I6: PRD-SAM-00005
A7: BIZ-SAM | B7: ENT-SAM-CUS | C7: 45105 | D7: Combine separator hours | E7: AST-SAM-004 | F7: 35.5 | G7: hrs | H7: Actual | I7: PRD-SAM-00006
A8: BIZ-SAM | B8: ENT-SAM-CUS | C8: 45105 | D8: Combine separator hours | E8: AST-SAM-004 | F8: 9.2 | G8: hrs | H8: Actual | I8: PRD-SAM-00007
A9: BIZ-SAM | B9: ENT-SAM-CUS | C9: 45108 | D9: Combine separator hours | E9: AST-SAM-004 | F9: 20.8 | G9: hrs | H9: Actual | I9: PRD-SAM-00008
A10: BIZ-SAM | B10: ENT-SAM-CUS | C10: 45109 | D10: Combine separator hours | E10: AST-SAM-004 | F10: 12.4 | G10: hrs | H10: Actual | I10: PRD-SAM-00009
A11: BIZ-SAM | B11: ENT-SAM-CORN | C11: 45183 | D11: Combine separator hours | E11: AST-SAM-004 | F11: 8 | G11: hrs | H11: Actual | I11: PRD-SAM-00010
A12: BIZ-SAM | B12: ENT-SAM-CUS | C12: 45205 | D12: Combine separator hours | E12: AST-SAM-004 | F12: 19.5 | G12: hrs | H12: Actual | I12: PRD-SAM-00011
A13: BIZ-SAM | B13: ENT-SAM-CUS | C13: 45206 | D13: Combine separator hours | E13: AST-SAM-004 | F13: 8.8 | G13: hrs | H13: Actual | I13: PRD-SAM-00012
... A92: BIZ-SAM | B92: ENT-SAM-CORN | C92: 46287 | D92: Combine separator hours | E92: AST-SAM-004 | F92: 8 | G92: hrs | H92: Actual | I92: PRD-SAM-00091

Sheet Inventory
A1: business_id | B1: as_of_date | C1: item_id | D1: item | E1: category | F1: enterprise_id | G1: quantity | H1: unit | I1: cost_basis_per_unit | J1: market_value_per_unit | K1: cost_basis_total | L1: market_value_total | M1: bs_valuation | N1: acquired_or_produced | O1: expected_use_or_sale | P1: location
A2: BIZ-SAM | B2: 44926 | C2: INV-CS-SAM-S22 | D2: Soybeans in on-farm bins (CS-SAM-S22) | E2: Crops - grain | F2: ENT-SAM-SOY | G2: 3800 | H2: bu | I2: 12.816 | J2: 14.24 | K2: 48700.8 | L2: 54112 | M2: market | N2: CS-SAM-S22 | O2: Sell per marketing plan | P2: On-farm bins (25,000 bu)
A3: BIZ-SAM | B3: 45107 | C3: INV-CS-SAM-W23-D1 | D3: Wheat in on-farm bins (CS-SAM-W23-D1) | E3: Crops - grain | F3: ENT-SAM-WHT | G3: 992 | H3: bu | I3: 7.155 | J3: 7.95 | K3: 7097.76 | L3: 7886.4 | M3: market | N3: CS-SAM-W23-D1 | O3: Sell per marketing plan | P3: On-farm bins (25,000 bu)
A4: BIZ-SAM | B4: 45138 | C4: INV-CS-SAM-W23-D1 | D4: Wheat in on-farm bins (CS-SAM-W23-D1) | E4: Crops - grain | F4: ENT-SAM-WHT | G4: 992 | H4: bu | I4: 6.822 | J4: 7.58 | K4: 6767.42 | L4: 7519.36 | M4: market | N4: CS-SAM-W23-D1 | O4: Sell per marketing plan | P4: On-farm bins (25,000 bu)
A5: BIZ-SAM | B5: 45169 | C5: INV-CS-SAM-W23-D1 | D5: Wheat in on-farm bins (CS-SAM-W23-D1) | E5: Crops - grain | F5: ENT-SAM-WHT | G5: 992 | H5: bu | I5: 6.48 | J5: 7.2 | K5: 6428.16 | L5: 7142.4 | M5: market | N5: CS-SAM-W23-D1 | O5: Sell per marketing plan | P5: On-farm bins (25,000 bu)
A6: BIZ-SAM | B6: 45199 | C6: INV-CS-SAM-W23-D1 | D6: Wheat in on-farm bins (CS-SAM-W23-D1) | E6: Crops - grain | F6: ENT-SAM-WHT | G6: 992 | H6: bu | I6: 6.138 | J6: 6.82 | K6: 6088.9 | L6: 6765.44 | M6: market | N6: CS-SAM-W23-D1 | O6: Sell per marketing plan | P6: On-farm bins (25,000 bu)
A7: BIZ-SAM | B7: 45230 | C7: INV-CS-SAM-C23-P1 | D7: Corn in on-farm bins (CS-SAM-C23-P1) | E7: Crops - grain | F7: ENT-SAM-CORN | G7: 15525 | H7: bu | I7: 4.14 | J7: 4.6 | K7: 64273.5 | L7: 71415 | M7: market | N7: CS-SAM-C23-P1 | O7: Sell per marketing plan | P7: On-farm bins (25,000 bu)
A8: BIZ-SAM | B8: 45260 | C8: INV-CS-SAM-C23-P1 | D8: Corn in on-farm bins (CS-SAM-C23-P1) | E8: Crops - grain | F8: ENT-SAM-CORN | G8: 15525 | H8: bu | I8: 4.095 | J8: 4.55 | K8: 63574.87 | L8: 70638.75 | M8: market | N8: CS-SAM-C23-P1 | O8: Sell per marketing plan | P8: On-farm bins (25,000 bu)
A9: BIZ-SAM | B9: 45291 | C9: INV-CS-SAM-C23-P1 | D9: Corn in on-farm bins (CS-SAM-C23-P1) | E9: Crops - grain | F9: ENT-SAM-CORN | G9: 15525 | H9: bu | I9: 4.005 | J9: 4.45 | K9: 62177.62 | L9: 69086.25 | M9: market | N9: CS-SAM-C23-P1 | O9: Sell per marketing plan | P9: On-farm bins (25,000 bu)
A10: BIZ-SAM | B10: 45322 | C10: INV-CS-SAM-C23-P1 | D10: Corn in on-farm bins (CS-SAM-C23-P1) | E10: Crops - grain | F10: ENT-SAM-CORN | G10: 15525 | H10: bu | I10: 3.915 | J10: 4.35 | K10: 60780.37 | L10: 67533.75 | M10: market | N10: CS-SAM-C23-P1 | O10: Sell per marketing plan | P10: On-farm bins (25,000 bu)
A11: BIZ-SAM | B11: 45351 | C11: INV-CS-SAM-C23-P1 | D11: Corn in on-farm bins (CS-SAM-C23-P1) | E11: Crops - grain | F11: ENT-SAM-CORN | G11: 15525 | H11: bu | I11: 3.834 | J11: 4.26 | K11: 59522.85 | L11: 66136.5 | M11: market | N11: CS-SAM-C23-P1 | O11: Sell per marketing plan | P11: On-farm bins (25,000 bu)
A12: BIZ-SAM | B12: 45382 | C12: INV-CS-SAM-C23-P1 | D12: Corn in on-farm bins (CS-SAM-C23-P1) | E12: Crops - grain | F12: ENT-SAM-CORN | G12: 6469 | H12: bu | I12: 3.843 | J12: 4.27 | K12: 24860.37 | L12: 27622.63 | M12: market | N12: CS-SAM-C23-P1 | O12: Sell per marketing plan | P12: On-farm bins (25,000 bu)
A13: BIZ-SAM | B13: 45412 | C13: INV-CS-SAM-C23-P1 | D13: Corn in on-farm bins (CS-SAM-C23-P1) | E13: Crops - grain | F13: ENT-SAM-CORN | G13: 6469 | H13: bu | I13: 3.87 | J13: 4.3 | K13: 25035.03 | L13: 27816.7 | M13: market | N13: CS-SAM-C23-P1 | O13: Sell per marketing plan | P13: On-farm bins (25,000 bu)
... A51: BIZ-SAM | B51: 46295 | C51: INV-CS-SAM-W26-D2 | D51: Wheat in on-farm bins (CS-SAM-W26-D2) | E51: Crops - grain | F51: ENT-SAM-WHT | G51: 864 | H51: bu | I51: 4.86 | J51: 5.4 | K51: 4199.04 | L51: 4665.6 | M51: market | N51: CS-SAM-W26-D2 | O51: Sell per marketing plan | P51: On-farm bins (25,000 bu)
A52: BIZ-SAM | B52: 44926 | C52: GRW-CS-SAM-W23-D1 | D52: Growing crop at cost - Wheat (CS-SAM-W23-D1) | E52: Growing crops | F52: ENT-SAM-WHT | G52: 1 | H52: crop | I52: 4819.2 | J52: 4819.2 | K52: 4819.2 | L52: 4819.2 | M52: cost | N52: 44840 | O52: Harvest Jun 2023
A53: BIZ-SAM | B53: 44957 | C53: GRW-CS-SAM-W23-D1 | D53: Growing crop at cost - Wheat (CS-SAM-W23-D1) | E53: Growing crops | F53: ENT-SAM-WHT | G53: 1 | H53: crop | I53: 4819.2 | J53: 4819.2 | K53: 4819.2 | L53: 4819.2 | M53: cost | N53: 44840 | O53: Harvest Jun 2023
A54: BIZ-SAM | B54: 44985 | C54: GRW-CS-SAM-W23-D1 | D54: Growing crop at cost - Wheat (CS-SAM-W23-D1) | E54: Growing crops | F54: ENT-SAM-WHT | G54: 1 | H54: crop | I54: 4819.2 | J54: 4819.2 | K54: 4819.2 | L54: 4819.2 | M54: cost | N54: 44840 | O54: Harvest Jun 2023
A55: BIZ-SAM | B55: 45016 | C55: GRW-CS-SAM-W23-D1 | D55: Growing crop at cost - Wheat (CS-SAM-W23-D1) | E55: Growing crops | F55: ENT-SAM-WHT | G55: 1 | H55: crop | I55: 11475.2 | J55: 11475.2 | K55: 11475.2 | L55: 11475.2 | M55: cost | N55: 44840 | O55: Harvest Jun 2023
A56: BIZ-SAM | B56: 45046 | C56: GRW-CS-SAM-W23-D1 | D56: Growing crop at cost - Wheat (CS-SAM-W23-D1) | E56: Growing crops | F56: ENT-SAM-WHT | G56: 1 | H56: crop | I56: 11475.2 | J56: 11475.2 | K56: 11475.2 | L56: 11475.2 | M56: cost | N56: 44840 | O56: Harvest Jun 2023
A57: BIZ-SAM | B57: 45077 | C57: GRW-CS-SAM-W23-D1 | D57: Growing crop at cost - Wheat (CS-SAM-W23-D1) | E57: Growing crops | F57: ENT-SAM-WHT | G57: 1 | H57: crop | I57: 11475.2 | J57: 11475.2 | K57: 11475.2 | L57: 11475.2 | M57: cost | N57: 44840 | O57: Harvest Jun 2023
A58: BIZ-SAM | B58: 45046 | C58: GRW-CS-SAM-C23-D2 | D58: Growing crop at cost - Corn (CS-SAM-C23-D2) | E58: Growing crops | F58: ENT-SAM-CORN | G58: 1 | H58: crop | I58: 19092.32 | J58: 19092.32 | K58: 19092.32 | L58: 19092.32 | M58: cost | N58: 45040 | O58: Harvest Sep 2023
A59: BIZ-SAM | B59: 45077 | C59: GRW-CS-SAM-C23-D2 | D59: Growing crop at cost - Corn (CS-SAM-C23-D2) | E59: Growing crops | F59: ENT-SAM-CORN | G59: 1 | H59: crop | I59: 19092.32 | J59: 19092.32 | K59: 19092.32 | L59: 19092.32 | M59: cost | N59: 45040 | O59: Harvest Sep 2023
A60: BIZ-SAM | B60: 45107 | C60: GRW-CS-SAM-C23-D2 | D60: Growing crop at cost - Corn (CS-SAM-C23-D2) | E60: Growing crops | F60: ENT-SAM-CORN | G60: 1 | H60: crop | I60: 20892.32 | J60: 20892.32 | K60: 20892.32 | L60: 20892.32 | M60: cost | N60: 45040 | O60: Harvest Sep 2023
A61: BIZ-SAM | B61: 45138 | C61: GRW-CS-SAM-C23-D2 | D61: Growing crop at cost - Corn (CS-SAM-C23-D2) | E61: Growing crops | F61: ENT-SAM-CORN | G61: 1 | H61: crop | I61: 20892.32 | J61: 20892.32 | K61: 20892.32 | L61: 20892.32 | M61: cost | N61: 45040 | O61: Harvest Sep 2023
A62: BIZ-SAM | B62: 45169 | C62: GRW-CS-SAM-C23-D2 | D62: Growing crop at cost - Corn (CS-SAM-C23-D2) | E62: Growing crops | F62: ENT-SAM-CORN | G62: 1 | H62: crop | I62: 20892.32 | J62: 20892.32 | K62: 20892.32 | L62: 20892.32 | M62: cost | N62: 45040 | O62: Harvest Sep 2023
A63: BIZ-SAM | B63: 45046 | C63: GRW-CS-SAM-C23-P1 | D63: Growing crop at cost - Corn (CS-SAM-C23-P1) | E63: Growing crops | F63: ENT-SAM-CORN | G63: 1 | H63: crop | I63: 49494.25 | J63: 49494.25 | K63: 49494.25 | L63: 49494.25 | M63: cost | N63: 45035 | O63: Harvest Oct 2023
... A162: BIZ-SAM | B162: 46295 | C162: GRW-CS-SAM-COT26 | D162: Growing crop at cost - Cotton (dryland) (CS-SAM-COT26) | E162: Growing crops | F162: ENT-SAM-COT | G162: 1 | H162: crop | I162: 30800.4 | J162: 30800.4 | K162: 30800.4 | L162: 30800.4 | M162: cost | N162: 46042 | O162: Harvest Nov 2026

Sheet Assets
A1: asset_id | B1: business_id | C1: description | D1: category | E1: enterprise_allocation | F1: purchase_date | G1: original_cost | H1: financing | I1: loan_id | J1: outstanding_loan_balance | K1: useful_life_years | L1: salvage_value | M1: depreciation_method | N1: annual_depreciation | O1: accumulated_depreciation | P1: net_book_value | Q1: estimated_current_value | R1: repairs_ttm | S1: repairs_2023 | T1: repairs_2024 | U1: repairs_2025 | V1: repairs_2026_ytd | W1: usage | X1: maintenance_notes | Y1: disposal_date | Z1: disposal_proceeds | AA1: notes | AB1: status
A2: AST-SAM-001 | B2: BIZ-SAM | C2: KS home quarter - 160 ac incl. 125-ac pivot (2008) | D2: Land | E2: ENT-SAM-OVH:100% | F2: 39508 | G2: 264000 | H2: Cash / owned | J2: 0 | L2: 0 | M2: Not depreciated | N2: 0 | O2: 0 | P2: 264000 | Q2: 595070.27 | R2: 0 | S2: 0 | T2: 0 | U2: 0 | V2: 0 | AB2: In service
A3: AST-SAM-002 | B3: BIZ-SAM | C3: KS dryland - 140 ac (2019) | D3: Land | E3: ENT-SAM-OVH:100% | F3: 43539 | G3: 546000 | H3: Financed - LN-SAM-001 | I3: LN-SAM-001 | J3: 311438.01 | L3: 0 | M3: Not depreciated | N3: 0 | O3: 0 | P3: 546000 | Q3: 1230713.5 | R3: 0 | S3: 0 | T3: 0 | U3: 0 | V3: 0 | AB3: In service
A4: AST-SAM-003 | B4: BIZ-SAM | C4: TX Carson Co. dryland cotton - 100 ac (inherited 2017) | D4: Land | E4: ENT-SAM-COT:100% | F4: 42979 | G4: 115000 | H4: Cash / owned | J4: 0 | L4: 0 | M4: Not depreciated | N4: 0 | O4: 0 | P4: 115000 | Q4: 259216.22 | R4: 0 | S4: 0 | T4: 0 | U4: 0 | V4: 0 | AB4: In service
A5: AST-SAM-004 | B5: BIZ-SAM | C5: 2019 John Deere S770 combine (bought used, 1,950 sep hrs) | D5: Machinery & equipment | E5: ENT-SAM-CUS:85%; ENT-SAM-CORN:7%; ENT-SAM-SOY:5%; ENT-SAM-WHT:3% | F5: 44575 | G5: 298000 | H5: Financed - LN-SAM-002 | I5: LN-SAM-002 | J5: 123089.46 | K5: 12 | L5: 100000 | M5: Straight-line (monthly) | N5: 16500 | O5: 78375 | P5: 219625 | Q5: 191100 | R5: 25330.4 | S5: 20101 | T5: 25380.56 | U5: 38495.04 | V5: 25330.4 | W5: ~1,000 separator hrs/yr (≈88% custom) | X5: Rotor gearbox/feeder house rebuild Aug 2025 $18,420 | AB5: In service
A6: AST-SAM-005 | B6: BIZ-SAM | C6: 12-row corn head | D6: Machinery & equipment | E6: ENT-SAM-CUS:70%; ENT-SAM-CORN:30% | F6: 44575 | G6: 64000 | H6: Financed - LN-SAM-002 | I6: LN-SAM-002 | J6: 123089.46 | K6: 12 | L6: 15000 | M6: Straight-line (monthly) | N6: 4083.33 | O6: 19395.83 | P6: 44604.17 | Q6: 43200 | R6: 0 | S6: 0 | T6: 0 | U6: 0 | V6: 0 | AB6: In service
A7: AST-SAM-006 | B7: BIZ-SAM | C7: 35' draper head (used) | D7: Machinery & equipment | E7: ENT-SAM-CUS:75%; ENT-SAM-WHT:15%; ENT-SAM-SOY:10% | F7: 44349 | G7: 52000 | H7: Cash / owned | J7: 0 | K7: 12 | L7: 12000 | M7: Straight-line (monthly) | N7: 3333.33 | O7: 17777.78 | P7: 34222.22 | Q7: 33300 | R7: 0 | S7: 0 | T7: 0 | U7: 0 | V7: 0 | AB7: In service
A8: AST-SAM-007 | B8: BIZ-SAM | C8: John Deere 8R 280 tractor (used, 2019) | D8: Machinery & equipment | E8: ENT-SAM-CORN:40%; ENT-SAM-SOY:30%; ENT-SAM-WHT:20%; ENT-SAM-CUS:10% | F8: 45723 | G8: 268500 | H8: Financed - LN-SAM-003 | I8: LN-SAM-003 | J8: 142216.85 | K8: 12 | L8: 100000 | M8: Straight-line (monthly) | N8: 14041.67 | O8: 22232.64 | P8: 246267.36 | Q8: 239700 | R8: 0 | S8: 0 | T8: 0 | U8: 0 | V8: 0 | W8: ~420 hrs/yr | AB8: In service
A9: AST-SAM-008 | B9: BIZ-SAM | C9: John Deere 7830 tractor (traded Mar 2023) | D9: Machinery & equipment | E9: ENT-SAM-CORN:45%; ENT-SAM-SOY:30%; ENT-SAM-WHT:25% | F9: 41680 | G9: 168000 | H9: Cash / owned | J9: 0 | K9: 12 | L9: 40000 | M9: Straight-line (monthly) | N9: 10666.67 | P9: 0 | Q9: 0 | R9: 0 | S9: 0 | T9: 0 | U9: 0 | V9: 0 | Y9: 45723 | Z9: 58000 | AB9: Disposed
A10: AST-SAM-009 | B10: BIZ-SAM | C10: Kinze 3600 16-row planter (used) | D10: Machinery & equipment | E10: ENT-SAM-CORN:55%; ENT-SAM-SOY:45% | F10: 43516 | G10: 62000 | H10: Cash / owned | J10: 0 | K10: 12 | L10: 12000 | M10: Straight-line (monthly) | N10: 4166.67 | O10: 31944.44 | P10: 30055.56 | Q10: 32900 | R10: 0 | S10: 0 | T10: 0 | U10: 0 | V10: 0 | AB10: In service
A11: AST-SAM-010 | B11: BIZ-SAM | C11: 30' no-till grain drill | D11: Machinery & equipment | E11: ENT-SAM-WHT:100% | F11: 42231 | G11: 21000 | H11: Cash / owned | J11: 0 | K11: 15 | L11: 4000 | M11: Straight-line (monthly) | N11: 1133.33 | O11: 12655.56 | P11: 8344.44 | Q11: 9400 | R11: 0 | S11: 0 | T11: 0 | U11: 0 | V11: 0 | AB11: In service
A12: AST-SAM-011 | B12: BIZ-SAM | C12: 90' pull-type sprayer | D12: Machinery & equipment | E12: ENT-SAM-CORN:40%; ENT-SAM-SOY:35%; ENT-SAM-WHT:25% | F12: 43891 | G12: 34500 | H12: Cash / owned | J12: 0 | K12: 12 | L12: 6000 | M12: Straight-line (monthly) | N12: 2375 | O12: 15635.42 | P12: 18864.58 | Q12: 18500 | R12: 0 | S12: 0 | T12: 0 | U12: 0 | V12: 0 | AB12: In service
A13: AST-SAM-012 | B13: BIZ-SAM | C13: 1000-bu grain cart | D13: Machinery & equipment | E13: ENT-SAM-CUS:60%; ENT-SAM-CORN:20%; ENT-SAM-SOY:12%; ENT-SAM-WHT:8% | F13: 44378 | G13: 47800 | H13: Cash / owned | J13: 0 | K13: 15 | L13: 12000 | M13: Straight-line (monthly) | N13: 2386.67 | O13: 12530 | P13: 35270 | Q13: 34500 | R13: 0 | S13: 0 | T13: 0 | U13: 0 | V13: 0 | AB13: In service
A14: AST-SAM-013 | B14: BIZ-SAM | C14: 1998 IH tandem grain truck | D14: Vehicles | E14: ENT-SAM-CUS:60%; ENT-SAM-CORN:20%; ENT-SAM-SOY:10%; ENT-SAM-WHT:10% | F14: 41030 | G14: 28000 | H14: Cash / owned | J14: 0 | K14: 10 | L14: 5000 | M14: Straight-line (monthly) | N14: 2300 | P14: 0 | Q14: 0 | R14: 0 | S14: 0 | T14: 0 | U14: 0 | V14: 0 | Y14: 45547 | Z14: 14500 | AB14: Disposed
A15: AST-SAM-014 | B15: BIZ-SAM | C15: 2016 Peterbilt 579 semi + 2018 Wilson hopper trailer | D15: Vehicles | E15: ENT-SAM-CUS:75%; ENT-SAM-CORN:15%; ENT-SAM-SOY:5%; ENT-SAM-WHT:5% | F15: 45520 | G15: 98500 | H15: Financed - LN-SAM-004 | I15: LN-SAM-004 | J15: 37098.41 | K15: 10 | L15: 35000 | M15: Straight-line (monthly) | N15: 6350 | O15: 13758.33 | P15: 84741.67 | Q15: 82500 | R15: 2673.46 | S15: 0 | T15: 1697.32 | U15: 2433.91 | V15: 1574.36 | W15: ~22,000 mi/yr | AB15: In service
A16: AST-SAM-015 | B16: BIZ-SAM | C16: Center pivot (7-tower) + irrigation well & pump | D16: Buildings & improvements | E16: ENT-SAM-CORN:60%; ENT-SAM-SOY:40% | F16: 42095 | G16: 142000 | H16: Cash / owned | J16: 0 | K16: 25 | L16: 10000 | M16: Straight-line (monthly) | N16: 5280 | O16: 60720 | P16: 81280 | Q16: 88800 | R16: 0 | S16: 0 | T16: 0 | U16: 0 | V16: 0 | AB16: In service
A17: AST-SAM-016 | B17: BIZ-SAM | C17: Grain bins 2x12,500 bu + dryer + leg | D17: Buildings & improvements | E17: ENT-SAM-CORN:60%; ENT-SAM-SOY:25%; ENT-SAM-WHT:15% | F17: 41122 | G17: 165000 | H17: Cash / owned | J17: 0 | K17: 25 | L17: 15000 | M17: Straight-line (monthly) | N17: 6000 | O17: 85000 | P17: 80000 | Q17: 92600 | R17: 0 | S17: 0 | T17: 0 | U17: 0 | V17: 0 | AB17: In service
A18: AST-SAM-017 | B18: BIZ-SAM | C18: Machine shop 60'x80' | D18: Buildings & improvements | E18: ENT-SAM-OVH:100% | F18: 40330 | G18: 118000 | H18: Cash / owned | J18: 0 | K18: 30 | L18: 0 | M18: Straight-line (monthly) | N18: 3933.33 | O18: 64244.44 | P18: 53755.56 | Q18: 71800 | R18: 0 | S18: 0 | T18: 0 | U18: 0 | V18: 0 | AB18: In service
A19: AST-SAM-018 | B19: BIZ-SAM | C19: 2021 Ford F-350 pickup | D19: Vehicles | E19: ENT-SAM-OVH:100% | F19: 44357 | G19: 61500 | H19: Financed - LN-SAM-005 | I19: LN-SAM-005 | J19: 0 | K19: 8 | L19: 20000 | M19: Straight-line (monthly) | N19: 5187.5 | O19: 27666.67 | P19: 33833.33 | Q19: 35200 | R19: 0 | S19: 0 | T19: 0 | U19: 0 | V19: 0 | AB19: In service
A20: AST-SAM-019 | B20: BIZ-SAM | C20: Field cultivator, header trailer & misc implements | D20: Machinery & equipment | E20: ENT-SAM-CORN:40%; ENT-SAM-SOY:30%; ENT-SAM-WHT:20%; ENT-SAM-CUS:10% | F20: 42430 | G20: 38000 | H20: Cash / owned | J20: 0 | K20: 15 | L20: 5000 | M20: Straight-line (monthly) | N20: 2200 | O20: 23283.33 | P20: 14716.67 | Q20: 17600 | R20: 0 | S20: 0 | T20: 0 | U20: 0 | V20: 0 | AB20: In service

Sheet Depreciation
A1: business_id | B1: asset_id | C1: enterprise_id | D1: year | E1: depreciation
A2: BIZ-SAM | B2: AST-SAM-004 | C2: ENT-SAM-CORN | D2: 2023 | E2: 1155
A3: BIZ-SAM | B3: AST-SAM-004 | C3: ENT-SAM-CORN | D3: 2024 | E3: 1155
A4: BIZ-SAM | B4: AST-SAM-004 | C4: ENT-SAM-CORN | D4: 2025 | E4: 1155
A5: BIZ-SAM | B5: AST-SAM-004 | C5: ENT-SAM-CORN | D5: 2026 | E5: 866.25
A6: BIZ-SAM | B6: AST-SAM-004 | C6: ENT-SAM-CUS | D6: 2023 | E6: 14025
A7: BIZ-SAM | B7: AST-SAM-004 | C7: ENT-SAM-CUS | D7: 2024 | E7: 14025
A8: BIZ-SAM | B8: AST-SAM-004 | C8: ENT-SAM-CUS | D8: 2025 | E8: 14025
A9: BIZ-SAM | B9: AST-SAM-004 | C9: ENT-SAM-CUS | D9: 2026 | E9: 10518.75
A10: BIZ-SAM | B10: AST-SAM-004 | C10: ENT-SAM-SOY | D10: 2023 | E10: 825
A11: BIZ-SAM | B11: AST-SAM-004 | C11: ENT-SAM-SOY | D11: 2024 | E11: 825
A12: BIZ-SAM | B12: AST-SAM-004 | C12: ENT-SAM-SOY | D12: 2025 | E12: 825
A13: BIZ-SAM | B13: AST-SAM-004 | C13: ENT-SAM-SOY | D13: 2026 | E13: 618.75
... A150: BIZ-SAM | B150: AST-SAM-019 | C150: ENT-SAM-WHT | D150: 2026 | E150: 330.03

Sheet Loans
A1: loan_id | B1: business_id | C1: lender | D1: lender_vendor_id | E1: debt_type | F1: purpose | G1: collateral | H1: origination_date | I1: original_principal | J1: interest_rate | K1: rate_type | L1: payment_frequency | M1: payment_amount | N1: number_of_payments | O1: first_payment_date | P1: maturity_date | Q1: principal_balance_at_cutoff | R1: next_payment_date | S1: annual_debt_service | T1: interest_paid_2023 | U1: interest_paid_2024 | V1: interest_paid_2025 | W1: interest_paid_2026_ytd | X1: principal_due_next_12m
A2: LN-SAM-001 | B2: BIZ-SAM | C2: Sunflower Plains Farm Credit, ACA | D2: VEN-SAM-007 | E2: Land loan | F2: KS 140-ac purchase | G2: 140 ac KS dryland (1st lien) | H2: 43539 | I2: 420000 | J2: 0.0435 | K2: Fixed | L2: Annual | M2: 31869.68 | N2: 20 | O2: 43800 | P2: 50740 | Q2: 311438.01 | R2: 46357 | S2: 31869.68 | T2: 15744.72 | U2: 15043.29 | V2: 14311.34 | W2: 0 | X2: 18322.13
A3: LN-SAM-002 | B3: BIZ-SAM | C3: Green Line Equipment Finance | D3: VEN-SAM-008 | E3: Equipment loan | F3: Combine & corn head | G3: S770 combine + corn head | H3: 44575 | I3: 262000 | J3: 0.049 | K3: Fixed | L3: Annual | M3: 45114.84 | N3: 7 | O3: 44940 | P3: 47132 | Q3: 123089.46 | R3: 46401 | S3: 45114.84 | T3: 12838 | U3: 11256.43 | V3: 9597.37 | W3: 7857.02 | X3: 39083.46
A4: LN-SAM-003 | B4: BIZ-SAM | C4: Green Line Equipment Finance | D4: VEN-SAM-008 | E4: Equipment loan | F4: 8R tractor | G4: JD 8R 280 tractor | H4: 45723 | I4: 165000 | J4: 0.0749 | K4: Fixed | L4: Annual | M4: 35141.65 | N4: 6 | O4: 46088 | P4: 47914 | Q4: 142216.85 | R4: 46453 | S4: 35141.65 | T4: 0 | U4: 0 | V4: 0 | W4: 12358.5 | X4: 24489.61
A5: LN-SAM-004 | B5: BIZ-SAM | C5: First Plains Bank | D5: VEN-SAM-009 | E5: Equipment loan | F5: Semi & trailer | G5: Peterbilt semi + hopper trailer | H5: 45520 | I5: 72000 | J5: 0.0725 | K5: Fixed | L5: Monthly | M5: 1732.49 | N5: 48 | O5: 45551 | P5: 46981 | Q5: 37098.41 | R5: 46311 | S5: 20789.88 | T5: 0 | U5: 1692.77 | V5: 4299.5 | W5: 2418.39 | X5: 18713.97
A6: LN-SAM-005 | B6: BIZ-SAM | C6: Prairie Auto Credit | D6: VEN-SAM-010 | E6: Vehicle loan | F6: Pickup | G6: 2021 F-350 | H6: 44357 | I6: 46000 | J6: 0.039 | K6: Fixed | L6: Monthly | M6: 845.09 | N6: 60 | O6: 44387 | P6: 46183 | Q6: 0 | S6: 0 | T6: 1132.05 | U6: 774.35 | V6: 402.45 | W6: 57.19 | X6: 0
A7: LOC-SAM-001 | B7: BIZ-SAM | C7: First Plains Bank | D7: VEN-SAM-009 | E7: Operating line of credit | F7: Seasonal operating needs | G7: Crops/livestock, receivables, equipment (blanket lien) | I7: 250000 | J7: 0.0775 | K7: Variable (prime + spread) | L7: Interest monthly; principal revolving | P7: 46447 | Q7: 221000 | R7: 46326 | X7: 221000

Sheet Loan_Schedule
A1: loan_id | B1: business_id | C1: payment_number | D1: due_date | E1: payment | F1: interest | G1: principal | H1: ending_balance | I1: status
A2: LN-SAM-001 | B2: BIZ-SAM | C2: 1 | D2: 43800 | E2: 31869.68 | F2: 18270 | G2: 13599.68 | H2: 406400.32 | I2: Paid
A3: LN-SAM-001 | B3: BIZ-SAM | C3: 2 | D3: 44166 | E3: 31869.68 | F3: 17678.41 | G3: 14191.27 | H3: 392209.05 | I3: Paid
A4: LN-SAM-001 | B4: BIZ-SAM | C4: 3 | D4: 44531 | E4: 31869.68 | F4: 17061.09 | G4: 14808.59 | H4: 377400.46 | I4: Paid
A5: LN-SAM-001 | B5: BIZ-SAM | C5: 4 | D5: 44896 | E5: 31869.68 | F5: 16416.92 | G5: 15452.76 | H5: 361947.7 | I5: Paid
A6: LN-SAM-001 | B6: BIZ-SAM | C6: 5 | D6: 45261 | E6: 31869.68 | F6: 15744.72 | G6: 16124.96 | H6: 345822.74 | I6: Paid
A7: LN-SAM-001 | B7: BIZ-SAM | C7: 6 | D7: 45627 | E7: 31869.68 | F7: 15043.29 | G7: 16826.39 | H7: 328996.35 | I7: Paid
A8: LN-SAM-001 | B8: BIZ-SAM | C8: 7 | D8: 45992 | E8: 31869.68 | F8: 14311.34 | G8: 17558.34 | H8: 311438.01 | I8: Paid
A9: LN-SAM-001 | B9: BIZ-SAM | C9: 8 | D9: 46357 | E9: 31869.68 | F9: 13547.55 | G9: 18322.13 | H9: 293115.88 | I9: Scheduled
A10: LN-SAM-001 | B10: BIZ-SAM | C10: 9 | D10: 46722 | E10: 31869.68 | F10: 12750.54 | G10: 19119.14 | H10: 273996.74 | I10: Scheduled
A11: LN-SAM-001 | B11: BIZ-SAM | C11: 10 | D11: 47088 | E11: 31869.68 | F11: 11918.86 | G11: 19950.82 | H11: 254045.92 | I11: Scheduled
A12: LN-SAM-001 | B12: BIZ-SAM | C12: 11 | D12: 47453 | E12: 31869.68 | F12: 11051 | G12: 20818.68 | H12: 233227.24 | I12: Scheduled
A13: LN-SAM-001 | B13: BIZ-SAM | C13: 12 | D13: 47818 | E13: 31869.68 | F13: 10145.38 | G13: 21724.3 | H13: 211502.94 | I13: Scheduled
... A142: LN-SAM-005 | B142: BIZ-SAM | C142: 60 | D142: 46183 | E142: 844.77 | F142: 2.74 | G142: 842.03 | H142: 0 | I142: Paid

Sheet Operating_Line
A1: business_id | B1: month_end | C1: line_balance | D1: limit | E1: available | F1: rate | G1: interest | H1: avg_balance
A2: BIZ-SAM | B2: 44957 | C2: 59000 | D2: 250000 | E2: 191000 | F2: 0.085 | G2: 621.32 | H2: 86064.52
A3: BIZ-SAM | B3: 44985 | C3: 59000 | D3: 250000 | E3: 191000 | F3: 0.0875 | G3: 396.03 | H3: 59000
A4: BIZ-SAM | B4: 45016 | C4: 73000 | D4: 250000 | E4: 177000 | F4: 0.09 | G4: 509.67 | H4: 66677.42
A5: BIZ-SAM | B5: 45046 | C5: 86000 | D5: 250000 | E5: 164000 | F5: 0.09 | G5: 607.32 | H5: 82100
A6: BIZ-SAM | B6: 45077 | C6: 126000 | D6: 250000 | E6: 124000 | F6: 0.0925 | G6: 871.27 | H6: 110903.23
A7: BIZ-SAM | B7: 45107 | C7: 158000 | D7: 250000 | E7: 92000 | F7: 0.0925 | G7: 1120.14 | H7: 147333.33
A8: BIZ-SAM | B8: 45138 | C8: 176000 | D8: 250000 | E8: 74000 | F8: 0.095 | G8: 1410.68 | H8: 174838.71
A9: BIZ-SAM | B9: 45169 | C9: 170000 | D9: 250000 | E9: 80000 | F9: 0.095 | G9: 1529.37 | H9: 189548.39
A10: BIZ-SAM | B10: 45199 | C10: 170000 | D10: 250000 | E10: 80000 | F10: 0.095 | G10: 1327.4 | H10: 170000
A11: BIZ-SAM | B11: 45230 | C11: 113000 | D11: 250000 | E11: 137000 | F11: 0.095 | G11: 1371.64 | H11: 170000
A12: BIZ-SAM | B12: 45260 | C12: 113000 | D12: 250000 | E12: 137000 | F12: 0.095 | G12: 882.33 | H12: 113000
A13: BIZ-SAM | B13: 45291 | C13: 92000 | D13: 250000 | E13: 158000 | F13: 0.095 | G13: 1089.25 | H13: 135000
... A46: BIZ-SAM | B46: 46295 | C46: 221000 | D46: 250000 | E46: 29000 | F46: 0.0775 | G46: 1592.47 | H46: 250000

Sheet Labor_Hours
A1: business_id | B1: month | C1: enterprise_id | D1: worker_type | E1: worker | F1: hours | G1: hourly_cost | H1: wages_paid | I1: note
A2: BIZ-SAM | B2: 45047 | C2: ENT-SAM-CUS | D2: Hired seasonal | E2: Hand/truck driver | F2: 56.5 | G2: 19 | H2: 1074.12 | I2: 60% custom / 40% own farm
A3: BIZ-SAM | B3: 45047 | C3: ENT-SAM-CUS | D3: Hired seasonal | E3: Hand/truck driver | F3: 59.1 | G3: 19 | H3: 1123.81 | I3: 60% custom / 40% own farm
A4: BIZ-SAM | B4: 45078 | C4: ENT-SAM-CUS | D4: Hired seasonal | E4: Hand/truck driver | F4: 62.4 | G4: 19 | H4: 1186.09 | I4: 60% custom / 40% own farm
A5: BIZ-SAM | B5: 45078 | C5: ENT-SAM-CUS | D5: Hired seasonal | E5: Hand/truck driver | F5: 111.1 | G5: 19 | H5: 2111.1 | I5: 60% custom / 40% own farm
A6: BIZ-SAM | B6: 45108 | C6: ENT-SAM-CUS | D6: Hired seasonal | E6: Hand/truck driver | F6: 111.2 | G6: 19 | H6: 2112.08 | I6: 60% custom / 40% own farm
A7: BIZ-SAM | B7: 45108 | C7: ENT-SAM-CUS | D7: Hired seasonal | E7: Hand/truck driver | F7: 52.3 | G7: 19 | H7: 993.56 | I7: 60% custom / 40% own farm
A8: BIZ-SAM | B8: 45139 | C8: ENT-SAM-CUS | D8: Hired seasonal | E8: Hand/truck driver | F8: 61.6 | G8: 19 | H8: 1169.52 | I8: 60% custom / 40% own farm
A9: BIZ-SAM | B9: 45139 | C9: ENT-SAM-CUS | D9: Hired seasonal | E9: Hand/truck driver | F9: 62.4 | G9: 19 | H9: 1186.2 | I9: 60% custom / 40% own farm
A10: BIZ-SAM | B10: 45170 | C10: ENT-SAM-CUS | D10: Hired seasonal | E10: Hand/truck driver | F10: 62.9 | G10: 19 | H10: 1195.99 | I10: 60% custom / 40% own farm
A11: BIZ-SAM | B11: 45170 | C11: ENT-SAM-CUS | D11: Hired seasonal | E11: Hand/truck driver | F11: 119.1 | G11: 19 | H11: 2262.98 | I11: 60% custom / 40% own farm
A12: BIZ-SAM | B12: 45170 | C12: ENT-SAM-CUS | D12: Hired seasonal | E12: Hand/truck driver | F12: 110.4 | G12: 19 | H12: 2096.97 | I12: 60% custom / 40% own farm
A13: BIZ-SAM | B13: 45200 | C13: ENT-SAM-CUS | D13: Hired seasonal | E13: Hand/truck driver | F13: 108.9 | G13: 19 | H13: 2068.17 | I13: 60% custom / 40% own farm
... A53: BIZ-SAM | B53: 46266 | C53: ENT-SAM-CUS | D53: Hired seasonal | E53: Hand/truck driver | F53: 113.3 | G53: 22 | H53: 2492.9 | I53: 60% custom / 40% own farm
A54: BIZ-SAM | B54: 44927 | C54: ENT-SAM-CUS | D54: Owner/family (unpaid) | E54: Sam (combine operator) | F54: 20 | G54: 0 | H54: 0
A55: BIZ-SAM | B55: 44927 | C55: ENT-SAM-OVH | D55: Owner/family (unpaid) | E55: Sam & Megan (own farm, books, grain cart) | F55: 70 | G55: 0 | H55: 0
A56: BIZ-SAM | B56: 44958 | C56: ENT-SAM-CUS | D56: Owner/family (unpaid) | E56: Sam (combine operator) | F56: 20 | G56: 0 | H56: 0
A57: BIZ-SAM | B57: 44958 | C57: ENT-SAM-OVH | D57: Owner/family (unpaid) | E57: Sam & Megan (own farm, books, grain cart) | F57: 70 | G57: 0 | H57: 0
A58: BIZ-SAM | B58: 44986 | C58: ENT-SAM-CUS | D58: Owner/family (unpaid) | E58: Sam (combine operator) | F58: 20 | G58: 0 | H58: 0
A59: BIZ-SAM | B59: 44986 | C59: ENT-SAM-OVH | D59: Owner/family (unpaid) | E59: Sam & Megan (own farm, books, grain cart) | F59: 70 | G59: 0 | H59: 0
A60: BIZ-SAM | B60: 45017 | C60: ENT-SAM-CUS | D60: Owner/family (unpaid) | E60: Sam (combine operator) | F60: 20 | G60: 0 | H60: 0
A61: BIZ-SAM | B61: 45017 | C61: ENT-SAM-OVH | D61: Owner/family (unpaid) | E61: Sam & Megan (own farm, books, grain cart) | F61: 150 | G61: 0 | H61: 0
A62: BIZ-SAM | B62: 45047 | C62: ENT-SAM-CUS | D62: Owner/family (unpaid) | E62: Sam (combine operator) | F62: 20 | G62: 0 | H62: 0
A63: BIZ-SAM | B63: 45047 | C63: ENT-SAM-OVH | D63: Owner/family (unpaid) | E63: Sam & Megan (own farm, books, grain cart) | F63: 150 | G63: 0 | H63: 0
A64: BIZ-SAM | B64: 45078 | C64: ENT-SAM-CUS | D64: Owner/family (unpaid) | E64: Sam (combine operator) | F64: 200 | G64: 0 | H64: 0
A65: BIZ-SAM | B65: 45078 | C65: ENT-SAM-OVH | D65: Owner/family (unpaid) | E65: Sam & Megan (own farm, books, grain cart) | F65: 150 | G65: 0 | H65: 0
... A143: BIZ-SAM | B143: 46266 | C143: ENT-SAM-OVH | D143: Owner/family (unpaid) | E143: Sam & Megan (own farm, books, grain cart) | F143: 150 | G143: 0 | H143: 0

Sheet Customers
A1: customer_id | B1: business_id | C1: name | D1: customer_type | E1: payment_terms_days | F1: location | G1: notes
A2: CUS-SAM-001 | B2: BIZ-SAM | C2: Central Prairie Co-op - grain | D2: Grain elevator | E2: 0 | F2: McPherson, KS
A3: CUS-SAM-002 | B3: BIZ-SAM | C3: High Plains Cotton Marketing Pool | D3: Cotton marketing cooperative pool | E3: 0 | F3: Lubbock, TX
A4: CUS-SAM-003 | B4: BIZ-SAM | C4: Carson County Co-op Gin (cottonseed) | D4: Gin | E4: 0
A5: CUS-SAM-004 | B5: BIZ-SAM | C5: Heritage Mills Flour - wheat | D5: Flour mill (wheat) | E5: 0 | F5: Hutchinson, KS
A6: CUS-SAM-005 | B6: BIZ-SAM | C6: USDA FSA / RMA (programs & indemnities) | D6: Government / insurance | E6: 0
A7: CUS-SAM-101 | B7: BIZ-SAM | C7: Heartland Land & Cattle | D7: Custom harvesting client | E7: 30 | F7: McPherson/Harvey/Marion Co., KS
A8: CUS-SAM-102 | B8: BIZ-SAM | C8: Ostrander Farms | D8: Custom harvesting client | E8: 30 | F8: McPherson/Harvey/Marion Co., KS | G8: Slow payer
A9: CUS-SAM-103 | B9: BIZ-SAM | C9: Rudd Brothers Partnership | D9: Custom harvesting client | E9: 30 | F9: McPherson/Harvey/Marion Co., KS | G9: 2025 fall invoice disputed (acre count) - unpaid
A10: CUS-SAM-104 | B10: BIZ-SAM | C10: Gail Schrag | D10: Custom harvesting client | E10: 30 | F10: McPherson/Harvey/Marion Co., KS
A11: CUS-SAM-105 | B11: BIZ-SAM | C11: Lindquist Family Farms | D11: Custom harvesting client | E11: 30 | F11: McPherson/Harvey/Marion Co., KS
A12: CUS-SAM-106 | B12: BIZ-SAM | C12: Prairie Rose Dairy | D12: Custom harvesting client | E12: 30 | F12: McPherson/Harvey/Marion Co., KS
A13: CUS-SAM-107 | B13: BIZ-SAM | C13: Dale & Jo Unruh | D13: Custom harvesting client | E13: 30 | F13: McPherson/Harvey/Marion Co., KS
A14: CUS-SAM-108 | B14: BIZ-SAM | C14: Smoky Hill Farms LLC | D14: Custom harvesting client | E14: 30 | F14: McPherson/Harvey/Marion Co., KS

Sheet Vendors
A1: vendor_id | B1: business_id | C1: name | D1: category | E1: payment_terms_days | F1: location | G1: notes
A2: VEN-SAM-001 | B2: BIZ-SAM | C2: Central Prairie Co-op | D2: Fertilizer, chemicals, fuel, propane | E2: 30 | F2: McPherson, KS
A3: VEN-SAM-002 | B3: BIZ-SAM | C3: Golden Plains Seed Co. | D3: Seed (corn/soy) | E3: 0 | F3: Hesston, KS
A4: VEN-SAM-003 | B4: BIZ-SAM | C4: Panhandle Custom Farming | D4: TX custom field operations | E4: 30 | F4: Panhandle, TX
